Workbook
Name Slicer_Sector: #N/A

Sheet CPI Dashboard

Sheet Objective 
B2: Objective
B3: The objective of this case study is to analyze India’s inflation patterns using Consumer Price Index (CPI) data. The CPI tracks changes in the price of a fixed basket of goods and services over time and reflects
B4: inflation trends faced by Indian consumers.
B5: This project aims to:
B6: 1. Identify the contribution of major CPI categories toward overall inflation,
B7: 2. Examine year-over-year inflation trends,
B8: 3. Evaluate food price inflation,
B9: 4. Assess the impact of COVID-19, and
B10: 5. Analyze how global crude oil fluctuations influence India’s inflation.

Sheet All_India_Index_Upto_April23
A1: Sector | B1: Year | C1: Month | D1: Cereals and products | E1: Meat and fish | F1: Egg | G1: Milk and products | H1: Oils and fats | I1: Fruits | J1: Vegetables | K1: Pulses and products | L1: Sugar and Confectionery | M1: Spices | N1: Non-alcoholic beverages | O1: Prepared meals, snacks, sweets etc. | P1: Food and beverages | Q1: Pan, tobacco and intoxicants | R1: Clothing | S1: Footwear | T1: Clothing and footwear | U1: Housing | V1: Fuel and light | W1: Household goods and services | X1: Health | Y1: Transport and communication | Z1: Recreation and amusement | AA1: Education | AB1: Personal care and effects | AC1: Miscellaneous | AD1: General index
A2: Rural | B2: 2013 | C2: January | D2: 107.5 | E2: 106.3 | F2: 108.1 | G2: 104.9 | H2: 106.1 | I2: 103.9 | J2: 101.9 | K2: 106.1 | L2: 106.8 | M2: 103.1 | N2: 104.8 | O2: 106.7 | P2: 105.5 | Q2: 105.1 | R2: 106.5 | S2: 105.8 | T2: 106.4 | U2: NA | V2: 105.5 | W2: 104.8 | X2: 104 | Y2: 103.3 | Z2: 103.4 | AA2: 103.8 | AB2: 104.7 | AC2: 104 | AD2: 105.1
A3: Urban | B3: 2013 | C3: January | D3: 110.5 | E3: 109.1 | F3: 113 | G3: 103.6 | H3: 103.4 | I3: 102.3 | J3: 102.9 | K3: 105.8 | L3: 105.1 | M3: 101.8 | N3: 105.1 | O3: 107.9 | P3: 105.9 | Q3: 105.2 | R3: 105.9 | S3: 105 | T3: 105.8 | U3: 100.3 | V3: 105.4 | W3: 104.8 | X3: 104.1 | Y3: 103.2 | Z3: 102.9 | AA3: 103.5 | AB3: 104.3 | AC3: 103.7 | AD3: 104
A4: Rural+Urban | B4: 2013 | C4: January | D4: 108.4 | E4: 107.3 | F4: 110 | G4: 104.4 | H4: 105.1 | I4: 103.2 | J4: 102.2 | K4: 106 | L4: 106.2 | M4: 102.7 | N4: 104.9 | O4: 107.3 | P4: 105.6 | Q4: 105.1 | R4: 106.3 | S4: 105.5 | T4: 106.2 | U4: 100.3 | V4: 105.5 | W4: 104.8 | X4: 104 | Y4: 103.2 | Z4: 103.1 | AA4: 103.6 | AB4: 104.5 | AC4: 103.9 | AD4: 104.6
A5: Rural | B5: 2013 | C5: February | D5: 109.2 | E5: 108.7 | F5: 110.2 | G5: 105.4 | H5: 106.7 | I5: 104 | J5: 102.4 | K5: 105.9 | L5: 105.7 | M5: 103.1 | N5: 105.1 | O5: 107.7 | P5: 106.3 | Q5: 105.6 | R5: 107.1 | S5: 106.3 | T5: 107 | U5: NA | V5: 106.2 | W5: 105.2 | X5: 104.4 | Y5: 103.9 | Z5: 104 | AA5: 104.1 | AB5: 104.6 | AC5: 104.4 | AD5: 105.8
A6: Urban | B6: 2013 | C6: February | D6: 112.9 | E6: 112.9 | F6: 116.9 | G6: 104 | H6: 103.5 | I6: 103.1 | J6: 104.9 | K6: 104.1 | L6: 103.8 | M6: 102.3 | N6: 106 | O6: 109 | P6: 107.2 | Q6: 106 | R6: 106.6 | S6: 105.5 | T6: 106.4 | U6: 100.4 | V6: 105.7 | W6: 105.2 | X6: 104.7 | Y6: 104.4 | Z6: 103.3 | AA6: 103.7 | AB6: 104.3 | AC6: 104.3 | AD6: 104.7
A7: Rural+Urban | B7: 2013 | C7: February | D7: 110.4 | E7: 110.2 | F7: 112.8 | G7: 104.9 | H7: 105.5 | I7: 103.6 | J7: 103.2 | K7: 105.3 | L7: 105.1 | M7: 102.8 | N7: 105.5 | O7: 108.3 | P7: 106.6 | Q7: 105.7 | R7: 106.9 | S7: 106 | T7: 106.8 | U7: 100.4 | V7: 106 | W7: 105.2 | X7: 104.5 | Y7: 104.2 | Z7: 103.6 | AA7: 103.9 | AB7: 104.5 | AC7: 104.4 | AD7: 105.3
A8: Rural | B8: 2013 | C8: March | D8: 110.2 | E8: 108.8 | F8: 109.9 | G8: 105.6 | H8: 106.2 | I8: 105.7 | J8: 101.4 | K8: 105.7 | L8: 105 | M8: 103.3 | N8: 105.6 | O8: 108.2 | P8: 106.6 | Q8: 106.5 | R8: 107.6 | S8: 106.8 | T8: 107.5 | U8: NA | V8: 106.1 | W8: 105.6 | X8: 104.7 | Y8: 104.6 | Z8: 104 | AA8: 104.3 | AB8: 104.3 | AC8: 104.6 | AD8: 106
A9: Urban | B9: 2013 | C9: March | D9: 113.9 | E9: 111.4 | F9: 113.2 | G9: 104.3 | H9: 102.7 | I9: 104.9 | J9: 103.8 | K9: 103.5 | L9: 102.6 | M9: 102.4 | N9: 107 | O9: 109.8 | P9: 107.3 | Q9: 106.8 | R9: 107.2 | S9: 106 | T9: 107 | U9: 100.4 | V9: 106 | W9: 105.7 | X9: 105.2 | Y9: 105.5 | Z9: 103.5 | AA9: 103.8 | AB9: 104.2 | AC9: 104.9 | AD9: 105
A10: Rural+Urban | B10: 2013 | C10: March | D10: 111.4 | E10: 109.7 | F10: 111.2 | G10: 105.1 | H10: 104.9 | I10: 105.3 | J10: 102.2 | K10: 105 | L10: 104.2 | M10: 103 | N10: 106.2 | O10: 108.9 | P10: 106.9 | Q10: 106.6 | R10: 107.4 | S10: 106.5 | T10: 107.3 | U10: 100.4 | V10: 106.1 | W10: 105.6 | X10: 104.9 | Y10: 105.1 | Z10: 103.7 | AA10: 104 | AB10: 104.3 | AC10: 104.7 | AD10: 105.5
A11: Rural | B11: 2013 | C11: April | D11: 110.2 | E11: 109.5 | F11: 106.9 | G11: 106.3 | H11: 105.7 | I11: 108.3 | J11: 103.4 | K11: 105.7 | L11: 104.2 | M11: 103.2 | N11: 106.5 | O11: 108.8 | P11: 107.1 | Q11: 107.1 | R11: 108.1 | S11: 107.4 | T11: 108 | U11: NA | V11: 106.5 | W11: 106.1 | X11: 105.1 | Y11: 104.4 | Z11: 104.5 | AA11: 104.8 | AB11: 102.7 | AC11: 104.6 | AD11: 106.4
A12: Urban | B12: 2013 | C12: April | D12: 114.6 | E12: 113.4 | F12: 106 | G12: 104.7 | H12: 102.1 | I12: 109.5 | J12: 109.7 | K12: 104.6 | L12: 102 | M12: 103.5 | N12: 108.2 | O12: 110.6 | P12: 108.8 | Q12: 108.5 | R12: 107.9 | S12: 106.4 | T12: 107.7 | U12: 100.5 | V12: 106.4 | W12: 106.5 | X12: 105.7 | Y12: 105 | Z12: 104 | AA12: 105.2 | AB12: 103.2 | AC12: 105.1 | AD12: 105.7
A13: Rural+Urban | B13: 2013 | C13: April | D13: 111.6 | E13: 110.9 | F13: 106.6 | G13: 105.7 | H13: 104.4 | I13: 108.9 | J13: 105.5 | K13: 105.3 | L13: 103.5 | M13: 103.3 | N13: 107.2 | O13: 109.6 | P13: 107.7 | Q13: 107.5 | R13: 108 | S13: 107 | T13: 107.9 | U13: 100.5 | V13: 106.5 | W13: 106.3 | X13: 105.3 | Y13: 104.7 | Z13: 104.2 | AA13: 105 | AB13: 102.9 | AC13: 104.8 | AD13: 106.1
A14: Rural | B14: 2013 | C14: May | D14: 110.9 | E14: 109.8 | F14: 105.9 | G14: 107.5 | H14: 105.3 | I14: 108.1 | J14: 107.3 | K14: 106.1 | L14: 103.7 | M14: 104 | N14: 107.4 | O14: 109.9 | P14: 108.1 | Q14: 108.1 | R14: 108.8 | S14: 107.9 | T14: 108.6 | U14: NA | V14: 107.5 | W14: 106.8 | X14: 105.7 | Y14: 104.1 | Z14: 105 | AA14: 105.5 | AB14: 102.1 | AC14: 104.8 | AD14: 107.2
A15: Urban | B15: 2013 | C15: May | D15: 115.4 | E15: 114.2 | F15: 102.7 | G15: 105.5 | H15: 101.5 | I15: 110.6 | J15: 123.7 | K15: 105.2 | L15: 101.9 | M15: 105 | N15: 109.1 | O15: 111.3 | P15: 111.1 | Q15: 109.8 | R15: 108.5 | S15: 106.7 | T15: 108.3 | U15: 100.5 | V15: 107.2 | W15: 107.1 | X15: 106.2 | Y15: 103.9 | Z15: 104.6 | AA15: 105.7 | AB15: 102.6 | AC15: 104.9 | AD15: 106.6
A16: Rural+Urban | B16: 2013 | C16: May | D16: 112.3 | E16: 111.3 | F16: 104.7 | G16: 106.8 | H16: 103.9 | I16: 109.3 | J16: 112.9 | K16: 105.8 | L16: 103.1 | M16: 104.3 | N16: 108.1 | O16: 110.5 | P16: 109.2 | Q16: 108.6 | R16: 108.7 | S16: 107.4 | T16: 108.5 | U16: 100.5 | V16: 107.4 | W16: 106.9 | X16: 105.9 | Y16: 104 | Z16: 104.8 | AA16: 105.6 | AB16: 102.3 | AC16: 104.8 | AD16: 106.9
A17: Rural | B17: 2013 | C17: June | D17: 112.3 | E17: 112.1 | F17: 108.1 | G17: 108.3 | H17: 105.9 | I17: 109.2 | J17: 118 | K17: 106.8 | L17: 104.1 | M17: 105.4 | N17: 108.2 | O17: 111 | P17: 110.6 | Q17: 109 | R17: 109.7 | S17: 108.8 | T17: 109.5 | U17: NA | V17: 108.5 | W17: 107.5 | X17: 106.3 | Y17: 105 | Z17: 105.6 | AA17: 106.5 | AB17: 102.5 | AC17: 105.5 | AD17: 108.9
A18: Urban | B18: 2013 | C18: June | D18: 117 | E18: 120.1 | F18: 112.5 | G18: 107.3 | H18: 101.3 | I18: 112.4 | J18: 143.6 | K18: 105.4 | L18: 101.4 | M18: 106.4 | N18: 110 | O18: 112.2 | P18: 115 | Q18: 110.9 | R18: 109.2 | S18: 107.2 | T18: 108.9 | U18: 106.6 | V18: 108 | W18: 107.7 | X18: 106.5 | Y18: 105.2 | Z18: 105.2 | AA18: 108.1 | AB18: 103.3 | AC18: 106.1 | AD18: 109.7
A19: Rural+Urban | B19: 2013 | C19: June | D19: 113.8 | E19: 114.9 | F19: 109.8 | G19: 107.9 | H19: 104.2 | I19: 110.7 | J19: 126.7 | K19: 106.3 | L19: 103.2 | M19: 105.7 | N19: 109 | O19: 111.6 | P19: 112.2 | Q19: 109.5 | R19: 109.5 | S19: 108.1 | T19: 109.3 | U19: 106.6 | V19: 108.3 | W19: 107.6 | X19: 106.4 | Y19: 105.1 | Z19: 105.4 | AA19: 107.4 | AB19: 102.8 | AC19: 105.8 | AD19: 109.3
A20: Rural | B20: 2013 | C20: July | D20: 113.4 | E20: 114.9 | F20: 110.5 | G20: 109.3 | H20: 106.2 | I20: 110.3 | J20: 129.2 | K20: 107.1 | L20: 104.3 | M20: 106.4 | N20: 109.1 | O20: 112.1 | P20: 113.1 | Q20: 109.8 | R20: 110.5 | S20: 109.5 | T20: 110.3 | U20: NA | V20: 109.5 | W20: 108.3 | X20: 106.9 | Y20: 106.8 | Z20: 106.4 | AA20: 107.8 | AB20: 102.5 | AC20: 106.5 | AD20: 110.7
A21: Urban | B21: 2013 | C21: July | D21: 117.8 | E21: 119.2 | F21: 114 | G21: 108.3 | H21: 101.1 | I21: 113.2 | J21: 160.9 | K21: 105.1 | L21: 101.3 | M21: 107.5 | N21: 110.4 | O21: 113.1 | P21: 117.5 | Q21: 111.7 | R21: 109.8 | S21: 107.8 | T21: 109.5 | U21: 107.7 | V21: 108.6 | W21: 108.1 | X21: 107.1 | Y21: 107.3 | Z21: 105.9 | AA21: 110.1 | AB21: 103.2 | AC21: 107.3 | AD21: 111.4
A22: Rural+Urban | B22: 2013 | C22: July | D22: 114.8 | E22: 116.4 | F22: 111.9 | G22: 108.9 | H22: 104.3 | I22: 111.7 | J22: 140 | K22: 106.4 | L22: 103.3 | M22: 106.8 | N22: 109.6 | O22: 112.6 | P22: 114.7 | Q22: 110.3 | R22: 110.2 | S22: 108.8 | T22: 110 | U22: 107.7 | V22: 109.2 | W22: 108.2 | X22: 107 | Y22: 107.1 | Z22: 106.1 | AA22: 109.1 | AB22: 102.8 | AC22: 106.9 | AD22: 111
A23: Rural | B23: 2013 | C23: August | D23: 114.3 | E23: 115.4 | F23: 111.1 | G23: 110 | H23: 106.4 | I23: 110.8 | J23: 138.9 | K23: 107.4 | L23: 104.1 | M23: 106.9 | N23: 109.7 | O23: 112.6 | P23: 114.9 | Q23: 110.7 | R23: 111.3 | S23: 110.2 | T23: 111.1 | U23: NA | V23: 109.9 | W23: 108.7 | X23: 107.5 | Y23: 107.8 | Z23: 106.8 | AA23: 108.7 | AB23: 105 | AC23: 107.5 | AD23: 112.1
A24: Urban | B24: 2013 | C24: August | D24: 118.3 | E24: 120.4 | F24: 112.7 | G24: 108.9 | H24: 101.1 | I24: 108.7 | J24: 177 | K24: 104.7 | L24: 101 | M24: 108.5 | N24: 110.9 | O24: 114.3 | P24: 119.6 | Q24: 112.4 | R24: 110.6 | S24: 108.3 | T24: 110.2 | U24: 108.9 | V24: 109.3 | W24: 108.7 | X24: 107.6 | Y24: 108.1 | Z24: 106.5 | AA24: 110.8 | AB24: 106 | AC24: 108.3 | AD24: 112.7
A25: Rural+Urban | B25: 2013 | C25: August | D25: 115.6 | E25: 117.2 | F25: 111.7 | G25: 109.6 | H25: 104.5 | I25: 109.8 | J25: 151.8 | K25: 106.5 | L25: 103.1 | M25: 107.4 | N25: 110.2 | O25: 113.4 | P25: 116.6 | Q25: 111.2 | R25: 111 | S25: 109.4 | T25: 110.7 | U25: 108.9 | V25: 109.7 | W25: 108.7 | X25: 107.5 | Y25: 108 | Z25: 106.6 | AA25: 109.9 | AB25: 105.4 | AC25: 107.9 | AD25: 112.4
A26: Rural | B26: 2013 | C26: September | D26: 115.4 | E26: 115.7 | F26: 111.7 | G26: 111 | H26: 107.4 | I26: 110.9 | J26: 154 | K26: 108.1 | L26: 104.2 | M26: 107.9 | N26: 110.4 | O26: 114 | P26: 117.8 | Q26: 111.7 | R26: 112.7 | S26: 111.4 | T26: 112.5 | U26: NA | V26: 111.1 | W26: 109.6 | X26: 108.3 | Y26: 109.3 | Z26: 107.7 | AA26: 109.8 | AB26: 106.7 | AC26: 108.7 | AD26: 114.2
A27: Urban | B27: 2013 | C27: September | D27: 118.6 | E27: 119.1 | F27: 113.2 | G27: 109.6 | H27: 101.7 | I27: 103.2 | J27: 174.3 | K27: 105.1 | L27: 100.8 | M27: 109.1 | N27: 111.1 | O27: 115.4 | P27: 119.2 | Q27: 112.9 | R27: 111.4 | S27: 109 | T27: 111.1 | U27: 109.7 | V27: 109.5 | W27: 109.6 | X27: 107.9 | Y27: 110.4 | Z27: 107.4 | AA27: 111.2 | AB27: 106.9 | AC27: 109.4 | AD27: 113.2
A28: Rural+Urban | B28: 2013 | C28: September | D28: 116.4 | E28: 116.9 | F28: 112.3 | G28: 110.5 | H28: 105.3 | I28: 107.3 | J28: 160.9 | K28: 107.1 | L28: 103.1 | M28: 108.3 | N28: 110.7 | O28: 114.6 | P28: 118.3 | Q28: 112 | R28: 112.2 | S28: 110.4 | T28: 111.9 | U28: 109.7 | V28: 110.5 | W28: 109.6 | X28: 108.1 | Y28: 109.9 | Z28: 107.5 | AA28: 110.6 | AB28: 106.8 | AC28: 109 | AD28: 113.7
A29: Rural | B29: 2013 | C29: October | D29: 116.3 | E29: 115.4 | F29: 112.6 | G29: 111.7 | H29: 107.7 | I29: 113.2 | J29: 164.9 | K29: 108.3 | L29: 103.9 | M29: 108.2 | N29: 111.1 | O29: 114.9 | P29: 119.8 | Q29: 112.2 | R29: 113.6 | S29: 112.3 | T29: 113.4 | U29: NA | V29: 111.6 | W29: 110.4 | X29: 108.9 | Y29: 109.3 | Z29: 108.3 | AA29: 110.2 | AB29: 107.5 | AC29: 109.1 | AD29: 115.5
A30: Urban | B30: 2013 | C30: October | D30: 118.9 | E30: 118.1 | F30: 114.5 | G30: 110.4 | H30: 102.3 | I30: 106.2 | J30: 183.5 | K30: 105.3 | L30: 100.2 | M30: 109.6 | N30: 111.4 | O30: 116 | P30: 120.8 | Q30: 113.5 | R30: 112.5 | S30: 109.7 | T30: 112 | U30: 110.5 | V30: 109.7 | W30: 110.2 | X30: 108.2 | Y30: 109.7 | Z30: 108 | AA30: 111.3 | AB30: 107.3 | AC30: 109.4 | AD30: 114
A31: Rural+Urban | B31: 2013 | C31: October | D31: 117.1 | E31: 116.3 | F31: 113.3 | G31: 111.2 | H31: 105.7 | I31: 109.9 | J31: 171.2 | K31: 107.3 | L31: 102.7 | M31: 108.7 | N31: 111.2 | O31: 115.4 | P31: 120.2 | Q31: 112.5 | R31: 113.2 | S31: 111.2 | T31: 112.8 | U31: 110.5 | V31: 110.9 | W31: 110.3 | X31: 108.6 | Y31: 109.5 | Z31: 108.1 | AA31: 110.8 | AB31: 107.4 | AC31: 109.2 | AD31: 114.8
A32: Rural | B32: 2013 | C32: November | D32: 117.3 | E32: 114.9 | F32: 116.2 | G32: 112.8 | H32: 108.9 | I32: 116.6 | J32: 178.1 | K32: 109.1 | L32: 103.6 | M32: 109 | N32: 111.8 | O32: 116 | P32: 122.5 | Q32: 112.8 | R32: 114.6 | S32: 113.1 | T32: 114.4 | U32: NA | V32: 112.6 | W32: 111.3 | X32: 109.7 | Y32: 109.6 | Z32: 108.7 | AA32: 111 | AB32: 108.2 | AC32: 109.8 | AD32: 117.4
A33: Urban | B33: 2013 | C33: November | D33: 119.8 | E33: 116.3 | F33: 122.6 | G33: 112 | H33: 103.2 | I33: 110 | J33: 192.8 | K33: 106.3 | L33: 99.5 | M33: 110.3 | N33: 111.8 | O33: 117.1 | P33: 122.9 | Q33: 114.1 | R33: 113.5 | S33: 110.3 | T33: 113 | U33: 111.1 | V33: 110 | W33: 110.9 | X33: 108.6 | Y33: 109.5 | Z33: 108.5 | AA33: 111.3 | AB33: 107.9 | AC33: 109.6 | AD33: 115
A34: Rural+Urban | B34: 2013 | C34: November | D34: 118.1 | E34: 115.4 | F34: 118.7 | G34: 112.5 | H34: 106.8 | I34: 113.5 | J34: 183.1 | K34: 108.2 | L34: 102.2 | M34: 109.4 | N34: 111.8 | O34: 116.5 | P34: 122.6 | Q34: 113.1 | R34: 114.2 | S34: 111.9 | T34: 113.8 | U34: 111.1 | V34: 111.6 | W34: 111.1 | X34: 109.3 | Y34: 109.5 | Z34: 108.6 | AA34: 111.2 | AB34: 108.1 | AC34: 109.7 | AD34: 116.3
A35: Rural | B35: 2013 | C35: December | D35: 118.4 | E35: 115.9 | F35: 120.4 | G35: 113.8 | H35: 109.5 | I35: 115.5 | J35: 145.7 | K35: 109.5 | L35: 102.9 | M35: 109.8 | N35: 112.1 | O35: 116.8 | P35: 118.7 | Q35: 113.6 | R35: 115.8 | S35: 114 | T35: 115.5 | U35: NA | V35: 112.8 | W35: 112.1 | X35: 110.1 | Y35: 109.9 | Z35: 109.2 | AA35: 111.6 | AB35: 108.1 | AC35: 110.1 | AD35: 115.5
A36: Urban | B36: 2013 | C36: December | D36: 120.5 | E36: 118.1 | F36: 128.5 | G36: 112.8 | H36: 103.4 | I36: 110.7 | J36: 144.8 | K36: 107.1 | L36: 98.6 | M36: 111.9 | N36: 112.1 | O36: 118.1 | P36: 117.8 | Q36: 115 | R36: 114.2 | S36: 110.9 | T36: 113.7 | U36: 110.7 | V36: 110.4 | W36: 111.3 | X36: 109 | Y36: 109.7 | Z36: 108.9 | AA36: 111.4 | AB36: 107.7 | AC36: 109.8 | AD36: 113.3
A37: Rural+Urban | B37: 2013 | C37: December | D37: 119.1 | E37: 116.7 | F37: 123.5 | G37: 113.4 | H37: 107.3 | I37: 113.3 | J37: 145.4 | K37: 108.7 | L37: 101.5 | M37: 110.5 | N37: 112.1 | O37: 117.4 | P37: 118.4 | Q37: 114 | R37: 115.2 | S37: 112.7 | T37: 114.8 | U37: 110.7 | V37: 111.9 | W37: 111.7 | X37: 109.7 | Y37: 109.8 | Z37: 109 | AA37: 111.5 | AB37: 107.9 | AC37: 110 | AD37: 114.5
A38: Rural | B38: 2014 | C38: January | D38: 118.9 | E38: 117.1 | F38: 120.5 | G38: 114.4 | H38: 109 | I38: 115.5 | J38: 123.9 | K38: 109.6 | L38: 101.8 | M38: 110.2 | N38: 112.4 | O38: 117.3 | P38: 116 | Q38: 114 | R38: 116.5 | S38: 114.5 | T38: 116.2 | U38: NA | V38: 113 | W38: 112.6 | X38: 110.6 | Y38: 110.5 | Z38: 109.6 | AA38: 111.8 | AB38: 108.3 | AC38: 110.6 | AD38: 114.2
A39: Urban | B39: 2014 | C39: January | D39: 121.2 | E39: 122 | F39: 129.9 | G39: 113.6 | H39: 102.9 | I39: 112.1 | J39: 118.9 | K39: 107.5 | L39: 96.9 | M39: 112.7 | N39: 112.1 | O39: 119 | P39: 115.5 | Q39: 115.7 | R39: 114.8 | S39: 111.3 | T39: 114.3 | U39: 111.6 | V39: 111 | W39: 111.9 | X39: 109.7 | Y39: 110.8 | Z39: 109.8 | AA39: 111.5 | AB39: 108 | AC39: 110.5 | AD39: 112.9
A40: Rural+Urban | B40: 2014 | C40: January | D40: 119.6 | E40: 118.8 | F40: 124.1 | G40: 114.1 | H40: 106.8 | I40: 113.9 | J40: 122.2 | K40: 108.9 | L40: 100.2 | M40: 111 | N40: 112.3 | O40: 118.1 | P40: 115.8 | Q40: 114.5 | R40: 115.8 | S40: 113.2 | T40: 115.4 | U40: 111.6 | V40: 112.2 | W40: 112.3 | X40: 110.3 | Y40: 110.7 | Z40: 109.7 | AA40: 111.6 | AB40: 108.2 | AC40: 110.6 | AD40: 113.6
A41: Rural | B41: 2014 | C41: February | D41: 119.4 | E41: 117.7 | F41: 121.2 | G41: 115 | H41: 109 | I41: 116.6 | J41: 116 | K41: 109.8 | L41: 101.1 | M41: 110.4 | N41: 112.9 | O41: 117.8 | P41: 115.3 | Q41: 114.2 | R41: 117.1 | S41: 114.5 | T41: 116.7 | U41: NA | V41: 113.2 | W41: 112.9 | X41: 110.9 | Y41: 110.8 | Z41: 109.9 | AA41: 112 | AB41: 108.7 | AC41: 110.9 | AD41: 114
A42: Urban | B42: 2014 | C42: February | D42: 121.9 | E42: 122 | F42: 124.5 | G42: 115.2 | H42: 102.5 | I42: 114.1 | J42: 111.5 | K42: 108.2 | L42: 95.4 | M42: 113.5 | N42: 112.1 | O42: 119.9 | P42: 115.2 | Q42: 116.2 | R42: 115.3 | S42: 111.7 | T42: 114.7 | U42: 112.5 | V42: 111.1 | W42: 112.6 | X42: 110.4 | Y42: 111.3 | Z42: 110.3 | AA42: 111.6 | AB42: 108.7 | AC42: 111 | AD42: 113.1
A43: Rural+Urban | B43: 2014 | C43: February | D43: 120.2 | E43: 119.2 | F43: 122.5 | G43: 115.1 | H43: 106.6 | I43: 115.4 | J43: 114.5 | K43: 109.3 | L43: 99.2 | M43: 111.4 | N43: 112.6 | O43: 118.8 | P43: 115.3 | Q43: 114.7 | R43: 116.4 | S43: 113.3 | T43: 115.9 | U43: 112.5 | V43: 112.4 | W43: 112.8 | X43: 110.7 | Y43: 111.1 | Z43: 110.1 | AA43: 111.8 | AB43: 108.7 | AC43: 110.9 | AD43: 113.6
A44: Rural | B44: 2014 | C44: March | D44: 120.1 | E44: 118.1 | F44: 120.7 | G44: 116.1 | H44: 109.3 | I44: 119.6 | J44: 117.9 | K44: 110.2 | L44: 101.2 | M44: 110.7 | N44: 113 | O44: 118.3 | P44: 116.2 | Q44: 114.6 | R44: 117.5 | S44: 114.9 | T44: 117.2 | U44: NA | V44: 113.4 | W44: 113.4 | X44: 111.4 | Y44: 111.2 | Z44: 110.2 | AA44: 112.4 | AB44: 108.9 | AC44: 111.3 | AD44: 114.6
A45: Urban | B45: 2014 | C45: March | D45: 122.1 | E45: 121.4 | F45: 121.5 | G45: 116.2 | H45: 102.8 | I45: 117.7 | J45: 113.3 | K45: 108.9 | L45: 96.3 | M45: 114.1 | N45: 112.2 | O45: 120.5 | P45: 116 | Q45: 116.7 | R45: 115.8 | S45: 112.1 | T45: 115.2 | U45: 113.2 | V45: 110.9 | W45: 113 | X45: 110.8 | Y45: 111.6 | Z45: 110.9 | AA45: 111.8 | AB45: 109.2 | AC45: 111.4 | AD45: 113.7
A46: Rural+Urban | B46: 2014 | C46: Marcrh | D46: 120.7 | E46: 119.3 | F46: 121 | G46: 116.1 | H46: 106.9 | I46: 118.7 | J46: 116.3 | K46: 109.8 | L46: 99.6 | M46: 111.8 | N46: 112.7 | O46: 119.3 | P46: 116.1 | Q46: 115.2 | R46: 116.8 | S46: 113.7 | T46: 116.4 | U46: 113.2 | V46: 112.5 | W46: 113.2 | X46: 111.2 | Y46: 111.4 | Z46: 110.6 | AA46: 112 | AB46: 109 | AC46: 111.3 | AD46: 114.2
A47: Rural | B47: 2014 | C47: April | D47: 120.2 | E47: 118.9 | F47: 118.1 | G47: 117 | H47: 109.7 | I47: 125.5 | J47: 120.5 | K47: 111 | L47: 102.6 | M47: 111.2 | N47: 113.5 | O47: 118.7 | P47: 117.2 | Q47: 115.4 | R47: 118.1 | S47: 116.1 | T47: 117.8 | U47: NA | V47: 113.4 | W47: 113.7 | X47: 111.8 | Y47: 111.2 | Z47: 110.5 | AA47: 113 | AB47: 108.9 | AC47: 111.5 | AD47: 115.4
A48: Urban | B48: 2014 | C48: April | D48: 122.5 | E48: 121.7 | F48: 113.3 | G48: 117 | H48: 103.1 | I48: 126.7 | J48: 121.2 | K48: 111 | L48: 100.3 | M48: 115.3 | N48: 112.7 | O48: 121 | P48: 118.2 | Q48: 117.6 | R48: 116.3 | S48: 112.5 | T48: 115.7 | U48: 113.9 | V48: 110.9 | W48: 113.4 | X48: 111 | Y48: 111.2 | Z48: 111.2 | AA48: 112.5 | AB48: 109.1 | AC48: 111.4 | AD48: 114.7
A49: Rural+Urban | B49: 2014 | C49: April | D49: 120.9 | E49: 119.9 | F49: 116.2 | G49: 117 | H49: 107.3 | I49: 126.1 | J49: 120.7 | K49: 111 | L49: 101.8 | M49: 112.6 | N49: 113.2 | O49: 119.8 | P49: 117.6 | Q49: 116 | R49: 117.4 | S49: 114.6 | T49: 117 | U49: 113.9 | V49: 112.5 | W49: 113.6 | X49: 111.5 | Y49: 111.2 | Z49: 110.9 | AA49: 112.7 | AB49: 109 | AC49: 111.5 | AD49: 115.1
A50: Rural | B50: 2014 | C50: May | D50: 120.3 | E50: 120.2 | F50: 116.9 | G50: 118 | H50: 110.1 | I50: 126.3 | J50: 123.9 | K50: 111.5 | L50: 103.5 | M50: 111.6 | N50: 114.2 | O50: 119.2 | P50: 118.2 | Q50: 116.3 | R50: 118.7 | S50: 116.8 | T50: 118.5 | U50: NA | V50: 113.4 | W50: 114.1 | X50: 112.1 | Y50: 111.4 | Z50: 110.9 | AA50: 113.1 | AB50: 108.9 | AC50: 111.8 | AD50: 116
A51: Urban | B51: 2014 | C51: May | D51: 122.7 | E51: 124.1 | F51: 114.2 | G51: 119.1 | H51: 103.5 | I51: 129.2 | J51: 127 | K51: 112.6 | L51: 101.3 | M51: 117 | N51: 112.9 | O51: 121.7 | P51: 120 | Q51: 118.3 | R51: 116.8 | S51: 112.9 | T51: 116.2 | U51: 114.3 | V51: 111.1 | W51: 114.1 | X51: 111.2 | Y51: 111.3 | Z51: 111.5 | AA51: 112.9 | AB51: 109.3 | AC51: 111.7 | AD51: 115.6
A52: Rural+Urban | B52: 2014 | C52: May | D52: 121.1 | E52: 121.6 | F52: 115.9 | G52: 118.4 | H52: 107.7 | I52: 127.7 | J52: 125 | K52: 111.9 | L52: 102.8 | M52: 113.4 | N52: 113.7 | O52: 120.4 | P52: 118.9 | Q52: 116.8 | R52: 118 | S52: 115.2 | T52: 117.6 | U52: 114.3 | V52: 112.5 | W52: 114.1 | X52: 111.8 | Y52: 111.3 | Z52: 111.2 | AA52: 113 | AB52: 109.1 | AC52: 111.8 | AD52: 115.8
A53: Rural | B53: 2014 | C53: June | D53: 120.7 | E53: 121.6 | F53: 116.1 | G53: 119.3 | H53: 110.3 | I53: 125.8 | J53: 129.3 | K53: 112.2 | L53: 103.6 | M53: 112.3 | N53: 114.9 | O53: 120.1 | P53: 119.5 | Q53: 117.3 | R53: 119.7 | S53: 117.3 | T53: 119.3 | U53: NA | V53: 114.4 | W53: 114.9 | X53: 112.8 | Y53: 112.2 | Z53: 111.4 | AA53: 114.3 | AB53: 108 | AC53: 112.3 | AD53: 117
A54: Urban | B54: 2014 | C54: June | D54: 123.1 | E54: 125.9 | F54: 115.4 | G54: 120.4 | H54: 103.4 | I54: 131.2 | J54: 137.5 | K54: 112.8 | L54: 101.4 | M54: 118.3 | N54: 113.2 | O54: 122.4 | P54: 122 | Q54: 119 | R54: 117.4 | S54: 113.2 | T54: 116.7 | U54: 113.9 | V54: 111.2 | W54: 114.3 | X54: 111.4 | Y54: 111.5 | Z54: 111.8 | AA54: 115.1 | AB54: 108.7 | AC54: 112.2 | AD54: 116.4
A55: Rural+Urban | B55: 2014 | C55: June | D55: 121.5 | E55: 123.1 | F55: 115.8 | G55: 119.7 | H55: 107.8 | I55: 128.3 | J55: 132.1 | K55: 112.4 | L55: 102.9 | M55: 114.3 | N55: 114.2 | O55: 121.2 | P55: 120.4 | Q55: 117.8 | R55: 118.8 | S55: 115.6 | T55: 118.3 | U55: 113.9 | V55: 113.2 | W55: 114.6 | X55: 112.3 | Y55: 111.8 | Z55: 111.6 | AA55: 114.8 | AB55: 108.3 | AC55: 112.3 | AD55: 116.7
A56: Rural | B56: 2014 | C56: July | D56: 121.7 | E56: 122.5 | F56: 117.7 | G56: 120.6 | H56: 110.4 | I56: 129.1 | J56: 150.1 | K56: 113.2 | L56: 104.8 | M56: 113.3 | N56: 115.6 | O56: 120.9 | P56: 123.3 | Q56: 118 | R56: 120.7 | S56: 118.3 | T56: 120.3 | U56: NA | V56: 115.3 | W56: 115.4 | X56: 113.4 | Y56: 113.2 | Z56: 111.8 | AA56: 115.5 | AB56: 108.8 | AC56: 113.1 | AD56: 119.5
A57: Urban | B57: 2014 | C57: July | D57: 123.8 | E57: 126.4 | F57: 118 | G57: 121.6 | H57: 103.5 | I57: 133.7 | J57: 172.4 | K57: 113.1 | L57: 102.7 | M57: 120 | N57: 113.8 | O57: 123.4 | P57: 127.1 | Q57: 121 | R57: 118 | S57: 113.6 | T57: 117.4 | U57: 114.8 | V57: 111.6 | W57: 114.9 | X57: 111.5 | Y57: 113 | Z57: 112.4 | AA57: 117.8 | AB57: 109.7 | AC57: 113.5 | AD57: 118.9
A58: Rural+Urban | B58: 2014 | C58: July | D58: 122.4 | E58: 123.9 | F58: 117.8 | G58: 121 | H58: 107.9 | I58: 131.2 | J58: 157.7 | K58: 113.2 | L58: 104.1 | M58: 115.5 | N58: 114.8 | O58: 122.1 | P58: 124.7 | Q58: 118.8 | R58: 119.6 | S58: 116.3 | T58: 119.1 | U58: 114.8 | V58: 113.9 | W58: 115.2 | X58: 112.7 | Y58: 113.1 | Z58: 112.1 | AA58: 116.8 | AB58: 109.2 | AC58: 113.3 | AD58: 119.2
A59: Rural | B59: 2014 | C59: August | D59: 121.8 | E59: 122.8 | F59: 117.8 | G59: 121.9 | H59: 110.6 | I59: 129.7 | J59: 161.1 | K59: 114.1 | L59: 105.1 | M59: 114.6 | N59: 115.8 | O59: 121.7 | P59: 125.3 | Q59: 118.8 | R59: 120.9 | S59: 118.8 | T59: 120.7 | U59: NA | V59: 115.4 | W59: 115.9 | X59: 114 | Y59: 113.2 | Z59: 112.2 | AA59: 116.2 | AB59: 109.4 | AC59: 113.5 | AD59: 120.7
A60: Urban | B60: 2014 | C60: August | D60: 124.8 | E60: 127.3 | F60: 116.5 | G60: 122.2 | H60: 103.6 | I60: 132.7 | J60: 181.9 | K60: 115.2 | L60: 102.7 | M60: 122.1 | N60: 114.4 | O60: 124.7 | P60: 128.9 | Q60: 123 | R60: 118.6 | S60: 114.1 | T60: 117.9 | U60: 115.5 | V60: 111.8 | W60: 115.3 | X60: 112.2 | Y60: 112.5 | Z60: 112.9 | AA60: 119.2 | AB60: 110.5 | AC60: 113.9 | AD60: 119.9
A61: Rural+Urban | B61: 2014 | C61: August | D61: 122.7 | E61: 124.4 | F61: 117.3 | G61: 122 | H61: 108 | I61: 131.1 | J61: 168.2 | K61: 114.5 | L61: 104.3 | M61: 117.1 | N61: 115.2 | O61: 123.1 | P61: 126.6 | Q61: 119.9 | R61: 120 | S61: 116.8 | T61: 119.6 | U61: 115.5 | V61: 114 | W61: 115.6 | X61: 113.3 | Y61: 112.8 | Z61: 112.6 | AA61: 118 | AB61: 109.9 | AC61: 113.7 | AD61: 120.3
A62: Rural | B62: 2014 | C62: September | D62: 122.3 | E62: 122.4 | F62: 117.8 | G62: 122.7 | H62: 110.4 | I62: 129.8 | J62: 158.8 | K62: 115 | L62: 104.7 | M62: 114.9 | N62: 116.5 | O62: 122.6 | P62: 125.3 | Q62: 119.5 | R62: 121.7 | S62: 119.2 | T62: 121.3 | U62: NA | V62: 115.8 | W62: 116.7 | X62: 114.5 | Y62: 112.8 | Z62: 112.6 | AA62: 116.6 | AB62: 109.1 | AC62: 113.7 | AD62: 120.9
A63: Urban | B63: 2014 | C63: September | D63: 124.2 | E63: 125.4 | F63: 116.4 | G63: 122.7 | H63: 103.5 | I63: 124.5 | J63: 168.6 | K63: 116.9 | L63: 101.9 | M63: 122.9 | N63: 114.8 | O63: 125.2 | P63: 126.7 | Q63: 124.3 | R63: 119.2 | S63: 114.5 | T63: 118.4 | U63: 116.1 | V63: 111.8 | W63: 115.5 | X63: 112.3 | Y63: 111.2 | Z63: 113.4 | AA63: 120 | AB63: 110 | AC63: 113.6 | AD63: 119.2
A64: Rural+Urban | B64: 2014 | C64: September | D64: 122.9 | E64: 123.5 | F64: 117.3 | G64: 122.7 | H64: 107.9 | I64: 127.3 | J64: 162.1 | K64: 115.6 | L64: 103.8 | M64: 117.6 | N64: 115.8 | O64: 123.8 | P64: 125.8 | Q64: 120.8 | R64: 120.7 | S64: 117.2 | T64: 120.1 | U64: 116.1 | V64: 114.3 | W64: 116.1 | X64: 113.7 | Y64: 112 | Z64: 113.1 | AA64: 118.6 | AB64: 109.5 | AC64: 113.7 | AD64: 120.1
A65: Rural | B65: 2014 | C65: October | D65: 122.6 | E65: 122.5 | F65: 118.3 | G65: 123.2 | H65: 110.5 | I65: 128.9 | J65: 155.3 | K65: 115.5 | L65: 104 | M65: 115.3 | N65: 116.8 | O65: 123.2 | P65: 125.1 | Q65: 120 | R65: 122.7 | S65: 120.3 | T65: 122.3 | U65: NA | V65: 116.4 | W65: 117.5 | X65: 115.3 | Y65: 112.6 | Z65: 113 | AA65: 116.9 | AB65: 109.3 | AC65: 114 | AD65: 121
A66: Urban | B66: 2014 | C66: October | D66: 124.6 | E66: 126.1 | F66: 117.8 | G66: 123.1 | H66: 103.5 | I66: 123.5 | J66: 159.6 | K66: 117.4 | L66: 101.2 | M66: 123.8 | N66: 115.2 | O66: 125.9 | P66: 125.8 | Q66: 124.3 | R66: 119.6 | S66: 114.9 | T66: 118.9 | U66: 116.7 | V66: 112 | W66: 115.8 | X66: 112.6 | Y66: 111 | Z66: 113.6 | AA66: 120.2 | AB66: 110.1 | AC66: 113.7 | AD66: 119.1
A67: Rural+Urban | B67: 2014 | C67: October | D67: 123.2 | E67: 123.8 | F67: 118.1 | G67: 123.2 | H67: 107.9 | I67: 126.4 | J67: 156.8 | K67: 116.1 | L67: 103.1 | M67: 118.1 | N67: 116.1 | O67: 124.5 | P67: 125.4 | Q67: 121.1 | R67: 121.5 | S67: 118.1 | T67: 121 | U67: 116.7 | V67: 114.7 | W67: 116.7 | X67: 114.3 | Y67: 111.8 | Z67: 113.3 | AA67: 118.8 | AB67: 109.6 | AC67: 113.9 | AD67: 120.1
A68: Rural | B68: 2014 | C68: November | D68: 122.7 | E68: 122.6 | F68: 119.9 | G68: 124 | H68: 110.5 | I68: 128.8 | J68: 152 | K68: 116.2 | L68: 103.3 | M68: 115.8 | N68: 116.8 | O68: 124.5 | P68: 124.9 | Q68: 120.8 | R68: 123.3 | S68: 120.5 | T68: 122.9 | U68: NA | V68: 117.3 | W68: 118.1 | X68: 115.9 | Y68: 112 | Z68: 113.3 | AA68: 117.2 | AB68: 108.8 | AC68: 114.1 | AD68: 121.1
A69: Urban | B69: 2014 | C69: November | D69: 124.5 | E69: 125.6 | F69: 122.7 | G69: 124.6 | H69: 103.2 | I69: 122.2 | J69: 153.2 | K69: 119.3 | L69: 99.8 | M69: 124.6 | N69: 115.8 | O69: 126.9 | P69: 125.4 | Q69: 125.8 | R69: 120.3 | S69: 115.4 | T69: 119.5 | U69: 117.1 | V69: 112.6 | W69: 116.4 | X69: 113 | Y69: 109.7 | Z69: 114 | AA69: 120.3 | AB69: 109.6 | AC69: 113.4 | AD69: 119
A70: Rural+Urban | B70: 2014 | C70: November | D70: 123.3 | E70: 123.7 | F70: 121 | G70: 124.2 | H70: 107.8 | I70: 125.7 | J70: 152.4 | K70: 117.2 | L70: 102.1 | M70: 118.7 | N70: 116.4 | O70: 125.6 | P70: 125.1 | Q70: 122.1 | R70: 122.1 | S70: 118.4 | T70: 121.6 | U70: 117.1 | V70: 115.5 | W70: 117.3 | X70: 114.8 | Y70: 110.8 | Z70: 113.7 | AA70: 119 | AB70: 109.1 | AC70: 113.8 | AD70: 120.1
A71: Rural | B71: 2014 | C71: December | D71: 122.4 | E71: 122.4 | F71: 121.8 | G71: 124.2 | H71: 110.2 | I71: 128.6 | J71: 140.3 | K71: 116.3 | L71: 102 | M71: 116 | N71: 117.3 | O71: 124.8 | P71: 123.3 | Q71: 121.7 | R71: 123.8 | S71: 120.6 | T71: 123.3 | U71: NA | V71: 117.4 | W71: 118.2 | X71: 116.2 | Y71: 111.5 | Z71: 113.3 | AA71: 117.7 | AB71: 109.4 | AC71: 114.2 | AD71: 120.3
A72: Urban | B72: 2014 | C72: December | D72: 124 | E72: 124.7 | F72: 126.3 | G72: 124.9 | H72: 103 | I72: 122.3 | J72: 141 | K72: 120.1 | L72: 97.8 | M72: 125.4 | N72: 116.1 | O72: 127.6 | P72: 124 | Q72: 126.4 | R72: 120.7 | S72: 115.8 | T72: 120 | U72: 116.5 | V72: 113 | W72: 116.8 | X72: 113.2 | Y72: 108.8 | Z72: 114.3 | AA72: 120.7 | AB72: 110.4 | AC72: 113.4 | AD72: 118.4
A73: Rural+Urban | B73: 2014 | C73: December | D73: 122.9 | E73: 123.2 | F73: 123.5 | G73: 124.5 | H73: 107.6 | I73: 125.7 | J73: 140.5 | K73: 117.6 | L73: 100.6 | M73: 119.1 | N73: 116.8 | O73: 126.1 | P73: 123.6 | Q73: 123 | R73: 122.6 | S73: 118.6 | T73: 122 | U73: 116.5 | V73: 115.7 | W73: 117.5 | X73: 115.1 | Y73: 110.1 | Z73: 113.9 | AA73: 119.5 | AB73: 109.8 | AC73: 113.8 | AD73: 119.4
A74: Rural | B74: 2015 | C74: January | D74: 123.1 | E74: 123.1 | F74: 122.1 | G74: 124.9 | H74: 111 | I74: 130.4 | J74: 132.3 | K74: 117.2 | L74: 100.5 | M74: 117.2 | N74: 117.9 | O74: 125.6 | P74: 122.8 | Q74: 122.7 | R74: 124.4 | S74: 121.6 | T74: 124 | U74: NA | V74: 118.4 | W74: 118.9 | X74: 116.6 | Y74: 111 | Z74: 114 | AA74: 118.2 | AB74: 110.2 | AC74: 114.5 | AD74: 120.3
A75: Urban | B75: 2015 | C75: January | D75: 124 | E75: 125.5 | F75: 126.6 | G75: 125.2 | H75: 104.3 | I75: 121.3 | J75: 134.4 | K75: 122.9 | L75: 96.1 | M75: 126.6 | N75: 116.5 | O75: 128 | P75: 123.5 | Q75: 127.4 | R75: 121 | S75: 116.1 | T75: 120.2 | U75: 117.3 | V75: 113.4 | W75: 117.2 | X75: 113.7 | Y75: 107.9 | Z75: 114.6 | AA75: 120.8 | AB75: 111.4 | AC75: 113.4 | AD75: 118.5
A76: Rural+Urban | B76: 2015 | C76: January | D76: 123.4 | E76: 123.9 | F76: 123.8 | G76: 125 | H76: 108.5 | I76: 126.2 | J76: 133 | K76: 119.1 | L76: 99 | M76: 120.3 | N76: 117.3 | O76: 126.7 | P76: 123.1 | Q76: 124 | R76: 123.1 | S76: 119.3 | T76: 122.5 | U76: 117.3 | V76: 116.5 | W76: 118.1 | X76: 115.5 | Y76: 109.4 | Z76: 114.3 | AA76: 119.7 | AB76: 110.7 | AC76: 114 | AD76: 119.5
A77: Rural | B77: 2015 | C77: February | D77: 123.4 | E77: 124.4 | F77: 122.1 | G77: 125.8 | H77: 111.5 | I77: 129.4 | J77: 128.2 | K77: 118.8 | L77: 100 | M77: 118.6 | N77: 118.8 | O77: 126.8 | P77: 122.8 | Q77: 124.2 | R77: 125.4 | S77: 122.7 | T77: 125 | U77: NA | V77: 120 | W77: 119.6 | X77: 117.7 | Y77: 110.9 | Z77: 114.8 | AA77: 118.7 | AB77: 110.8 | AC77: 115 | AD77: 120.6
A78: Urban | B78: 2015 | C78: February | D78: 124.3 | E78: 126.5 | F78: 119.5 | G78: 125.6 | H78: 104.9 | I78: 121.6 | J78: 131.8 | K78: 125.1 | L78: 95 | M78: 127.7 | N78: 116.8 | O78: 128.6 | P78: 123.7 | Q78: 128.1 | R78: 121.3 | S78: 116.5 | T78: 120.6 | U78: 118.1 | V78: 114 | W78: 117.7 | X78: 114.1 | Y78: 106.8 | Z78: 114.9 | AA78: 120.4 | AB78: 111.7 | AC78: 113.2 | AD78: 118.7
A79: Rural+Urban | B79: 2015 | C79: February | D79: 123.7 | E79: 125.1 | F79: 121.1 | G79: 125.7 | H79: 109.1 | I79: 125.8 | J79: 129.4 | K79: 120.9 | L79: 98.3 | M79: 121.6 | N79: 118 | O79: 127.6 | P79: 123.1 | Q79: 125.2 | R79: 123.8 | S79: 120.1 | T79: 123.3 | U79: 118.1 | V79: 117.7 | W79: 118.7 | X79: 116.3 | Y79: 108.7 | Z79: 114.9 | AA79: 119.7 | AB79: 111.2 | AC79: 114.1 | AD79: 119.7
A80: Rural | B80: 2015 | C80: March | D80: 123.3 | E80: 124.7 | F80: 118.9 | G80: 126 | H80: 111.8 | I80: 130.9 | J80: 128 | K80: 119.9 | L80: 98.9 | M80: 119.4 | N80: 118.9 | O80: 127.7 | P80: 123.1 | Q80: 124.7 | R80: 126 | S80: 122.9 | T80: 125.5 | U80: NA | V80: 120.6 | W80: 120.2 | X80: 118.2 | Y80: 111.6 | Z80: 115.5 | AA80: 119.4 | AB80: 110.8 | AC80: 115.5 | AD80: 121.1
A81: Urban | B81: 2015 | C81: March | D81: 124 | E81: 126.7 | F81: 113.5 | G81: 125.9 | H81: 104.8 | I81: 123.8 | J81: 131.4 | K81: 127.2 | L81: 93.2 | M81: 127.4 | N81: 117 | O81: 129.2 | P81: 123.9 | Q81: 128.8 | R81: 121.7 | S81: 116.9 | T81: 120.9 | U81: 118.6 | V81: 114.4 | W81: 118 | X81: 114.3 | Y81: 108.4 | Z81: 115.4 | AA81: 120.6 | AB81: 111.3 | AC81: 113.8 | AD81: 119.1
A82: Rural+Urban | B82: 2015 | C82: March | D82: 123.5 | E82: 125.4 | F82: 116.8 | G82: 126 | H82: 109.2 | I82: 127.6 | J82: 129.2 | K82: 122.4 | L82: 97 | M82: 122.1 | N82: 118.1 | O82: 128.4 | P82: 123.4 | Q82: 125.8 | R82: 124.3 | S82: 120.4 | T82: 123.7 | U82: 118.6 | V82: 118.3 | W82: 119.2 | X82: 116.7 | Y82: 109.9 | Z82: 115.4 | AA82: 120.1 | AB82: 111 | AC82: 114.7 | AD82: 120.2
A83: Rural | B83: 2015 | C83: April | D83: 123.3 | E83: 125.5 | F83: 117.2 | G83: 126.8 | H83: 111.9 | I83: 134.2 | J83: 127.5 | K83: 121.5 | L83: 97.8 | M83: 119.8 | N83: 119.4 | O83: 128.7 | P83: 123.6 | Q83: 125.7 | R83: 126.4 | S83: 123.3 | T83: 126 | U83: NA | V83: 121.2 | W83: 120.9 | X83: 118.6 | Y83: 111.9 | Z83: 116.2 | AA83: 119.9 | AB83: 111.6 | AC83: 116 | AD83: 121.5
A84: Urban | B84: 2015 | C84: April | D84: 123.8 | E84: 128.2 | F84: 110 | G84: 126.3 | H84: 104.5 | I84: 130.6 | J84: 130.8 | K84: 131.3 | L84: 91.6 | M84: 127.7 | N84: 117.2 | O84: 129.5 | P84: 124.6 | Q84: 130.1 | R84: 122.1 | S84: 117.2 | T84: 121.3 | U84: 119.2 | V84: 114.7 | W84: 118.4 | X84: 114.6 | Y84: 108.4 | Z84: 115.6 | AA84: 121.7 | AB84: 111.8 | AC84: 114.2 | AD84: 119.7
A85: Rural+Urban | B85: 2015 | C85: April | D85: 123.5 | E85: 126.4 | F85: 114.4 | G85: 126.6 | H85: 109.2 | I85: 132.5 | J85: 128.6 | K85: 124.8 | L85: 95.7 | M85: 122.4 | N85: 118.5 | O85: 129.1 | P85: 124 | Q85: 126.9 | R85: 124.7 | S85: 120.8 | T85: 124.1 | U85: 119.2 | V85: 118.7 | W85: 119.7 | X85: 117.1 | Y85: 110.1 | Z85: 115.9 | AA85: 121 | AB85: 111.7 | AC85: 115.1 | AD85: 120.7
A86: Rural | B86: 2015 | C86: May | D86: 123.5 | E86: 127.1 | F86: 117.3 | G86: 127.7 | H86: 112.5 | I86: 134.1 | J86: 128.5 | K86: 124.3 | L86: 97.6 | M86: 120.7 | N86: 120.2 | O86: 129.8 | P86: 124.4 | Q86: 126.7 | R86: 127.3 | S86: 124.1 | T86: 126.8 | U86: NA | V86: 121.9 | W86: 121.5 | X86: 119.4 | Y86: 113.3 | Z86: 116.7 | AA86: 120.5 | AB86: 112.3 | AC86: 116.9 | AD86: 122.4
A87: Urban | B87: 2015 | C87: May | D87: 123.8 | E87: 129.7 | F87: 111.3 | G87: 126.6 | H87: 105.2 | I87: 130.8 | J87: 135.6 | K87: 142.6 | L87: 90.8 | M87: 128.8 | N87: 117.7 | O87: 129.9 | P87: 126.1 | Q87: 131.3 | R87: 122.4 | S87: 117.4 | T87: 121.6 | U87: 119.6 | V87: 114.9 | W87: 118.7 | X87: 114.9 | Y87: 110.8 | Z87: 116 | AA87: 122 | AB87: 112.4 | AC87: 115.2 | AD87: 120.7
A88: Rural+Urban | B88: 2015 | C88: May | D88: 123.6 | E88: 128 | F88: 115 | G88: 127.3 | H88: 109.8 | I88: 132.6 | J88: 130.9 | K88: 130.5 | L88: 95.3 | M88: 123.4 | N88: 119.2 | O88: 129.8 | P88: 125 | Q88: 127.9 | R88: 125.4 | S88: 121.3 | T88: 124.7 | U88: 119.6 | V88: 119.2 | W88: 120.2 | X88: 117.7 | Y88: 112 | Z88: 116.3 | AA88: 121.4 | AB88: 112.3 | AC88: 116.1 | AD88: 121.6
A89: Rural | B89: 2015 | C89: June | D89: 124.1 | E89: 130.4 | F89: 122.1 | G89: 128.7 | H89: 114.1 | I89: 133.2 | J89: 135.2 | K89: 131.9 | L89: 96.3 | M89: 123 | N89: 121.1 | O89: 131.2 | P89: 126.6 | Q89: 128.2 | R89: 128.4 | S89: 125.1 | T89: 128 | U89: NA | V89: 122.6 | W89: 122.8 | X89: 120.4 | Y89: 114.2 | Z89: 117.9 | AA89: 122 | AB89: 113 | AC89: 117.9 | AD89: 124.1
A90: Urban | B90: 2015 | C90: June | D90: 123.6 | E90: 134.4 | F90: 120.9 | G90: 127.3 | H90: 106 | I90: 132.3 | J90: 146.7 | K90: 148.1 | L90: 89.8 | M90: 130.5 | N90: 118 | O90: 130.5 | P90: 128.5 | Q90: 132.1 | R90: 123.2 | S90: 117.6 | T90: 122.3 | U90: 119 | V90: 115.1 | W90: 119.2 | X90: 115.4 | Y90: 111.7 | Z90: 116.2 | AA90: 123.8 | AB90: 112.5 | AC90: 116 | AD90: 121.7
A91: Rural+Urban | B91: 2015 | C91: June | D91: 123.9 | E91: 131.8 | F91: 121.6 | G91: 128.2 | H91: 111.1 | I91: 132.8 | J91: 139.1 | K91: 137.4 | L91: 94.1 | M91: 125.5 | N91: 119.8 | O91: 130.9 | P91: 127.3 | Q91: 129.2 | R91: 126.4 | S91: 122 | T91: 125.7 | U91: 119 | V91: 119.8 | W91: 121.1 | X91: 118.5 | Y91: 112.9 | Z91: 116.9 | AA91: 123.1 | AB91: 112.8 | AC91: 117 | AD91: 123
A92: Rural | B92: 2015 | C92: July | D92: 124 | E92: 131.5 | F92: 122 | G92: 128.7 | H92: 113.5 | I92: 133.3 | J92: 140.8 | K92: 133.8 | L92: 94.1 | M92: 123.4 | N92: 121 | O92: 131.7 | P92: 127.5 | Q92: 129.4 | R92: 128.8 | S92: 125.5 | T92: 128.3 | U92: NA | V92: 123 | W92: 123 | X92: 120.8 | Y92: 114.1 | Z92: 118 | AA92: 122.9 | AB92: 112.7 | AC92: 118.1 | AD92: 124.7
A93: Urban | B93: 2015 | C93: July | D93: 123.2 | E93: 134.3 | F93: 119.5 | G93: 127.7 | H93: 106.3 | I93: 132.8 | J93: 153.5 | K93: 149.5 | L93: 85.7 | M93: 131.5 | N93: 118.3 | O93: 131.1 | P93: 129.5 | Q93: 133.1 | R93: 123.5 | S93: 117.9 | T93: 122.7 | U93: 119.9 | V93: 115.3 | W93: 119.5 | X93: 116 | Y93: 111.5 | Z93: 116.6 | AA93: 125.4 | AB93: 111.7 | AC93: 116.3 | AD93: 122.4
A94: Rural+Urban | B94: 2015 | C94: July | D94: 123.7 | E94: 132.5 | F94: 121 | G94: 128.3 | H94: 110.9 | I94: 133.1 | J94: 145.1 | K94: 139.1 | L94: 91.3 | M94: 126.1 | N94: 119.9 | O94: 131.4 | P94: 128.2 | Q94: 130.4 | R94: 126.7 | S94: 122.3 | T94: 126.1 | U94: 119.9 | V94: 120.1 | W94: 121.3 | X94: 119 | Y94: 112.7 | Z94: 117.2 | AA94: 124.4 | AB94: 112.3 | AC94: 117.2 | AD94: 123.6
A95: Rural | B95: 2015 | C95: August | D95: 124.7 | E95: 131.3 | F95: 121.3 | G95: 128.8 | H95: 114 | I95: 134.2 | J95: 153.6 | K95: 137.9 | L95: 93.1 | M95: 123.9 | N95: 121.5 | O95: 132.5 | P95: 129.8 | Q95: 130.1 | R95: 129.5 | S95: 126.3 | T95: 129 | U95: NA | V95: 123.8 | W95: 123.7 | X95: 121.1 | Y95: 113.6 | Z95: 118.5 | AA95: 123.6 | AB95: 112.5 | AC95: 118.2 | AD95: 126.1
A96: Urban | B96: 2015 | C96: August | D96: 123.1 | E96: 131.7 | F96: 118.1 | G96: 128 | H96: 106.8 | I96: 130.1 | J96: 165.5 | K96: 156 | L96: 85.3 | M96: 132.7 | N96: 118.8 | O96: 131.7 | P96: 131.1 | Q96: 134.2 | R96: 123.7 | S96: 118.2 | T96: 122.9 | U96: 120.9 | V96: 115.3 | W96: 120 | X96: 116.6 | Y96: 109.9 | Z96: 117.2 | AA96: 126.2 | AB96: 112 | AC96: 116.2 | AD96: 123.2
A97: Rural+Urban | B97: 2015 | C97: August | D97: 124.2 | E97: 131.4 | F97: 120.1 | G97: 128.5 | H97: 111.4 | I97: 132.3 | J97: 157.6 | K97: 144 | L97: 90.5 | M97: 126.8 | N97: 120.4 | O97: 132.1 | P97: 130.3 | Q97: 131.2 | R97: 127.2 | S97: 122.9 | T97: 126.6 | U97: 120.9 | V97: 120.6 | W97: 122 | X97: 119.4 | Y97: 111.7 | Z97: 117.8 | AA97: 125.1 | AB97: 112.3 | AC97: 117.2 | AD97: 124.8
A98: Rural | B98: 2015 | C98: September | D98: 125.1 | E98: 131.1 | F98: 120.7 | G98: 129.2 | H98: 114.7 | I98: 132.3 | J98: 158.9 | K98: 142.1 | L98: 92.5 | M98: 125.4 | N98: 121.9 | O98: 132.7 | P98: 131 | Q98: 131 | R98: 130.4 | S98: 126.8 | T98: 129.9 | U98: NA | V98: 123.7 | W98: 124.5 | X98: 121.4 | Y98: 113.8 | Z98: 119.6 | AA98: 124.5 | AB98: 113.7 | AC98: 118.8 | AD98: 127
A99: Urban | B99: 2015 | C99: September | D99: 123.4 | E99: 129 | F99: 115.6 | G99: 128.3 | H99: 107 | I99: 124 | J99: 168.5 | K99: 165.4 | L99: 86.3 | M99: 134.4 | N99: 119.1 | O99: 132.3 | P99: 131.5 | Q99: 134.7 | R99: 124 | S99: 118.6 | T99: 123.2 | U99: 121.6 | V99: 115.1 | W99: 120.4 | X99: 117.1 | Y99: 109.1 | Z99: 117.3 | AA99: 126.5 | AB99: 112.9 | AC99: 116.2 | AD99: 123.5
A100: Rural+Urban | B100: 2015 | C100: September | D100: 124.6 | E100: 130.4 | F100: 118.7 | G100: 128.9 | H100: 111.9 | I100: 128.4 | J100: 162.2 | K100: 150 | L100: 90.4 | M100: 128.4 | N100: 120.7 | O100: 132.5 | P100: 131.2 | Q100: 132 | R100: 127.9 | S100: 123.4 | T100: 127.2 | U100: 121.6 | V100: 120.4 | W100: 122.6 | X100: 119.8 | Y100: 111.3 | Z100: 118.3 | AA100: 125.7 | AB100: 113.4 | AC100: 117.5 | AD100: 125.4
...

Sheet CPI Data
A1: Sector | B1: Year | C1: Month | D1: Time Period | E1: Cereals and products | F1: Meat and fish | G1: Egg | H1: Milk and products | I1: Oils and fats | J1: Fruits | K1: Vegetables | L1: Pulses and products | M1: Sugar and Confectionery | N1: Spices | O1: Non-alcoholic beverages | P1: Prepared meals, snacks, sweets etc. | Q1: Food and beverages | R1: Pan, tobacco and intoxicants | S1: Clothing | T1: Footwear | U1: Clothing and footwear | V1: Housing | W1: Fuel and light | X1: Household goods and services | Y1: Health | Z1: Transport and communication | AA1: Recreation and amusement | AB1: Education | AC1: Personal care and effects | AD1: Miscellaneous | AE1: General index | AF1: FOOD | AG1: CLOTHING | AH1: ESSENTIAL | AI1: HEALTH | AJ1: ENERGY | AK1: LUXURY
A2: Rural | B2: 2013 | C2: January | D2: =B2&" "&C2 -> 2013 January | E2: 107.5 | F2: 106.3 | G2: 108.1 | H2: 104.9 | I2: 106.1 | J2: 103.9 | K2: 101.9 | L2: 106.1 | M2: 106.8 | N2: 103.1 | O2: 104.8 | P2: 106.7 | Q2: 105.5 | R2: 105.1 | S2: 106.5 | T2: 105.8 | U2: 106.4 | V2: 100.3 | W2: 105.5 | X2: 104.8 | Y2: 104 | Z2: 103.3 | AA2: 103.4 | AB2: 103.8 | AC2: 104.7 | AD2: 104 | AE2: 105.1 | AF2: =SUM($E2:$Q2) -> 1371.7 | AG2: =SUM($S2:$U2) -> 318.7 | AH2: =SUM(V2,X2,AB2) -> 308.9 | AI2: =SUM(Y2,AC2) -> 208.7 | AJ2: =SUM(W2,Z2) -> 208.8 | AK2: =SUM(R2,AA2,AD2) -> 312.5
A3: Urban | B3: 2013 | C3: January | D3: =B3&" "&C3 -> 2013 January | E3: 110.5 | F3: 109.1 | G3: 113 | H3: 103.6 | I3: 103.4 | J3: 102.3 | K3: 102.9 | L3: 105.8 | M3: 105.1 | N3: 101.8 | O3: 105.1 | P3: 107.9 | Q3: 105.9 | R3: 105.2 | S3: 105.9 | T3: 105 | U3: 105.8 | V3: 100.3 | W3: 105.4 | X3: 104.8 | Y3: 104.1 | Z3: 103.2 | AA3: 102.9 | AB3: 103.5 | AC3: 104.3 | AD3: 103.7 | AE3: 104 | AF3: =SUM($E3:$Q3) -> 1376.4 | AG3: =SUM($S3:$U3) -> 316.7 | AH3: =SUM(V3,X3,AB3) -> 308.6 | AI3: =SUM(Y3,AC3) -> 208.4 | AJ3: =SUM(W3,Z3) -> 208.6 | AK3: =SUM(R3,AA3,AD3) -> 311.8
A4: Rural+Urban | B4: 2013 | C4: January | D4: =B4&" "&C4 -> 2013 January | E4: 108.4 | F4: 107.3 | G4: 110 | H4: 104.4 | I4: 105.1 | J4: 103.2 | K4: 102.2 | L4: 106 | M4: 106.2 | N4: 102.7 | O4: 104.9 | P4: 107.3 | Q4: 105.6 | R4: 105.1 | S4: 106.3 | T4: 105.5 | U4: 106.2 | V4: 100.3 | W4: 105.5 | X4: 104.8 | Y4: 104 | Z4: 103.2 | AA4: 103.1 | AB4: 103.6 | AC4: 104.5 | AD4: 103.9 | AE4: 104.6 | AF4: =SUM($E4:$Q4) -> 1373.3 | AG4: =SUM($S4:$U4) -> 318 | AH4: =SUM(V4,X4,AB4) -> 308.7 | AI4: =SUM(Y4,AC4) -> 208.5 | AJ4: =SUM(W4,Z4) -> 208.7 | AK4: =SUM(R4,AA4,AD4) -> 312.1
A5: Rural | B5: 2013 | C5: February | D5: =B5&" "&C5 -> 2013 February | E5: 109.2 | F5: 108.7 | G5: 110.2 | H5: 105.4 | I5: 106.7 | J5: 104 | K5: 102.4 | L5: 105.9 | M5: 105.7 | N5: 103.1 | O5: 105.1 | P5: 107.7 | Q5: 106.3 | R5: 105.6 | S5: 107.1 | T5: 106.3 | U5: 107 | V5: 100.4 | W5: 106.2 | X5: 105.2 | Y5: 104.4 | Z5: 103.9 | AA5: 104 | AB5: 104.1 | AC5: 104.6 | AD5: 104.4 | AE5: 105.8 | AF5: =SUM($E5:$Q5) -> 1380.4 | AG5: =SUM($S5:$U5) -> 320.4 | AH5: =SUM(V5,X5,AB5) -> 309.7 | AI5: =SUM(Y5,AC5) -> 209 | AJ5: =SUM(W5,Z5) -> 210.1 | AK5: =SUM(R5,AA5,AD5) -> 314
A6: Urban | B6: 2013 | C6: February | D6: =B6&" "&C6 -> 2013 February | E6: 112.9 | F6: 112.9 | G6: 116.9 | H6: 104 | I6: 103.5 | J6: 103.1 | K6: 104.9 | L6: 104.1 | M6: 103.8 | N6: 102.3 | O6: 106 | P6: 109 | Q6: 107.2 | R6: 106 | S6: 106.6 | T6: 105.5 | U6: 106.4 | V6: 100.4 | W6: 105.7 | X6: 105.2 | Y6: 104.7 | Z6: 104.4 | AA6: 103.3 | AB6: 103.7 | AC6: 104.3 | AD6: 104.3 | AE6: 104.7 | AF6: =SUM($E6:$Q6) -> 1390.6 | AG6: =SUM($S6:$U6) -> 318.5 | AH6: =SUM(V6,X6,AB6) -> 309.3 | AI6: =SUM(Y6,AC6) -> 209 | AJ6: =SUM(W6,Z6) -> 210.1 | AK6: =SUM(R6,AA6,AD6) -> 313.6
A7: Rural+Urban | B7: 2013 | C7: February | D7: =B7&" "&C7 -> 2013 February | E7: 110.4 | F7: 110.2 | G7: 112.8 | H7: 104.9 | I7: 105.5 | J7: 103.6 | K7: 103.2 | L7: 105.3 | M7: 105.1 | N7: 102.8 | O7: 105.5 | P7: 108.3 | Q7: 106.6 | R7: 105.7 | S7: 106.9 | T7: 106 | U7: 106.8 | V7: 100.4 | W7: 106 | X7: 105.2 | Y7: 104.5 | Z7: 104.2 | AA7: 103.6 | AB7: 103.9 | AC7: 104.5 | AD7: 104.4 | AE7: 105.3 | AF7: =SUM($E7:$Q7) -> 1384.2 | AG7: =SUM($S7:$U7) -> 319.7 | AH7: =SUM(V7,X7,AB7) -> 309.5 | AI7: =SUM(Y7,AC7) -> 209 | AJ7: =SUM(W7,Z7) -> 210.2 | AK7: =SUM(R7,AA7,AD7) -> 313.7
A8: Rural | B8: 2013 | C8: March | D8: =B8&" "&C8 -> 2013 March | E8: 110.2 | F8: 108.8 | G8: 109.9 | H8: 105.6 | I8: 106.2 | J8: 105.7 | K8: 101.4 | L8: 105.7 | M8: 105 | N8: 103.3 | O8: 105.6 | P8: 108.2 | Q8: 106.6 | R8: 106.5 | S8: 107.6 | T8: 106.8 | U8: 107.5 | V8: 100.4 | W8: 106.1 | X8: 105.6 | Y8: 104.7 | Z8: 104.6 | AA8: 104 | AB8: 104.3 | AC8: 104.3 | AD8: 104.6 | AE8: 106 | AF8: =SUM($E8:$Q8) -> 1382.2 | AG8: =SUM($S8:$U8) -> 321.9 | AH8: =SUM(V8,X8,AB8) -> 310.3 | AI8: =SUM(Y8,AC8) -> 209 | AJ8: =SUM(W8,Z8) -> 210.7 | AK8: =SUM(R8,AA8,AD8) -> 315.1
A9: Urban | B9: 2013 | C9: March | D9: =B9&" "&C9 -> 2013 March | E9: 113.9 | F9: 111.4 | G9: 113.2 | H9: 104.3 | I9: 102.7 | J9: 104.9 | K9: 103.8 | L9: 103.5 | M9: 102.6 | N9: 102.4 | O9: 107 | P9: 109.8 | Q9: 107.3 | R9: 106.8 | S9: 107.2 | T9: 106 | U9: 107 | V9: 100.4 | W9: 106 | X9: 105.7 | Y9: 105.2 | Z9: 105.5 | AA9: 103.5 | AB9: 103.8 | AC9: 104.2 | AD9: 104.9 | AE9: 105 | AF9: =SUM($E9:$Q9) -> 1386.8 | AG9: =SUM($S9:$U9) -> 320.2 | AH9: =SUM(V9,X9,AB9) -> 309.9 | AI9: =SUM(Y9,AC9) -> 209.4 | AJ9: =SUM(W9,Z9) -> 211.5 | AK9: =SUM(R9,AA9,AD9) -> 315.2
A10: Rural+Urban | B10: 2013 | C10: March | D10: =B10&" "&C10 -> 2013 March | E10: 111.4 | F10: 109.7 | G10: 111.2 | H10: 105.1 | I10: 104.9 | J10: 105.3 | K10: 102.2 | L10: 105 | M10: 104.2 | N10: 103 | O10: 106.2 | P10: 108.9 | Q10: 106.9 | R10: 106.6 | S10: 107.4 | T10: 106.5 | U10: 107.3 | V10: 100.4 | W10: 106.1 | X10: 105.6 | Y10: 104.9 | Z10: 105.1 | AA10: 103.7 | AB10: 104 | AC10: 104.3 | AD10: 104.7 | AE10: 105.5 | AF10: =SUM($E10:$Q10) -> 1384 | AG10: =SUM($S10:$U10) -> 321.2 | AH10: =SUM(V10,X10,AB10) -> 310 | AI10: =SUM(Y10,AC10) -> 209.2 | AJ10: =SUM(W10,Z10) -> 211.2 | AK10: =SUM(R10,AA10,AD10) -> 315
A11: Rural | B11: 2013 | C11: April | D11: =B11&" "&C11 -> 2013 April | E11: 110.2 | F11: 109.5 | G11: 106.9 | H11: 106.3 | I11: 105.7 | J11: 108.3 | K11: 103.4 | L11: 105.7 | M11: 104.2 | N11: 103.2 | O11: 106.5 | P11: 108.8 | Q11: 107.1 | R11: 107.1 | S11: 108.1 | T11: 107.4 | U11: 108 | V11: 100.5 | W11: 106.5 | X11: 106.1 | Y11: 105.1 | Z11: 104.4 | AA11: 104.5 | AB11: 104.8 | AC11: 102.7 | AD11: 104.6 | AE11: 106.4 | AF11: =SUM($E11:$Q11) -> 1385.8 | AG11: =SUM($S11:$U11) -> 323.5 | AH11: =SUM(V11,X11,AB11) -> 311.4 | AI11: =SUM(Y11,AC11) -> 207.8 | AJ11: =SUM(W11,Z11) -> 210.9 | AK11: =SUM(R11,AA11,AD11) -> 316.2
A12: Urban | B12: 2013 | C12: April | D12: =B12&" "&C12 -> 2013 April | E12: 114.6 | F12: 113.4 | G12: 106 | H12: 104.7 | I12: 102.1 | J12: 109.5 | K12: 109.7 | L12: 104.6 | M12: 102 | N12: 103.5 | O12: 108.2 | P12: 110.6 | Q12: 108.8 | R12: 108.5 | S12: 107.9 | T12: 106.4 | U12: 107.7 | V12: 100.5 | W12: 106.4 | X12: 106.5 | Y12: 105.7 | Z12: 105 | AA12: 104 | AB12: 105.2 | AC12: 103.2 | AD12: 105.1 | AE12: 105.7 | AF12: =SUM($E12:$Q12) -> 1397.7 | AG12: =SUM($S12:$U12) -> 322 | AH12: =SUM(V12,X12,AB12) -> 312.2 | AI12: =SUM(Y12,AC12) -> 208.9 | AJ12: =SUM(W12,Z12) -> 211.4 | AK12: =SUM(R12,AA12,AD12) -> 317.6
A13: Rural+Urban | B13: 2013 | C13: April | D13: =B13&" "&C13 -> 2013 April | E13: 111.6 | F13: 110.9 | G13: 106.6 | H13: 105.7 | I13: 104.4 | J13: 108.9 | K13: 105.5 | L13: 105.3 | M13: 103.5 | N13: 103.3 | O13: 107.2 | P13: 109.6 | Q13: 107.7 | R13: 107.5 | S13: 108 | T13: 107 | U13: 107.9 | V13: 100.5 | W13: 106.5 | X13: 106.3 | Y13: 105.3 | Z13: 104.7 | AA13: 104.2 | AB13: 105 | AC13: 102.9 | AD13: 104.8 | AE13: 106.1 | AF13: =SUM($E13:$Q13) -> 1390.2 | AG13: =SUM($S13:$U13) -> 322.9 | AH13: =SUM(V13,X13,AB13) -> 311.8 | AI13: =SUM(Y13,AC13) -> 208.2 | AJ13: =SUM(W13,Z13) -> 211.2 | AK13: =SUM(R13,AA13,AD13) -> 316.5
... A226: Rural+Urban | B226: 2019 | C226: March | D226: =B226&" "&C226 -> 2019 March | E226: 137.8 | F226: 153 | G226: 140.3 | H226: 142.3 | I226: 122 | J226: 137.6 | K226: 132.6 | L226: 121.8 | M226: 109 | N226: 139.5 | O226: 133.7 | P226: 155.2 | Q226: 138.1 | R226: 163.5 | S226: 147.9 | T226: 139.9 | U226: 146.7 | V226: 149 | W226: 139.7 | X226: 143.8 | Y226: 146.2 | Z226: 124.6 | AA226: 137.7 | AB226: 150.3 | AC226: 133.4 | AD226: 137.7 | AE226: 140.4 | AF226: =SUM($E226:$Q226) -> 1762.9 | AG226: =SUM($S226:$U226) -> 434.5 | AH226: =SUM(V226,X226,AB226) -> 443.1 | AI226: =SUM(Y226,AC226) -> 279.6 | AJ226: =SUM(W226,Z226) -> 264.3 | AK226: =SUM(R226,AA226,AD226) -> 438.9
A227: Rural | B227: 2019 | C227: April | D227: =B227&" "&C227 -> 2019 April | E227: =AVERAGE(E224,E221,E218,E215,E212,E209) -> 137.3 | F227: =AVERAGE(F224,F221,F218,F215,F212,F209) -> 151.65 | G227: =AVERAGE(G224,G221,G218,G215,G212,G209) -> 137.45 | H227: =AVERAGE(H224,H221,H218,H215,H212,H209) -> 142.26667 | I227: =AVERAGE(I224,I221,I218,I215,I212,I209) -> 123.76667 | J227: =AVERAGE(J224,J221,J218,J215,J212,J209) -> 139.33333 | K227: =AVERAGE(K224,K221,K218,K215,K212,K209) -> 136.71667 | L227: =AVERAGE(L224,L221,L218,L215,L212,L209) -> 121.4 | ... U227: =AVERAGE(U224,U221,U218,U215,U212,U209) -> 150.21667 | V227: 148.4 | W227: =AVERAGE(W224,W221,W218,W215,W212,W209) -> 147.81667 | X227: =AVERAGE(X224,X221,X218,X215,X212,X209) -> 149.2 | Y227: =AVERAGE(Y224,Y221,Y218,Y215,Y212,Y209) -> 148.28333 | Z227: =AVERAGE(Z224,Z221,Z218,Z215,Z212,Z209) -> 129.61667 | AA227: =AVERAGE(AA224,AA221,AA218,AA215,AA212,AA209) -> 142.76667 | AB227: =AVERAGE(AB224,AB221,AB218,AB215,AB212,AB209) -> 153.25 | AC227: =AVERAGE(AC224,AC221,AC218,AC215,AC212,AC209) -> 133.85 | AD227: =AVERAGE(AD224,AD221,AD218,AD215,AD212,AD209) -> 141.3 | AE227: =AVERAGE(AE224,AE221,AE218,AE215,AE212,AE209) -> 141.61667 | AF227: =SUM($E227:$Q227) -> 1770.5667 | AG227: =SUM($S227:$U227) -> 446.73333 | AH227: =SUM(V227,X227,AB227) -> 450.85 | AI227: =SUM(Y227,AC227) -> 282.13333 | AJ227: =SUM(W227,Z227) -> 277.43333 | AK227: =SUM(R227,AA227,AD227) -> 446.11667
A228: Urban | B228: 2019 | C228: April | D228: =B228&" "&C228 -> 2019 April | E228: =AVERAGE(E225,E222,E219) -> 139.13333 | F228: =AVERAGE(F225,F222,F219) -> 150.2 | G228: =AVERAGE(G225,G222,G219) -> 143.9 | H228: =AVERAGE(H225,H222,H219) -> 141.76667 | I228: =AVERAGE(I225,I222,I219) -> 118.3 | J228: =AVERAGE(J225,J222,J219) -> 137.2 | K228: =AVERAGE(K225,K222,K219) -> 134.43333 | L228: =AVERAGE(L225,L222,L219) -> 119.6 | ... U228: =AVERAGE(U225,U222,U219) -> 141.36667 | V228: 148.4 | W228: =AVERAGE(W225,W222,W219) -> 128.16667 | X228: =AVERAGE(X225,X222,X219) -> 136.56667 | Y228: =AVERAGE(Y225,Y222,Y219) -> 138.5 | Z228: =AVERAGE(Z225,Z222,Z219) -> 119.23333 | AA228: =AVERAGE(AA225,AA222,AA219) -> 132.36667 | AB228: =AVERAGE(AB225,AB222,AB219) -> 146.63333 | AC228: =AVERAGE(AC225,AC222,AC219) -> 132.4 | AD228: =AVERAGE(AD225,AD222,AD219) -> 132.33333 | AE228: =AVERAGE(AE225,AE222,AE219) -> 138.7 | AF228: =SUM($E228:$Q228) -> 1755.7 | AG228: =SUM($S228:$U228) -> 415.43333 | AH228: =SUM(V228,X228,AB228) -> 431.6 | AI228: =SUM(Y228,AC228) -> 270.9 | AJ228: =SUM(W228,Z228) -> 247.4 | AK228: =SUM(R228,AA228,AD228) -> 429.66667
A229: Rural+Urban | B229: 2019 | C229: April | D229: =B229&" "&C229 -> 2019 April | E229: =AVERAGE(E226,E223,E220) -> 137.5 | F229: =AVERAGE(F226,F223,F220) -> 152.13333 | G229: =AVERAGE(G226,G223,G220) -> 140.66667 | H229: =AVERAGE(H226,H223,H220) -> 142.2 | I229: =AVERAGE(I226,I223,I220) -> 121.93333 | J229: =AVERAGE(J226,J223,J220) -> 136.46667 | K229: =AVERAGE(K226,K223,K220) -> 131.2 | L229: =AVERAGE(L226,L223,L220) -> 121.03333 | ... U229: =AVERAGE(U226,U223,U220) -> 146.53333 | V229: 148.4 | W229: =AVERAGE(W226,W223,W220) -> 139.2 | X229: =AVERAGE(X226,X223,X220) -> 143.7 | Y229: =AVERAGE(Y226,Y223,Y220) -> 145.63333 | Z229: =AVERAGE(Z226,Z223,Z220) -> 123.93333 | AA229: =AVERAGE(AA226,AA223,AA220) -> 137.16667 | AB229: =AVERAGE(AB226,AB223,AB220) -> 150.26667 | AC229: =AVERAGE(AC226,AC223,AC220) -> 133.43333 | AD229: =AVERAGE(AD226,AD223,AD220) -> 137.33333 | AE229: =AVERAGE(AE226,AE223,AE220) -> 139.96667 | AF229: =SUM($E229:$Q229) -> 1757.8 | AG229: =SUM($S229:$U229) -> 433.8 | AH229: =SUM(V229,X229,AB229) -> 442.36667 | AI229: =SUM(Y229,AC229) -> 279.06667 | AJ229: =SUM(W229,Z229) -> 263.13333 | AK229: =SUM(R229,AA229,AD229) -> 437.86667
A230: Rural | B230: 2019 | C230: May | D230: =B230&" "&C230 -> 2019 May | E230: 137.4 | F230: 159.5 | G230: 134.5 | H230: 142.6 | I230: 124 | J230: 143.7 | K230: 133.4 | L230: 125.1 | M230: 109.3 | N230: 139.3 | O230: 137.7 | P230: 156.4 | Q230: 139.2 | R230: 163.3 | S230: 151.3 | T230: 146.6 | U230: 150.7 | V230: 150.1 | W230: 146.9 | X230: 149.5 | Y230: 151.3 | Z230: 130.2 | AA230: 145.9 | AB230: 156.7 | AC230: 133.9 | AD230: 142.9 | AE230: 142.4 | AF230: =SUM($E230:$Q230) -> 1782.1 | AG230: =SUM($S230:$U230) -> 448.6 | AH230: =SUM(V230,X230,AB230) -> 456.3 | AI230: =SUM(Y230,AC230) -> 285.2 | AJ230: =SUM(W230,Z230) -> 277.1 | AK230: =SUM(R230,AA230,AD230) -> 452.1
A231: Urban | B231: 2019 | C231: May | D231: =B231&" "&C231 -> 2019 May | E231: 140.4 | F231: 156.7 | G231: 138.3 | H231: 142.4 | I231: 118.6 | J231: 149.7 | K231: 161.6 | L231: 124.4 | M231: 111.2 | N231: 141 | O231: 128.9 | P231: 154.5 | Q231: 143.8 | R231: 166.2 | S231: 144 | T231: 131.7 | U231: 142.2 | V231: 150.1 | W231: 129.4 | X231: 137.2 | Y231: 139.8 | Z231: 120.1 | AA231: 134 | AB231: 148 | AC231: 132.6 | AD231: 133.3 | AE231: 141.5 | AF231: =SUM($E231:$Q231) -> 1811.5 | AG231: =SUM($S231:$U231) -> 417.9 | AH231: =SUM(V231,X231,AB231) -> 435.3 | AI231: =SUM(Y231,AC231) -> 272.4 | AJ231: =SUM(W231,Z231) -> 249.5 | AK231: =SUM(R231,AA231,AD231) -> 433.5
A232: Rural+Urban | B232: 2019 | C232: May | D232: =B232&" "&C232 -> 2019 May | E232: 138.3 | F232: 158.5 | G232: 136 | H232: 142.5 | I232: 122 | J232: 146.5 | K232: 143 | L232: 124.9 | M232: 109.9 | N232: 139.9 | O232: 134 | P232: 155.5 | Q232: 140.9 | R232: 164.1 | S232: 148.4 | T232: 140.4 | U232: 147.3 | V232: 150.1 | W232: 140.3 | X232: 143.7 | Y232: 146.9 | Z232: 124.9 | AA232: 139.2 | AB232: 151.6 | AC232: 133.4 | AD232: 138.2 | AE232: 142 | AF232: =SUM($E232:$Q232) -> 1791.9 | AG232: =SUM($S232:$U232) -> 436.1 | AH232: =SUM(V232,X232,AB232) -> 445.4 | AI232: =SUM(Y232,AC232) -> 280.3 | AJ232: =SUM(W232,Z232) -> 265.2 | AK232: =SUM(R232,AA232,AD232) -> 441.5
A233: Rural | B233: 2019 | C233: June | D233: =B233&" "&C233 -> 2019 June | E233: 137.8 | F233: 163.5 | G233: 136.2 | H233: 143.2 | I233: 124.3 | J233: 143.3 | K233: 140.6 | L233: 128.7 | M233: 110.6 | N233: 140.4 | O233: 138 | P233: 156.6 | Q233: 141 | R233: 164.2 | S233: 151.4 | T233: 146.5 | U233: 150.7 | V233: 149.4 | W233: 147.8 | X233: 149.6 | Y233: 151.7 | Z233: 130.2 | AA233: 146.4 | AB233: 157.7 | AC233: 134.8 | AD233: 143.3 | AE233: 143.6 | AF233: =SUM($E233:$Q233) -> 1804.2 | AG233: =SUM($S233:$U233) -> 448.6 | AH233: =SUM(V233,X233,AB233) -> 456.7 | AI233: =SUM(Y233,AC233) -> 286.5 | AJ233: =SUM(W233,Z233) -> 278 | AK233: =SUM(R233,AA233,AD233) -> 453.9
A234: Urban | B234: 2019 | C234: June | D234: =B234&" "&C234 -> 2019 June | E234: 140.7 | F234: 159.6 | G234: 140.4 | H234: 143.4 | I234: 118.6 | J234: 150.9 | K234: 169.8 | L234: 127.4 | M234: 111.8 | N234: 141 | O234: 129 | P234: 155.1 | Q234: 145.6 | R234: 166.7 | S234: 144.3 | T234: 131.7 | U234: 142.4 | V234: 149.4 | W234: 130.5 | X234: 137.4 | Y234: 140.3 | Z234: 119.6 | AA234: 134.3 | AB234: 148.9 | AC234: 133.7 | AD234: 133.6 | AE234: 142.1 | AF234: =SUM($E234:$Q234) -> 1833.3 | AG234: =SUM($S234:$U234) -> 418.4 | AH234: =SUM(V234,X234,AB234) -> 435.7 | AI234: =SUM(Y234,AC234) -> 274 | AJ234: =SUM(W234,Z234) -> 250.1 | AK234: =SUM(R234,AA234,AD234) -> 434.6
A235: Rural+Urban | B235: 2019 | C235: June | D235: =B235&" "&C235 -> 2019 June | E235: 138.7 | F235: 162.1 | G235: 137.8 | H235: 143.3 | I235: 122.2 | J235: 146.8 | K235: 150.5 | L235: 128.3 | M235: 111 | N235: 140.6 | O235: 134.2 | P235: 155.9 | Q235: 142.7 | R235: 164.9 | S235: 148.6 | T235: 140.4 | U235: 147.4 | V235: 149.4 | W235: 141.2 | X235: 143.8 | Y235: 147.4 | Z235: 124.6 | AA235: 139.6 | AB235: 152.5 | AC235: 134.3 | AD235: 138.6 | AE235: 142.9 | AF235: =SUM($E235:$Q235) -> 1814.1 | AG235: =SUM($S235:$U235) -> 436.4 | AH235: =SUM(V235,X235,AB235) -> 445.7 | AI235: =SUM(Y235,AC235) -> 281.7 | AJ235: =SUM(W235,Z235) -> 265.8 | AK235: =SUM(R235,AA235,AD235) -> 443.1
A236: Rural | B236: 2019 | C236: July | D236: =B236&" "&C236 -> 2019 July | E236: 138.4 | F236: 164 | G236: 138.4 | H236: 143.9 | I236: 124.4 | J236: 146.4 | K236: 150.1 | L236: 130.6 | M236: 110.8 | N236: 141.7 | O236: 138.5 | P236: 156.7 | Q236: 143 | R236: 164.5 | S236: 151.6 | T236: 146.6 | U236: 150.9 | V236: 150.6 | W236: 146.8 | X236: 150 | Y236: 152.2 | Z236: 131.2 | AA236: 147.5 | AB236: 159.1 | AC236: 136.1 | AD236: 144.2 | AE236: 144.9 | AF236: =SUM($E236:$Q236) -> 1826.9 | AG236: =SUM($S236:$U236) -> 449.1 | AH236: =SUM(V236,X236,AB236) -> 459.7 | AI236: =SUM(Y236,AC236) -> 288.3 | AJ236: =SUM(W236,Z236) -> 278 | AK236: =SUM(R236,AA236,AD236) -> 456.2
A237: Urban | B237: 2019 | C237: July | D237: =B237&" "&C237 -> 2019 July | E237: 141.4 | F237: 160.2 | G237: 142.5 | H237: 144.1 | I237: 119.3 | J237: 154.7 | K237: 180.1 | L237: 128.9 | M237: 111.8 | N237: 141.6 | O237: 129.5 | P237: 155.6 | Q237: 147.7 | R237: 167.2 | S237: 144.7 | T237: 131.9 | U237: 142.7 | V237: 150.6 | W237: 127 | X237: 137.7 | Y237: 140.8 | Z237: 120.6 | AA237: 135 | AB237: 150.4 | AC237: 135.1 | AD237: 134.5 | AE237: 143.3 | AF237: =SUM($E237:$Q237) -> 1857.4 | AG237: =SUM($S237:$U237) -> 419.3 | AH237: =SUM(V237,X237,AB237) -> 438.7 | AI237: =SUM(Y237,AC237) -> 275.9 | AJ237: =SUM(W237,Z237) -> 247.6 | AK237: =SUM(R237,AA237,AD237) -> 436.7
A238: Rural+Urban | B238: 2019 | C238: July | D238: =B238&" "&C238 -> 2019 July | E238: 139.3 | F238: 162.7 | G238: 140 | H238: 144 | I238: 122.5 | J238: 150.3 | K238: 160.3 | L238: 130 | M238: 111.1 | N238: 141.7 | O238: 134.7 | P238: 156.2 | Q238: 144.7 | R238: 165.2 | S238: 148.9 | T238: 140.5 | U238: 147.6 | V238: 150.6 | W238: 139.3 | X238: 144.2 | Y238: 147.9 | Z238: 125.6 | AA238: 140.5 | AB238: 154 | AC238: 135.7 | AD238: 139.5 | AE238: 144.2 | AF238: =SUM($E238:$Q238) -> 1837.5 | AG238: =SUM($S238:$U238) -> 437 | AH238: =SUM(V238,X238,AB238) -> 448.8 | AI238: =SUM(Y238,AC238) -> 283.6 | AJ238: =SUM(W238,Z238) -> 264.9 | AK238: =SUM(R238,AA238,AD238) -> 445.2
A239: Rural | B239: 2019 | C239: August | D239: =B239&" "&C239 -> 2019 August | E239: 139.2 | F239: 161.9 | G239: 137.1 | H239: 144.6 | I239: 124.7 | J239: 145.5 | K239: 156.2 | L239: 131.5 | M239: 111.7 | N239: 142.7 | O239: 138.5 | P239: 156.9 | Q239: 144 | R239: 165.1 | S239: 151.8 | T239: 146.6 | U239: 151.1 | V239: 151.6 | W239: 146.4 | X239: 150.2 | Y239: 152.7 | Z239: 131.4 | AA239: 148 | AB239: 159.7 | AC239: 138.8 | AD239: 144.9 | AE239: 145.7 | AF239: =SUM($E239:$Q239) -> 1834.5 | AG239: =SUM($S239:$U239) -> 449.5 | AH239: =SUM(V239,X239,AB239) -> 461.5 | AI239: =SUM(Y239,AC239) -> 291.5 | AJ239: =SUM(W239,Z239) -> 277.8 | AK239: =SUM(R239,AA239,AD239) -> 458
A240: Urban | B240: 2019 | C240: August | D240: =B240&" "&C240 -> 2019 August | E240: 142.1 | F240: 158.3 | G240: 140.8 | H240: 144.9 | I240: 119.9 | J240: 153.9 | K240: 189.1 | L240: 129.8 | M240: 112.7 | N240: 142.5 | O240: 129.8 | P240: 156.2 | Q240: 149.1 | R240: 167.9 | S240: 145 | T240: 132.2 | U240: 143 | V240: 151.6 | W240: 125.5 | X240: 138.1 | Y240: 141.5 | Z240: 120.8 | AA240: 135.4 | AB240: 151.5 | AC240: 137.8 | AD240: 135.3 | AE240: 144.2 | AF240: =SUM($E240:$Q240) -> 1869.1 | AG240: =SUM($S240:$U240) -> 420.2 | AH240: =SUM(V240,X240,AB240) -> 441.2 | AI240: =SUM(Y240,AC240) -> 279.3 | AJ240: =SUM(W240,Z240) -> 246.3 | AK240: =SUM(R240,AA240,AD240) -> 438.6
A241: Rural+Urban | B241: 2019 | C241: August | D241: =B241&" "&C241 -> 2019 August | E241: 140.1 | F241: 160.6 | G241: 138.5 | H241: 144.7 | I241: 122.9 | J241: 149.4 | K241: 167.4 | L241: 130.9 | M241: 112 | N241: 142.6 | O241: 134.9 | P241: 156.6 | Q241: 145.9 | R241: 165.8 | S241: 149.1 | T241: 140.6 | U241: 147.9 | V241: 151.6 | W241: 138.5 | X241: 144.5 | Y241: 148.5 | Z241: 125.8 | AA241: 140.9 | AB241: 154.9 | AC241: 138.4 | AD241: 140.2 | AE241: 145 | AF241: =SUM($E241:$Q241) -> 1846.5 | AG241: =SUM($S241:$U241) -> 437.6 | AH241: =SUM(V241,X241,AB241) -> 451 | AI241: =SUM(Y241,AC241) -> 286.9 | AJ241: =SUM(W241,Z241) -> 264.3 | AK241: =SUM(R241,AA241,AD241) -> 446.9
... A262: Rural+Urban | B262: 2020 | C262: March | D262: =B262&" "&C262 -> 2020 March | E262: 145.1 | F262: 167 | G262: 148.1 | H262: 151.5 | I262: 131.2 | J262: 142.5 | K262: 157.3 | L262: 141.1 | M262: 113.2 | N262: 153.2 | O262: 136.7 | P262: 159.6 | Q262: 148.9 | R262: 171.2 | S262: 151.2 | T262: 141.9 | U262: 149.8 | V262: 154.5 | W262: 148.9 | X262: 146.4 | Y262: 152.3 | Z262: 129.9 | AA262: 143.7 | AB262: 156.1 | AC262: 145.2 | AD262: 143.8 | AE262: 148.6 | AF262: =SUM($E262:$Q262) -> 1895.4 | AG262: =SUM($S262:$U262) -> 442.9 | AH262: =SUM(V262,X262,AB262) -> 457 | AI262: =SUM(Y262,AC262) -> 297.5 | AJ262: =SUM(W262,Z262) -> 278.8 | AK262: =SUM(R262,AA262,AD262) -> 458.7
A263: Rural | B263: 2020 | C263: April | D263: =B263&" "&C263 -> 2020 April | E263: 147.2 | F263: =AVERAGE(F260,F257,F254) -> 167.2 | G263: 146.9 | H263: 155.6 | I263: 137.1 | J263: 147.3 | K263: 162.7 | L263: 150.2 | M263: 119.8 | N263: 158.7 | O263: 139.2 | P263: =AVERAGE(P260,P257,P254) -> 159.3 | Q263: 150.1 | R263: =AVERAGE(R260,R257,R254) -> 169.5 | S263: =AVERAGE(S260,S257,S254) -> 153.06667 | T263: =AVERAGE(T260,T257,T254) -> 147.5 | U263: =AVERAGE(U260,U257,U254) -> 152.3 | V263: 155.6 | W263: 148.4 | X263: =AVERAGE(X260,X257,X254) -> 151.66667 | Y263: 154.3 | Z263: =AVERAGE(Z260,Z257,Z254) -> 136.03333 | AA263: =AVERAGE(AA260,AA257,AA254) -> 150.56667 | AB263: =AVERAGE(AB260,AB257,AB254) -> 161.6 | AC263: =AVERAGE(AC260,AC257,AC254) -> 143.66667 | AD263: =AVERAGE(AD260,AD257,AD254) -> 148.36667 | AE263: =AVERAGE(AE260,AE257,AE254) -> 150.7 | AF263: =SUM($E263:$Q263) -> 1941.3 | AG263: =SUM($S263:$U263) -> 452.86667 | AH263: =SUM(V263,X263,AB263) -> 468.86667 | AI263: =SUM(Y263,AC263) -> 297.96667 | AJ263: =SUM(W263,Z263) -> 284.43333 | AK263: =SUM(R263,AA263,AD263) -> 468.43333
A264: Urban | B264: 2020 | C264: April | D264: =B264&" "&C264 -> 2020 April | E264: 151.8 | F264: =AVERAGE(F261,F258,F255) -> 167.56667 | G264: 151.9 | H264: 155.5 | I264: 131.6 | J264: 152.9 | K264: 180 | L264: 150.8 | M264: 121.2 | N264: 154 | O264: 133.5 | P264: =AVERAGE(P261,P258,P255) -> 158.86667 | Q264: 153.5 | R264: =AVERAGE(R261,R258,R255) -> 172.03333 | S264: =AVERAGE(S261,S258,S255) -> 147.33333 | T264: =AVERAGE(T261,T258,T255) -> 133.5 | U264: =AVERAGE(U261,U258,U255) -> 145.23333 | V264: 155.6 | W264: 137.1 | X264: =AVERAGE(X261,X258,X255) -> 140.43333 | Y264: 144.8 | Z264: =AVERAGE(Z261,Z258,Z255) -> 125.3 | AA264: =AVERAGE(AA261,AA258,AA255) -> 137.6 | AB264: =AVERAGE(AB261,AB258,AB255) -> 152.26667 | AC264: =AVERAGE(AC261,AC258,AC255) -> 143.63333 | AD264: =AVERAGE(AD261,AD258,AD255) -> 138.5 | AE264: =AVERAGE(AE261,AE258,AE255) -> 147.73333 | AF264: =SUM($E264:$Q264) -> 1963.1333 | AG264: =SUM($S264:$U264) -> 426.06667 | AH264: =SUM(V264,X264,AB264) -> 448.3 | AI264: =SUM(Y264,AC264) -> 288.43333 | AJ264: =SUM(W264,Z264) -> 262.4 | AK264: =SUM(R264,AA264,AD264) -> 448.13333
A265: Rural+Urban | B265: 2020 | C265: April | D265: =B265&" "&C265 -> 2020 April | E265: 148.7 | F265: =AVERAGE(F262,F259,F256) -> 167.3 | G265: 148.8 | H265: 155.6 | I265: 135.1 | J265: 149.9 | K265: 168.6 | L265: 150.4 | M265: 120.3 | N265: 157.1 | O265: 136.8 | P265: =AVERAGE(P262,P259,P256) -> 159.1 | Q265: 151.4 | R265: =AVERAGE(R262,R259,R256) -> 170.16667 | S265: =AVERAGE(S262,S259,S256) -> 150.83333 | T265: =AVERAGE(T262,T259,T256) -> 141.7 | U265: =AVERAGE(U262,U259,U256) -> 149.5 | V265: 155.6 | W265: 144.1 | X265: =AVERAGE(X262,X259,X256) -> 146.33333 | Y265: 150.7 | Z265: =AVERAGE(Z262,Z259,Z256) -> 130.36667 | AA265: =AVERAGE(AA262,AA259,AA256) -> 143.23333 | AB265: =AVERAGE(AB262,AB259,AB256) -> 156.13333 | AC265: =AVERAGE(AC262,AC259,AC256) -> 143.63333 | AD265: =AVERAGE(AD262,AD259,AD256) -> 143.6 | AE265: =AVERAGE(AE262,AE259,AE256) -> 149.3 | AF265: =SUM($E265:$Q265) -> 1949.1 | AG265: =SUM($S265:$U265) -> 442.03333 | AH265: =SUM(V265,X265,AB265) -> 458.06667 | AI265: =SUM(Y265,AC265) -> 294.33333 | AJ265: =SUM(W265,Z265) -> 274.46667 | AK265: =SUM(R265,AA265,AD265) -> 457
A266: Rural | B266: 2020 | C266: May | D266: =B266&" "&C266 -> 2020 May | E266: =AVERAGE(E263,E260,E257) -> 145.26667 | F266: =AVERAGE(F263,F260,F257) -> 167.16667 | G266: =AVERAGE(G263,G260,G257) -> 148.46667 | H266: =AVERAGE(H263,H260,H257) -> 152.73333 | I266: =AVERAGE(I263,I260,I257) -> 134.7 | J266: =AVERAGE(J263,J260,J257) -> 143.26667 | K266: =AVERAGE(K263,K260,K257) -> 160.03333 | L266: =AVERAGE(L263,L260,L257) -> 144.6 | ... U266: =AVERAGE(U263,U260,U257) -> 152.36667 | V266: 155.6 | W266: =AVERAGE(W265,W264,W263) -> 143.2 | X266: =AVERAGE(X263,X260,X257) -> 151.65556 | Y266: =AVERAGE(Y263,Y260,Y257) -> 155.73333 | Z266: =AVERAGE(Z263,Z260,Z257) -> 135.94444 | AA266: =AVERAGE(AA263,AA260,AA257) -> 150.72222 | AB266: =AVERAGE(AB263,AB260,AB257) -> 161.56667 | AC266: =AVERAGE(AC263,AC260,AC257) -> 144.05556 | AD266: =AVERAGE(AD263,AD260,AD257) -> 148.45556 | AE266: =AVERAGE(AE263,AE260,AE257) -> 150.3 | AF266: =SUM($E266:$Q266) -> 1915.2333 | AG266: =SUM($S266:$U266) -> 453.05556 | AH266: =SUM(V266,X266,AB266) -> 468.82222 | AI266: =SUM(Y266,AC266) -> 299.78889 | AJ266: =SUM(W266,Z266) -> 279.14444 | AK266: =SUM(R266,AA266,AD266) -> 468.97778
A267: Urban | B267: 2020 | C267: May | D267: =B267&" "&C267 -> 2020 May | E267: =AVERAGE(E264,E261,E258) -> 148.16667 | F267: =AVERAGE(F264,F261,F258) -> 167.55556 | G267: =AVERAGE(G264,G261,G258) -> 151.3 | H267: =AVERAGE(H264,H261,H258) -> 152.43333 | I267: =AVERAGE(I264,I261,I258) -> 128.83333 | J267: =AVERAGE(J264,J261,J258) -> 146.43333 | K267: =AVERAGE(K264,K261,K258) -> 176.23333 | L267: =AVERAGE(L264,L261,L258) -> 143.36667 | ... U267: =AVERAGE(U264,U261,U258) -> 145.34444 | V267: 155.6 | W267: =AVERAGE(W264,W261,W258) -> 139.13333 | X267: =AVERAGE(X264,X261,X258) -> 140.54444 | Y267: =AVERAGE(Y264,Y261,Y258) -> 144.73333 | Z267: =AVERAGE(Z264,Z261,Z258) -> 125.03333 | AA267: =AVERAGE(AA264,AA261,AA258) -> 137.73333 | AB267: =AVERAGE(AB264,AB261,AB258) -> 152.32222 | AC267: =AVERAGE(AC264,AC261,AC258) -> 144.14444 | AD267: =AVERAGE(AD264,AD261,AD258) -> 138.53333 | AE267: =AVERAGE(AE264,AE261,AE258) -> 147.57778 | AF267: =SUM($E267:$Q267) -> 1926.0778 | AG267: =SUM($S267:$U267) -> 426.38889 | AH267: =SUM(V267,X267,AB267) -> 448.46667 | AI267: =SUM(Y267,AC267) -> 288.87778 | AJ267: =SUM(W267,Z267) -> 264.16667 | AK267: =SUM(R267,AA267,AD267) -> 448.71111
A268: Rural+Urban | B268: 2020 | C268: May | D268: =B268&" "&C268 -> 2020 May | E268: =AVERAGE(E265,E262,E259) -> 146.2 | F268: =AVERAGE(F265,F262,F259) -> 167.26667 | G268: =AVERAGE(G265,G262,G259) -> 149.56667 | H268: =AVERAGE(H265,H262,H259) -> 152.63333 | I268: =AVERAGE(I265,I262,I259) -> 132.56667 | J268: =AVERAGE(J265,J262,J259) -> 144.73333 | K268: =AVERAGE(K265,K262,K259) -> 165.53333 | L268: =AVERAGE(L265,L262,L259) -> 144.2 | ... U268: =AVERAGE(U265,U262,U259) -> 149.6 | V268: 154.96667 | W268: =AVERAGE(W265,W262,W259) -> 146.73333 | X268: =AVERAGE(X265,X262,X259) -> 146.37778 | Y268: =AVERAGE(Y265,Y262,Y259) -> 151.56667 | Z268: =AVERAGE(Z265,Z262,Z259) -> 130.18889 | AA268: =AVERAGE(AA265,AA262,AA259) -> 143.37778 | AB268: =AVERAGE(AB265,AB262,AB259) -> 156.14444 | AC268: =AVERAGE(AC265,AC262,AC259) -> 144.07778 | AD268: =AVERAGE(AD265,AD262,AD259) -> 143.66667 | AE268: =AVERAGE(AE265,AE262,AE259) -> 149 | AF268: =SUM($E268:$Q268) -> 1918.7 | AG268: =SUM($S268:$U268) -> 442.31111 | AH268: =SUM(V268,X268,AB268) -> 457.48889 | AI268: =SUM(Y268,AC268) -> 295.64444 | AJ268: =SUM(W268,Z268) -> 276.92222 | AK268: =SUM(R268,AA268,AD268) -> 457.53333
A269: Rural | B269: 2020 | C269: June | D269: =B269&" "&C269 -> 2020 June | E269: 148.2 | F269: 190.3 | G269: 149.4 | H269: 153.3 | I269: 138.2 | J269: 143.2 | K269: 148.9 | L269: 150.3 | M269: 113.2 | N269: 159.8 | O269: 142.1 | P269: 161.8 | Q269: 152.3 | R269: 182.4 | S269: 154.7 | T269: 150 | U269: 154.1 | V269: 154.7 | W269: 144.9 | X269: 151.7 | Y269: 158.2 | Z269: 141.4 | AA269: 153.2 | AB269: 161.8 | AC269: 151.2 | AD269: 151.7 | AE269: 152.7 | AF269: =SUM($E269:$Q269) -> 1951 | AG269: =SUM($S269:$U269) -> 458.8 | AH269: =SUM(V269,X269,AB269) -> 468.2 | AI269: =SUM(Y269,AC269) -> 309.4 | AJ269: =SUM(W269,Z269) -> 286.3 | AK269: =SUM(R269,AA269,AD269) -> 487.3
A270: Urban | B270: 2020 | C270: June | D270: =B270&" "&C270 -> 2020 June | E270: 152.7 | F270: 197 | G270: 154.6 | H270: 153.4 | I270: 132.9 | J270: 151.8 | K270: 171.2 | L270: 152 | M270: 116.3 | N270: 158.8 | O270: 135.6 | P270: 161.7 | Q270: 157 | R270: 186.7 | S270: 149.1 | T270: 136.6 | U270: 147.2 | V270: 154.7 | W270: 137.1 | X270: 140.4 | Y270: 148.1 | Z270: 129.3 | AA270: 144.5 | AB270: 152.5 | AC270: 152.2 | AD270: 142 | AE270: 150.8 | AF270: =SUM($E270:$Q270) -> 1995 | AG270: =SUM($S270:$U270) -> 432.9 | AH270: =SUM(V270,X270,AB270) -> 447.6 | AI270: =SUM(Y270,AC270) -> 300.3 | AJ270: =SUM(W270,Z270) -> 266.4 | AK270: =SUM(R270,AA270,AD270) -> 473.2
A271: Rural+Urban | B271: 2020 | C271: June | D271: =B271&" "&C271 -> 2020 June | E271: 149.6 | F271: 192.7 | G271: 151.4 | H271: 153.3 | I271: 136.3 | J271: 147.2 | K271: 156.5 | L271: 150.9 | M271: 114.2 | N271: 159.5 | O271: 139.4 | P271: 161.8 | Q271: 154 | R271: 183.5 | S271: 152.5 | T271: 144.4 | U271: 151.4 | V271: 154.7 | W271: 141.9 | X271: 146.4 | Y271: 154.4 | Z271: 135 | AA271: 148.3 | AB271: 156.4 | AC271: 151.6 | AD271: 147 | AE271: 151.8 | AF271: =SUM($E271:$Q271) -> 1966.8 | AG271: =SUM($S271:$U271) -> 448.3 | AH271: =SUM(V271,X271,AB271) -> 457.5 | AI271: =SUM(Y271,AC271) -> 306 | AJ271: =SUM(W271,Z271) -> 276.9 | AK271: =SUM(R271,AA271,AD271) -> 478.8
A272: Rural | B272: 2020 | C272: July | D272: =B272&" "&C272 -> 2020 July | E272: 148.2 | F272: 190.3 | G272: 149.4 | H272: 153.3 | I272: 138.2 | J272: 143.2 | K272: 148.9 | L272: 150.3 | M272: 113.2 | N272: 159.8 | O272: 142.1 | P272: 161.8 | Q272: 152.3 | R272: 182.4 | S272: 154.7 | T272: 150 | U272: 154.1 | V272: 154.7 | W272: 144.9 | X272: 151.7 | Y272: 158.2 | Z272: 141.4 | AA272: 153.2 | AB272: 161.8 | AC272: 151.2 | AD272: 151.7 | AE272: 152.7 | AF272: =SUM($E272:$Q272) -> 1951 | AG272: =SUM($S272:$U272) -> 458.8 | AH272: =SUM(V272,X272,AB272) -> 468.2 | AI272: =SUM(Y272,AC272) -> 309.4 | AJ272: =SUM(W272,Z272) -> 286.3 | AK272: =SUM(R272,AA272,AD272) -> 487.3
A273: Urban | B273: 2020 | C273: July | D273: =B273&" "&C273 -> 2020 July | E273: 152.7 | F273: 197 | G273: 154.6 | H273: 153.4 | I273: 132.9 | J273: 151.8 | K273: 171.2 | L273: 152 | M273: 116.3 | N273: 158.8 | O273: 135.6 | P273: 161.7 | Q273: 157 | R273: 186.7 | S273: 149.1 | T273: 136.6 | U273: 147.2 | V273: 154.7 | W273: 137.1 | X273: 140.4 | Y273: 148.1 | Z273: 129.3 | AA273: 144.5 | AB273: 152.5 | AC273: 152.2 | AD273: 142 | AE273: 150.8 | AF273: =SUM($E273:$Q273) -> 1995 | AG273: =SUM($S273:$U273) -> 432.9 | AH273: =SUM(V273,X273,AB273) -> 447.6 | AI273: =SUM(Y273,AC273) -> 300.3 | AJ273: =SUM(W273,Z273) -> 266.4 | AK273: =SUM(R273,AA273,AD273) -> 473.2
A274: Rural+Urban | B274: 2020 | C274: July | D274: =B274&" "&C274 -> 2020 July | E274: 149.6 | F274: 192.7 | G274: 151.4 | H274: 153.3 | I274: 136.3 | J274: 147.2 | K274: 156.5 | L274: 150.9 | M274: 114.2 | N274: 159.5 | O274: 139.4 | P274: 161.8 | Q274: 154 | R274: 183.5 | S274: 152.5 | T274: 144.4 | U274: 151.4 | V274: 154.7 | W274: 141.9 | X274: 146.4 | Y274: 154.4 | Z274: 135 | AA274: 148.3 | AB274: 156.4 | AC274: 151.6 | AD274: 147 | AE274: 151.8 | AF274: =SUM($E274:$Q274) -> 1966.8 | AG274: =SUM($S274:$U274) -> 448.3 | AH274: =SUM(V274,X274,AB274) -> 457.5 | AI274: =SUM(Y274,AC274) -> 306 | AJ274: =SUM(W274,Z274) -> 276.9 | AK274: =SUM(R274,AA274,AD274) -> 478.8
A275: Rural | B275: 2020 | C275: August | D275: =B275&" "&C275 -> 2020 August | E275: 147.6 | F275: 187.2 | G275: 148.4 | H275: 153.3 | I275: 139.8 | J275: 146.9 | K275: 171 | L275: 149.9 | M275: 114.2 | N275: 160 | O275: 143.5 | P275: 161.5 | Q275: 155.3 | R275: 180.9 | S275: 155.1 | T275: 149.3 | U275: 154.3 | V275: 155.5 | W275: 145.8 | X275: 151.9 | Y275: 158.8 | Z275: 143.6 | AA275: 152.2 | AB275: 162.7 | AC275: 153.6 | AD275: 153 | AE275: 154.7 | AF275: =SUM($E275:$Q275) -> 1978.6 | AG275: =SUM($S275:$U275) -> 458.7 | AH275: =SUM(V275,X275,AB275) -> 470.1 | AI275: =SUM(Y275,AC275) -> 312.4 | AJ275: =SUM(W275,Z275) -> 289.4 | AK275: =SUM(R275,AA275,AD275) -> 486.1
A276: Urban | B276: 2020 | C276: August | D276: =B276&" "&C276 -> 2020 August | E276: 151.6 | F276: 197.8 | G276: 154.5 | H276: 153.4 | I276: 133.4 | J276: 154.5 | K276: 191.9 | L276: 151.3 | M276: 116.8 | N276: 160 | O276: 136.5 | P276: 163.3 | Q276: 159.9 | R276: 187.2 | S276: 150 | T276: 135.2 | U276: 147.8 | V276: 155.5 | W276: 138.3 | X276: 144.5 | Y276: 148.7 | Z276: 133.9 | AA276: 141.2 | AB276: 155.5 | AC276: 155.2 | AD276: 144.8 | AE276: 152.9 | AF276: =SUM($E276:$Q276) -> 2024.9 | AG276: =SUM($S276:$U276) -> 433 | AH276: =SUM(V276,X276,AB276) -> 455.5 | AI276: =SUM(Y276,AC276) -> 303.9 | AJ276: =SUM(W276,Z276) -> 272.2 | AK276: =SUM(R276,AA276,AD276) -> 473.2
A277: Rural+Urban | B277: 2020 | C277: August | D277: =B277&" "&C277 -> 2020 August | E277: 148.9 | F277: 190.9 | G277: 150.8 | H277: 153.3 | I277: 137.4 | J277: 150.4 | K277: 178.1 | L277: 150.4 | M277: 115.1 | N277: 160 | O277: 140.6 | P277: 162.3 | Q277: 157 | R277: 182.6 | S277: 153.1 | T277: 143.4 | U277: 151.7 | V277: 155.5 | W277: 143 | X277: 148.4 | Y277: 155 | Z277: 138.5 | AA277: 146 | AB277: 158.5 | AC277: 154.3 | AD277: 149 | AE277: 153.9 | AF277: =SUM($E277:$Q277) -> 1995.2 | AG277: =SUM($S277:$U277) -> 448.2 | AH277: =SUM(V277,X277,AB277) -> 462.4 | AI277: =SUM(Y277,AC277) -> 309.3 | AJ277: =SUM(W277,Z277) -> 281.5 | AK277: =SUM(R277,AA277,AD277) -> 477.6
A278: Rural | B278: 2020 | C278: September | D278: =B278&" "&C278 -> 2020 September | E278: 146.9 | F278: 183.9 | G278: 149.5 | H278: 153.4 | I278: 140.4 | J278: 147 | K278: 178.8 | L278: 149.3 | M278: 115.1 | N278: 160 | O278: 145.4 | P278: 161.6 | Q278: 156.1 | R278: 182.9 | S278: 155.4 | T278: 149.9 | U278: 154.6 | V278: 156.3 | W278: 146.4 | X278: 151.6 | Y278: 159.1 | Z278: 144.6 | AA278: 152.8 | AB278: 161.1 | AC278: 157.4 | AD278: 153.7 | AE278: 155.4 | AF278: =SUM($E278:$Q278) -> 1987.4 | AG278: =SUM($S278:$U278) -> 459.9 | AH278: =SUM(V278,X278,AB278) -> 469 | AI278: =SUM(Y278,AC278) -> 316.5 | AJ278: =SUM(W278,Z278) -> 291 | AK278: =SUM(R278,AA278,AD278) -> 489.4
A279: Urban | B279: 2020 | C279: September | D279: =B279&" "&C279 -> 2020 September | E279: 151.5 | F279: 193.1 | G279: 157.3 | H279: 153.9 | I279: 134.4 | J279: 155.4 | K279: 202 | L279: 150.8 | M279: 118.9 | N279: 160.9 | O279: 137.7 | P279: 164.4 | Q279: 161.3 | R279: 188.7 | S279: 150.2 | T279: 136.3 | U279: 148.1 | V279: 156.3 | W279: 137.2 | X279: 145.4 | Y279: 150 | Z279: 135.1 | AA279: 141.8 | AB279: 154.9 | AC279: 159.8 | AD279: 146 | AE279: 154 | AF279: =SUM($E279:$Q279) -> 2041.6 | AG279: =SUM($S279:$U279) -> 434.6 | AH279: =SUM(V279,X279,AB279) -> 456.6 | AI279: =SUM(Y279,AC279) -> 309.8 | AJ279: =SUM(W279,Z279) -> 272.3 | AK279: =SUM(R279,AA279,AD279) -> 476.5
A280: Rural+Urban | B280: 2020 | C280: September | D280: =B280&" "&C280 -> 2020 September | E280: 148.4 | F280: 187.1 | G280: 152.5 | H280: 153.6 | I280: 138.2 | J280: 150.9 | K280: 186.7 | L280: 149.8 | M280: 116.4 | N280: 160.3 | O280: 142.2 | P280: 162.9 | Q280: 158 | R280: 184.4 | S280: 153.4 | T280: 144.3 | U280: 152 | V280: 156.3 | W280: 142.9 | X280: 148.7 | Y280: 155.6 | Z280: 139.6 | AA280: 146.6 | AB280: 157.5 | AC280: 158.4 | AD280: 150 | AE280: 154.7 | AF280: =SUM($E280:$Q280) -> 2007 | AG280: =SUM($S280:$U280) -> 449.7 | AH280: =SUM(V280,X280,AB280) -> 462.5 | AI280: =SUM(Y280,AC280) -> 314 | AJ280: =SUM(W280,Z280) -> 282.5 | AK280: =SUM(R280,AA280,AD280) -> 481
... A376: Rural+Urban | B376: 2023 | C376: May | D376: =B376&" "&C376 -> 2023 May | E376: 173.7 | F376: 214.3 | G376: 173.2 | H376: 179.5 | I376: 170 | J376: 172.2 | K376: 161 | L376: 175.6 | M376: 122.7 | N376: 218 | O376: 173.4 | P376: 194.2 | Q376: 179.1 | R376: 201 | S376: 187.3 | T376: 179.7 | U376: 186.2 | V376: 175.6 | W376: 182.8 | X376: 175.2 | Y376: 185.7 | Z376: 164.8 | AA376: 171.2 | AB376: 177.1 | AC376: 185.2 | AD376: 175.7 | AE376: 179.1 | AF376: =SUM($E376:$Q376) -> 2306.9 | AG376: =SUM($S376:$U376) -> 553.2 | AH376: =SUM(V376,X376,AB376) -> 527.9 | AI376: =SUM(Y376,AC376) -> 370.9 | AJ376: =SUM(W376,Z376) -> 347.6 | AK376: =SUM(R376,AA376,AD376) -> 547.9

Sheet 1. Broder_Cat _Contribution
B1: 1. Highest Contribution of Different Broader Categories Towards The CPI Basket
B3: Contribution of Broader Categories Based On Month
B4: Sector | C4: Year | D4: Month | E4: Food | F4: Clothing | G4: Essential | H4: Health | I4: Energy | J4: Lux
B5: Rural | C5: 2023 | D5: May | E5: {=INDEX('CPI Data'!AF:AF,MATCH(1,('CPI Data'!$A:$A=$B5)*('CPI Data'!$B:$B=$C5)*('CPI Data'!$C:$C=$D5),0))} -> 2290.7 | F5: {=INDEX('CPI Data'!AG:AG,MATCH(1,('CPI Data'!$A:$A=$B5)*('CPI Data'!$B:$B=$C5)*('CPI Data'!$C:$C=$D5),0))} -> 569.9 | G5: {=INDEX('CPI Data'!AH:AH,MATCH(1,('CPI Data'!$A:$A=$B5)*('CPI Data'!$B:$B=$C5)*('CPI Data'!$C:$C=$D5),0))} -> 535.7 | H5: {=INDEX('CPI Data'!AI:AI,MATCH(1,('CPI Data'!$A:$A=$B5)*('CPI Data'!$B:$B=$C5)*('CPI Data'!$C:$C=$D5),0))} -> 372.7 | I5: {=INDEX('CPI Data'!AJ:AJ,MATCH(1,('CPI Data'!$A:$A=$B5)*('CPI Data'!$B:$B=$C5)*('CPI Data'!$C:$C=$D5),0))} -> 352.2 | J5: {=INDEX('CPI Data'!AK:AK,MATCH(1,('CPI Data'!$A:$A=$B5)*('CPI Data'!$B:$B=$C5)*('CPI Data'!$C:$C=$D5),0))} -> 553.2
B6: Urban | C6: 2023 | D6: May | E6: {=INDEX('CPI Data'!AF:AF,MATCH(1,('CPI Data'!$A:$A=$B6)*('CPI Data'!$B:$B=$C6)*('CPI Data'!$C:$C=$D6),0))} -> 2335.1 | F6: {=INDEX('CPI Data'!AG:AG,MATCH(1,('CPI Data'!$A:$A=$B6)*('CPI Data'!$B:$B=$C6)*('CPI Data'!$C:$C=$D6),0))} -> 528.7 | G6: {=INDEX('CPI Data'!AH:AH,MATCH(1,('CPI Data'!$A:$A=$B6)*('CPI Data'!$B:$B=$C6)*('CPI Data'!$C:$C=$D6),0))} -> 520.5 | H6: {=INDEX('CPI Data'!AI:AI,MATCH(1,('CPI Data'!$A:$A=$B6)*('CPI Data'!$B:$B=$C6)*('CPI Data'!$C:$C=$D6),0))} -> 367.8 | I6: {=INDEX('CPI Data'!AJ:AJ,MATCH(1,('CPI Data'!$A:$A=$B6)*('CPI Data'!$B:$B=$C6)*('CPI Data'!$C:$C=$D6),0))} -> 343.8 | J6: {=INDEX('CPI Data'!AK:AK,MATCH(1,('CPI Data'!$A:$A=$B6)*('CPI Data'!$B:$B=$C6)*('CPI Data'!$C:$C=$D6),0))} -> 545
B7: Rural+Urban | C7: 2023 | D7: May | E7: {=INDEX('CPI Data'!AF:AF,MATCH(1,('CPI Data'!$A:$A=$B7)*('CPI Data'!$B:$B=$C7)*('CPI Data'!$C:$C=$D7),0))} -> 2306.9 | F7: {=INDEX('CPI Data'!AG:AG,MATCH(1,('CPI Data'!$A:$A=$B7)*('CPI Data'!$B:$B=$C7)*('CPI Data'!$C:$C=$D7),0))} -> 553.2 | G7: {=INDEX('CPI Data'!AH:AH,MATCH(1,('CPI Data'!$A:$A=$B7)*('CPI Data'!$B:$B=$C7)*('CPI Data'!$C:$C=$D7),0))} -> 527.9 | H7: {=INDEX('CPI Data'!AI:AI,MATCH(1,('CPI Data'!$A:$A=$B7)*('CPI Data'!$B:$B=$C7)*('CPI Data'!$C:$C=$D7),0))} -> 370.9 | I7: {=INDEX('CPI Data'!AJ:AJ,MATCH(1,('CPI Data'!$A:$A=$B7)*('CPI Data'!$B:$B=$C7)*('CPI Data'!$C:$C=$D7),0))} -> 347.6 | J7: {=INDEX('CPI Data'!AK:AK,MATCH(1,('CPI Data'!$A:$A=$B7)*('CPI Data'!$B:$B=$C7)*('CPI Data'!$C:$C=$D7),0))} -> 547.9
C8: CPI Total | E8: =SUM(E5:E7) -> 6932.7 | F8: =SUM(F5:F7) -> 1651.8 | G8: =SUM(G5:G7) -> 1584.1 | H8: =SUM(H5:H7) -> 1111.4 | I8: =SUM(I5:I7) -> 1043.6 | J8: =SUM(J5:J7) -> 1646.1
C9: Inflation Rate% | E9: =E8/SUM($E$8:$J$8) -> 0.49626692 | F9: =F8/SUM($E$8:$J$8) -> 0.11824162 | G9: =G8/SUM($E$8:$J$8) -> 0.11339542 | H9: =H8/SUM($E$8:$J$8) -> 0.0795579 | I9: =I8/SUM($E$8:$J$8) -> 0.074704539 | J9: =J8/SUM($E$8:$J$8) -> 0.1178336
B11: Rural+Urban | C11: 2023 | D11: May
B12: Broader Categories and Their Contributions(May 2023)
B13: CPI Category | C13: CPI Value | D13: Contribution Rate %
B14: Food | C14: {=INDEX('CPI Data'!AF:AF,MATCH(1,('CPI Data'!$A:$A=$B$11)*('CPI Data'!$B:$B=$C$11)*('CPI Data'!$C:$C=$D$11),0))} -> 2306.9 | D14: =(C14/SUM($C$14:$C$19)) -> 0.49563854
B15: Clothing | C15: {=INDEX('CPI Data'!AG:AG,MATCH(1,('CPI Data'!$A:$A=B11)*('CPI Data'!$B:$B=C11)*('CPI Data'!$C:$C=D11),0))} -> 553.2 | D15: =(C15/SUM($C$14:$C$19)) -> 0.11885528
B16: Essential | C16: {=INDEX('CPI Data'!AH:AH,MATCH(1,('CPI Data'!$A:$A=B11)*('CPI Data'!$B:$B=C11)*('CPI Data'!$C:$C=D11),0))} -> 527.9 | D16: =(C16/SUM($C$14:$C$19)) -> 0.11341956
B17: Health | C17: {=INDEX('CPI Data'!AI:AI,MATCH(1,('CPI Data'!$A:$A=B11)*('CPI Data'!$B:$B=C11)*('CPI Data'!$C:$C=D11),0))} -> 370.9 | D17: =(C17/SUM($C$14:$C$19)) -> 0.079688037
B18: Energy | C18: {=INDEX('CPI Data'!AJ:AJ,MATCH(1,('CPI Data'!$A:$A=B11)*('CPI Data'!$B:$B=C11)*('CPI Data'!$C:$C=D11),0))} -> 347.6 | D18: =(C18/SUM($C$14:$C$19)) -> 0.074682021
B19: Luxury | C19: {=INDEX('CPI Data'!AK:AK,MATCH(1,('CPI Data'!$A:$A=B11)*('CPI Data'!$B:$B=C11)*('CPI Data'!$C:$C=D11),0))} -> 547.9 | D19: =(C19/SUM($C$14:$C$19)) -> 0.11771657
B20: Total | C20: =SUM(C14:C19) -> 4654.4 | D20: =SUM(D14:D19) -> 1
B23: Broader Categories and Their Contributions (May 2023)
B24: CPI Category | C24: Rural Contribution (%) | D24: Urban Contribution (%) | E24: Rural + Urban Contribution (%)
B25: Food | C25: 0.4900522 | D25: 0.50315672 | E25: 0.49563854
B26: Clothing | C26: 0.12191939 | D26: 0.11392187 | E26: 0.11885528
B27: Essential | C27: 0.11460294 | D27: 0.11215497 | E27: 0.11341956
B28: Health | C28: 0.079732158 | D28: 0.079251869 | E28: 0.079688037
B29: Energy | C29: 0.075346569 | D29: 0.074080459 | E29: 0.074682021
B30: Luxury | C30: 0.11834674 | D30: 0.11743412 | E30: 0.11771657
B31: Total | C31: 1 | D31: 1 | E31: 1
B34: Interpretation & Analysis
B35: Food is the dominant contributor (≈50%), making it the single largest driver of overall inflation.
B36: Clothing (~12%) and Essentials (~11%) follow as major spending categories across households.
B37: Health (~8%) and Energy (~7%) contribute moderately, indicating stable but smaller inflationary impact.
B38: Luxury goods (~12%) show significant spending, reflecting shifting lifestyle and rising disposable incomes.
B39: Rural and Urban patterns remain similar, with food dominating both regions.
B41: Insights
B42: Food inflation has the strongest influence on total CPI — stabilizing food supply chains should be a priority.
B43: Uniform rural–urban spending trends enable consistent nationwide inflation-control strategies.
B44: Health and energy categories are less volatile, contributing to CPI stability.
B45: Luxury spending in rural areas signals improving income levels and evolving consumption behaviour.

Sheet 2. Inflation & Deflation Rate
A1: 2. YOY INCREASE IN CPI (Rural + Urban) INFLATION FROM 2017 to 2023 FOR THE ENTIRE BASKET
B4: Calcuated YOY increment growth by Urban+Rural
B5: Sector | C5: Year | D5: January | E5: December | F5: Y-O-Y %
B6: Rural+Urban | C6: 2017 | D6: =AVERAGEIFS('CPI Data'!$AE:$AE,'CPI Data'!$B:$B,'2. Inflation & Deflation Rate'!$C6,'CPI Data'!$C:$C,'2. Inflation & Deflation Rate'!$D$5,'CPI Data'!$A:$A,'2. Inflation & Deflation Rate'!$B$6) -> 130.3 | E6: =AVERAGEIFS('CPI Data'!$AE:$AE,'CPI Data'!$B:$B,'2. Inflation & Deflation Rate'!$C6,'CPI Data'!$C:$C,'2. Inflation & Deflation Rate'!$E$5,'CPI Data'!$A:$A,'2. Inflation & Deflation Rate'!$B$6) -> 137.2 | F6: =(E6-D6)/D6 -> 0.05295472
C7: 2018 | D7: =AVERAGEIFS('CPI Data'!$AE:$AE,'CPI Data'!$B:$B,'2. Inflation & Deflation Rate'!$C7,'CPI Data'!$C:$C,'2. Inflation & Deflation Rate'!$D$5,'CPI Data'!$A:$A,'2. Inflation & Deflation Rate'!$B$6) -> 136.9 | E7: =AVERAGEIFS('CPI Data'!$AE:$AE,'CPI Data'!$B:$B,'2. Inflation & Deflation Rate'!$C7,'CPI Data'!$C:$C,'2. Inflation & Deflation Rate'!$E$5,'CPI Data'!$A:$A,'2. Inflation & Deflation Rate'!$B$6) -> 140.1 | F7: =(E7-D7)/D7 -> 0.023374726
C8: 2019 | D8: =AVERAGEIFS('CPI Data'!$AE:$AE,'CPI Data'!$B:$B,'2. Inflation & Deflation Rate'!$C8,'CPI Data'!$C:$C,'2. Inflation & Deflation Rate'!$D$5,'CPI Data'!$A:$A,'2. Inflation & Deflation Rate'!$B$6) -> 139.6 | E8: =AVERAGEIFS('CPI Data'!$AE:$AE,'CPI Data'!$B:$B,'2. Inflation & Deflation Rate'!$C8,'CPI Data'!$C:$C,'2. Inflation & Deflation Rate'!$E$5,'CPI Data'!$A:$A,'2. Inflation & Deflation Rate'!$B$6) -> 150.4 | F8: =(E8-D8)/D8 -> 0.077363897
C9: 2020 | D9: =AVERAGEIFS('CPI Data'!$AE:$AE,'CPI Data'!$B:$B,'2. Inflation & Deflation Rate'!$C9,'CPI Data'!$C:$C,'2. Inflation & Deflation Rate'!$D$5,'CPI Data'!$A:$A,'2. Inflation & Deflation Rate'!$B$6) -> 150.2 | E9: =AVERAGEIFS('CPI Data'!$AE:$AE,'CPI Data'!$B:$B,'2. Inflation & Deflation Rate'!$C9,'CPI Data'!$C:$C,'2. Inflation & Deflation Rate'!$E$5,'CPI Data'!$A:$A,'2. Inflation & Deflation Rate'!$B$6) -> 158.9 | F9: =(E9-D9)/D9 -> 0.05792277
C10: 2021 | D10: =AVERAGEIFS('CPI Data'!$AE:$AE,'CPI Data'!$B:$B,'2. Inflation & Deflation Rate'!$C10,'CPI Data'!$C:$C,'2. Inflation & Deflation Rate'!$D$5,'CPI Data'!$A:$A,'2. Inflation & Deflation Rate'!$B$6) -> 157.3 | E10: =AVERAGEIFS('CPI Data'!$AE:$AE,'CPI Data'!$B:$B,'2. Inflation & Deflation Rate'!$C10,'CPI Data'!$C:$C,'2. Inflation & Deflation Rate'!$E$5,'CPI Data'!$A:$A,'2. Inflation & Deflation Rate'!$B$6) -> 166.2 | F10: =(E10-D10)/D10 -> 0.056579784
C11: 2022 | D11: =AVERAGEIFS('CPI Data'!$AE:$AE,'CPI Data'!$B:$B,'2. Inflation & Deflation Rate'!$C11,'CPI Data'!$C:$C,'2. Inflation & Deflation Rate'!$D$5,'CPI Data'!$A:$A,'2. Inflation & Deflation Rate'!$B$6) -> 165.7 | E11: =AVERAGEIFS('CPI Data'!$AE:$AE,'CPI Data'!$B:$B,'2. Inflation & Deflation Rate'!$C11,'CPI Data'!$C:$C,'2. Inflation & Deflation Rate'!$E$5,'CPI Data'!$A:$A,'2. Inflation & Deflation Rate'!$B$6) -> 175.7 | F11: =(E11-D11)/D11 -> 0.06035003
B16: Broader categories wise Y-O-Y inflation
B17: Year | C17: Month | D17: Food | E17: Clothing | F17: Essential | G17: Health | H17: Energy | I17: Lux
B18: 2019 | C18: January | D18: =AVERAGEIFS('CPI Data'!AF:AF,'CPI Data'!$A:$A,'2. Inflation & Deflation Rate'!$B$6,'CPI Data'!$B:$B,'2. Inflation & Deflation Rate'!$B18,'CPI Data'!$C:$C,'2. Inflation & Deflation Rate'!$C18) -> 1753.4 | E18: =AVERAGEIFS('CPI Data'!AG:AG,'CPI Data'!$A:$A,'2. Inflation & Deflation Rate'!$B$6,'CPI Data'!$B:$B,'2. Inflation & Deflation Rate'!$B18,'CPI Data'!$C:$C,'2. Inflation & Deflation Rate'!$C18) -> 433 | F18: =AVERAGEIFS('CPI Data'!AH:AH,'CPI Data'!$A:$A,'2. Inflation & Deflation Rate'!$B$6,'CPI Data'!$B:$B,'2. Inflation & Deflation Rate'!$B18,'CPI Data'!$C:$C,'2. Inflation & Deflation Rate'!$C18) -> 441.5 | G18: =AVERAGEIFS('CPI Data'!AI:AI,'CPI Data'!$A:$A,'2. Inflation & Deflation Rate'!$B$6,'CPI Data'!$B:$B,'2. Inflation & Deflation Rate'!$B18,'CPI Data'!$C:$C,'2. Inflation & Deflation Rate'!$C18) -> 277.9 | H18: =AVERAGEIFS('CPI Data'!AJ:AJ,'CPI Data'!$A:$A,'2. Inflation & Deflation Rate'!$B$6,'CPI Data'!$B:$B,'2. Inflation & Deflation Rate'!$B18,'CPI Data'!$C:$C,'2. Inflation & Deflation Rate'!$C18) -> 262.8 | I18: =AVERAGEIFS('CPI Data'!AK:AK,'CPI Data'!$A:$A,'2. Inflation & Deflation Rate'!$B$6,'CPI Data'!$B:$B,'2. Inflation & Deflation Rate'!$B18,'CPI Data'!$C:$C,'2. Inflation & Deflation Rate'!$C18) -> 436.8
B19: 2019 | C19: December | D19: =AVERAGEIFS('CPI Data'!AF:AF,'CPI Data'!$A:$A,'2. Inflation & Deflation Rate'!$B$6,'CPI Data'!$B:$B,'2. Inflation & Deflation Rate'!$B19,'CPI Data'!$C:$C,'2. Inflation & Deflation Rate'!$C19) -> 1946.1 | E19: =AVERAGEIFS('CPI Data'!AG:AG,'CPI Data'!$A:$A,'2. Inflation & Deflation Rate'!$B$6,'CPI Data'!$B:$B,'2. Inflation & Deflation Rate'!$B19,'CPI Data'!$C:$C,'2. Inflation & Deflation Rate'!$C19) -> 440.6 | F19: =AVERAGEIFS('CPI Data'!AH:AH,'CPI Data'!$A:$A,'2. Inflation & Deflation Rate'!$B$6,'CPI Data'!$B:$B,'2. Inflation & Deflation Rate'!$B19,'CPI Data'!$C:$C,'2. Inflation & Deflation Rate'!$C19) -> 454.3 | G19: =AVERAGEIFS('CPI Data'!AI:AI,'CPI Data'!$A:$A,'2. Inflation & Deflation Rate'!$B$6,'CPI Data'!$B:$B,'2. Inflation & Deflation Rate'!$B19,'CPI Data'!$C:$C,'2. Inflation & Deflation Rate'!$C19) -> 290.8 | H19: =AVERAGEIFS('CPI Data'!AJ:AJ,'CPI Data'!$A:$A,'2. Inflation & Deflation Rate'!$B$6,'CPI Data'!$B:$B,'2. Inflation & Deflation Rate'!$B19,'CPI Data'!$C:$C,'2. Inflation & Deflation Rate'!$C19) -> 273.5 | I19: =AVERAGEIFS('CPI Data'!AK:AK,'CPI Data'!$A:$A,'2. Inflation & Deflation Rate'!$B$6,'CPI Data'!$B:$B,'2. Inflation & Deflation Rate'!$B19,'CPI Data'!$C:$C,'2. Inflation & Deflation Rate'!$C19) -> 453.3
C20: Inflation Rate | D20: =(D19-D18)/D18 -> 0.10990076 | E20: =(E19-E18)/E18 -> 0.017551963 | F20: =(F19-F18)/F18 -> 0.028992072 | G20: =(G19-G18)/G18 -> 0.046419575 | H20: =(H19-H18)/H18 -> 0.040715373 | I20: =(I19-I18)/I18 -> 0.037774725
B36: Interpretation and Analysis:
B38: As graph is depicting hieghest inflation in year 2019 with 7.7% increment.
B39: Reason: Due to 11% increment in Food & Beverages category

Sheet 3.MoM & AbsChange
A1: 3. A M-O-M PRICE TRENDS OF BROADER FOOD BUCKET FOR JUN 2022- MAY 23
A4: Food Inflation/Deflation Rate (MoM)%
A5: Time Period | B5: Food & Beverages | C5: Food Inflation Rate (MoM)%
A6: 2022 May | B6: =AVERAGEIF('CPI Data'!$D:$D,'3.MoM & AbsChange'!$A6,'CPI Data'!$Q:$Q) -> 173.86667
A7: 2022 June | B7: =AVERAGEIF('CPI Data'!$D:$D,'3.MoM & AbsChange'!$A7,'CPI Data'!$Q:$Q) -> 175.53333 | C7: =((B7-B6)/B6) -> 0.0095858896
A8: 2022 July | B8: =AVERAGEIF('CPI Data'!$D:$D,'3.MoM & AbsChange'!$A8,'CPI Data'!$Q:$Q) -> 175.63333 | C8: =((B8-B7)/B7) -> 0.00056969237
A9: 2022 August | B9: =AVERAGEIF('CPI Data'!$D:$D,'3.MoM & AbsChange'!$A9,'CPI Data'!$Q:$Q) -> 176.86667 | C9: =((B9-B8)/B8) -> 0.0070222054
A10: 2022 September | B10: =AVERAGEIF('CPI Data'!$D:$D,'3.MoM & AbsChange'!$A10,'CPI Data'!$Q:$Q) -> 178.36667 | C10: =((B10-B9)/B9) -> 0.0084809649
A11: 2022 October | B11: =AVERAGEIF('CPI Data'!$D:$D,'3.MoM & AbsChange'!$A11,'CPI Data'!$Q:$Q) -> 180.1 | C11: =((B11-B10)/B10) -> 0.0097178098
A12: 2022 November | B12: =AVERAGEIF('CPI Data'!$D:$D,'3.MoM & AbsChange'!$A12,'CPI Data'!$Q:$Q) -> 178.73333 | C12: =((B12-B11)/B11) -> -0.0075883768
A13: 2022 December | B13: =AVERAGEIF('CPI Data'!$D:$D,'3.MoM & AbsChange'!$A13,'CPI Data'!$Q:$Q) -> 176.3 | C13: =((B13-B12)/B12) -> -0.013614323
A14: 2023 January | B14: =AVERAGEIF('CPI Data'!$D:$D,'3.MoM & AbsChange'!$A14,'CPI Data'!$Q:$Q) -> 177.06667 | C14: =((B14-B13)/B13) -> 0.0043486481
A15: 2023 February | B15: =AVERAGEIF('CPI Data'!$D:$D,'3.MoM & AbsChange'!$A15,'CPI Data'!$Q:$Q) -> 177.5 | C15: =((B15-B14)/B14) -> 0.0024472892
A16: 2023 March | B16: =AVERAGEIF('CPI Data'!$D:$D,'3.MoM & AbsChange'!$A16,'CPI Data'!$Q:$Q) -> 177.53333 | C16: =((B16-B15)/B15) -> 0.00018779343
A17: 2023 April | B17: =AVERAGEIF('CPI Data'!$D:$D,'3.MoM & AbsChange'!$A17,'CPI Data'!$Q:$Q) -> 178.5 | C17: =((B17-B16)/B16) -> 0.0054449869
A18: 2023 May | B18: =AVERAGEIF('CPI Data'!$D:$D,'3.MoM & AbsChange'!$A18,'CPI Data'!$Q:$Q) -> 179.66667 | C18: =((B18-B17)/B17) -> 0.0065359477
A21: Time Period | B21: Cereals and products | C21: Meat and fish. | D21: Egg | E21: Milk and products | F21: Oils and fats | G21: Fruits | H21: Vegetables | I21: Pulses and products | J21: Sugar and Confectionery | K21: Spices | L21: Non-alcoholic beverages | M21: Prepared meals, snacks, sweets etc.
A22: 2022 June | B22: =AVERAGEIF('CPI Data'!$D:$D,'3.MoM & AbsChange'!$A22,'CPI Data'!E:E) -> 155.43333 | C22: =AVERAGEIF('CPI Data'!$D:$D,'3.MoM & AbsChange'!$A22,'CPI Data'!F:F) -> 220 | D22: =AVERAGEIF('CPI Data'!$D:$D,'3.MoM & AbsChange'!$A22,'CPI Data'!G:G) -> 171.06667 | E22: =AVERAGEIF('CPI Data'!$D:$D,'3.MoM & AbsChange'!$A22,'CPI Data'!H:H) -> 165.86667 | F22: =AVERAGEIF('CPI Data'!$D:$D,'3.MoM & AbsChange'!$A22,'CPI Data'!I:I) -> 199.2 | G22: =AVERAGEIF('CPI Data'!$D:$D,'3.MoM & AbsChange'!$A22,'CPI Data'!J:J) -> 169.86667 | H22: =AVERAGEIF('CPI Data'!$D:$D,'3.MoM & AbsChange'!$A22,'CPI Data'!K:K) -> 187.03333 | I22: =AVERAGEIF('CPI Data'!$D:$D,'3.MoM & AbsChange'!$A22,'CPI Data'!L:L) -> 164.16667 | J22: =AVERAGEIF('CPI Data'!$D:$D,'3.MoM & AbsChange'!$A22,'CPI Data'!M:M) -> 120.13333 | K22: =AVERAGEIF('CPI Data'!$D:$D,'3.MoM & AbsChange'!$A22,'CPI Data'!N:N) -> 186.5 | L22: =AVERAGEIF('CPI Data'!$D:$D,'3.MoM & AbsChange'!$A22,'CPI Data'!O:O) -> 167.06667 | M22: =AVERAGEIF('CPI Data'!$D:$D,'3.MoM & AbsChange'!$A22,'CPI Data'!P:P) -> 184.03333
A23: 2023 May | B23: =AVERAGEIF('CPI Data'!$D:$D,'3.MoM & AbsChange'!$A23,'CPI Data'!E:E) -> 173.86667 | C23: =AVERAGEIF('CPI Data'!$D:$D,'3.MoM & AbsChange'!$A23,'CPI Data'!F:F) -> 215.06667 | D23: =AVERAGEIF('CPI Data'!$D:$D,'3.MoM & AbsChange'!$A23,'CPI Data'!G:G) -> 173.63333 | E23: =AVERAGEIF('CPI Data'!$D:$D,'3.MoM & AbsChange'!$A23,'CPI Data'!H:H) -> 179.5 | F23: =AVERAGEIF('CPI Data'!$D:$D,'3.MoM & AbsChange'!$A23,'CPI Data'!I:I) -> 169.23333 | G23: =AVERAGEIF('CPI Data'!$D:$D,'3.MoM & AbsChange'!$A23,'CPI Data'!J:J) -> 172.33333 | H23: =AVERAGEIF('CPI Data'!$D:$D,'3.MoM & AbsChange'!$A23,'CPI Data'!K:K) -> 164.9 | I23: =AVERAGEIF('CPI Data'!$D:$D,'3.MoM & AbsChange'!$A23,'CPI Data'!L:L) -> 175.8 | J23: =AVERAGEIF('CPI Data'!$D:$D,'3.MoM & AbsChange'!$A23,'CPI Data'!M:M) -> 122.93333 | K23: =AVERAGEIF('CPI Data'!$D:$D,'3.MoM & AbsChange'!$A23,'CPI Data'!N:N) -> 216.96667 | L23: =AVERAGEIF('CPI Data'!$D:$D,'3.MoM & AbsChange'!$A23,'CPI Data'!O:O) -> 172.66667 | M23: =AVERAGEIF('CPI Data'!$D:$D,'3.MoM & AbsChange'!$A23,'CPI Data'!P:P) -> 194.33333
A26: Absolute Change in Food Subcategories (Jun 2022 → May 2023)
A27: Subcategories | B27: Jun-22 | C27: May-23 | D27: Absolute Change
A28: Spices | B28: =HLOOKUP($A28,$A$21:$M$23,2,0) -> 186.5 | C28: =HLOOKUP($A28,$A$21:$M$23,3,0) -> 216.96667 | D28: =(C28-B28)/B28 -> 0.16336014
A29: Cereals and products | B29: =HLOOKUP($A29,$A$21:$M$23,2,0) -> 155.43333 | C29: =HLOOKUP($A29,$A$21:$M$23,3,0) -> 173.86667 | D29: =(C29-B29)/B29 -> 0.11859318
A30: Milk and products | B30: =HLOOKUP($A30,$A$21:$M$23,2,0) -> 165.86667 | C30: =HLOOKUP($A30,$A$21:$M$23,3,0) -> 179.5 | D30: =(C30-B30)/B30 -> 0.082194534
A31: Pulses and products | B31: =HLOOKUP($A31,$A$21:$M$23,2,0) -> 164.16667 | C31: =HLOOKUP($A31,$A$21:$M$23,3,0) -> 175.8 | D31: =(C31-B31)/B31 -> 0.070862944
A32: Prepared meals, snacks, sweets etc. | B32: =HLOOKUP($A32,$A$21:$M$23,2,0) -> 184.03333 | C32: =HLOOKUP($A32,$A$21:$M$23,3,0) -> 194.33333 | D32: =(C32-B32)/B32 -> 0.055968122
A33: Non-alcoholic beverages | B33: =HLOOKUP($A33,$A$21:$M$23,2,0) -> 167.06667 | C33: =HLOOKUP($A33,$A$21:$M$23,3,0) -> 172.66667 | D33: =(C33-B33)/B33 -> 0.033519553
A34: Sugar and Confectionery | B34: =HLOOKUP($A34,$A$21:$M$23,2,0) -> 120.13333 | C34: =HLOOKUP($A34,$A$21:$M$23,3,0) -> 122.93333 | D34: =(C34-B34)/B34 -> 0.023307436
A35: Egg | B35: =HLOOKUP($A35,$A$21:$M$23,2,0) -> 171.06667 | C35: =HLOOKUP($A35,$A$21:$M$23,3,0) -> 173.63333 | D35: =(C35-B35)/B35 -> 0.015003897
A36: Fruits | B36: =HLOOKUP($A36,$A$21:$M$23,2,0) -> 169.86667 | C36: =HLOOKUP($A36,$A$21:$M$23,3,0) -> 172.33333 | D36: =(C36-B36)/B36 -> 0.014521193
A37: Meat and fish. | B37: =HLOOKUP($A37,$A$21:$M$23,2,0) -> 220 | C37: =HLOOKUP($A37,$A$21:$M$23,3,0) -> 215.06667 | D37: =(C37-B37)/B37 -> -0.022424242
A38: Vegetables | B38: =HLOOKUP($A38,$A$21:$M$23,2,0) -> 187.03333 | C38: =HLOOKUP($A38,$A$21:$M$23,3,0) -> 164.9 | D38: =(C38-B38)/B38 -> -0.11833898
A39: Oils and fats | B39: =HLOOKUP($A39,$A$21:$M$23,2,0) -> 199.2 | C39: =HLOOKUP($A39,$A$21:$M$23,3,0) -> 169.23333 | D39: =(C39-B39)/B39 -> -0.15043507
A42: Interpretation and Analysis
A43: Food inflation (MoM %) showed high volatility between June 2022 and May 2023 due to fluctuations in essential food prices.
A44: Highest MoM inflation: October 2022 (+0.97%) — driven by cereals, milk, and vegetables during festive demand and seasonal shortages.
A45: Lowest MoM inflation: December 2022 (–1.36%) — due to falling prices of vegetables and oils after a strong winter harvest.
A46: The overall trend shows alternating spikes and dips, influenced by crop cycles and weather conditions.
A48: Absolute Change (Jun 2022 → May 2023)
A49: Spices (+16.3%) recorded the highest rise, making them the biggest contributor to food inflation.
A50: Cereals (+11.9%) and Milk (+8.2%) also rose significantly due to strong demand and rising input costs.
A51: Oils & Fats (–15%) showed the sharpest decline due to lower global edible oil prices and improved domestic supply.
A53: Insight
A54: Food inflation between June 2022 and May 2023 was primarily driven by spikes in spices, cereals, and milk prices, offset partially by a fall in edible-oil costs.
A55: The data confirms that volatile food categories continue to be the main driver of India’s retail inflation trend.

Sheet 4. Pre & Post
B1: 4. COVID-19 AFFECTED INFLATION RATE IN INDIA FROM MARCH 2019 - FEB 2020
B3: Rural+Urban | C3: Categories
B4: Time Label | C4: Year | D4: Month | E4: FOOD | F4: CLOTHING | G4: ESSENTIAL | H4: HEALTH | I4: ENERGY | J4: LUXURY
B5: Start (Before) | C5: 2019 | D5: March | E5: {=INDEX('CPI Data'!AF:AF,MATCH(1,('CPI Data'!$A:$A=$B$3)*('CPI Data'!$B:$B=$C5)*('CPI Data'!$C:$C=$D5),0))} -> 1762.9 | F5: {=INDEX('CPI Data'!AG:AG,MATCH(1,('CPI Data'!$A:$A=$B$3)*('CPI Data'!$B:$B=$C5)*('CPI Data'!$C:$C=$D5),0))} -> 434.5 | G5: {=INDEX('CPI Data'!AH:AH,MATCH(1,('CPI Data'!$A:$A=$B$3)*('CPI Data'!$B:$B=$C5)*('CPI Data'!$C:$C=$D5),0))} -> 443.1 | H5: {=INDEX('CPI Data'!AI:AI,MATCH(1,('CPI Data'!$A:$A=$B$3)*('CPI Data'!$B:$B=$C5)*('CPI Data'!$C:$C=$D5),0))} -> 279.6 | I5: {=INDEX('CPI Data'!AJ:AJ,MATCH(1,('CPI Data'!$A:$A=$B$3)*('CPI Data'!$B:$B=$C5)*('CPI Data'!$C:$C=$D5),0))} -> 264.3 | J5: {=INDEX('CPI Data'!AK:AK,MATCH(1,('CPI Data'!$A:$A=$B$3)*('CPI Data'!$B:$B=$C5)*('CPI Data'!$C:$C=$D5),0))} -> 438.9
B6: End (Before) | C6: 2020 | D6: February | E6: {=INDEX('CPI Data'!AF:AF,MATCH(1,('CPI Data'!$A:$A=$B$3)*('CPI Data'!$B:$B=$C6)*('CPI Data'!$C:$C=$D6),0))} -> 1911.6 | F6: {=INDEX('CPI Data'!AG:AG,MATCH(1,('CPI Data'!$A:$A=$B$3)*('CPI Data'!$B:$B=$C6)*('CPI Data'!$C:$C=$D6),0))} -> 442 | G6: {=INDEX('CPI Data'!AH:AH,MATCH(1,('CPI Data'!$A:$A=$B$3)*('CPI Data'!$B:$B=$C6)*('CPI Data'!$C:$C=$D6),0))} -> 457.4 | H6: {=INDEX('CPI Data'!AI:AI,MATCH(1,('CPI Data'!$A:$A=$B$3)*('CPI Data'!$B:$B=$C6)*('CPI Data'!$C:$C=$D6),0))} -> 295.1 | I6: {=INDEX('CPI Data'!AJ:AJ,MATCH(1,('CPI Data'!$A:$A=$B$3)*('CPI Data'!$B:$B=$C6)*('CPI Data'!$C:$C=$D6),0))} -> 277.5 | J6: {=INDEX('CPI Data'!AK:AK,MATCH(1,('CPI Data'!$A:$A=$B$3)*('CPI Data'!$B:$B=$C6)*('CPI Data'!$C:$C=$D6),0))} -> 456.9
B7: Start (COVID) | C7: 2020 | D7: March | E7: {=INDEX('CPI Data'!AF:AF,MATCH(1,('CPI Data'!$A:$A=$B$3)*('CPI Data'!$B:$B=$C7)*('CPI Data'!$C:$C=$D7),0))} -> 1895.4 | F7: {=INDEX('CPI Data'!AG:AG,MATCH(1,('CPI Data'!$A:$A=$B$3)*('CPI Data'!$B:$B=$C7)*('CPI Data'!$C:$C=$D7),0))} -> 442.9 | G7: {=INDEX('CPI Data'!AH:AH,MATCH(1,('CPI Data'!$A:$A=$B$3)*('CPI Data'!$B:$B=$C7)*('CPI Data'!$C:$C=$D7),0))} -> 457 | H7: {=INDEX('CPI Data'!AI:AI,MATCH(1,('CPI Data'!$A:$A=$B$3)*('CPI Data'!$B:$B=$C7)*('CPI Data'!$C:$C=$D7),0))} -> 297.5 | I7: {=INDEX('CPI Data'!AJ:AJ,MATCH(1,('CPI Data'!$A:$A=$B$3)*('CPI Data'!$B:$B=$C7)*('CPI Data'!$C:$C=$D7),0))} -> 278.8 | J7: {=INDEX('CPI Data'!AK:AK,MATCH(1,('CPI Data'!$A:$A=$B$3)*('CPI Data'!$B:$B=$C7)*('CPI Data'!$C:$C=$D7),0))} -> 458.7
B8: End (COVID) | C8: 2021 | D8: February | E8: {=INDEX('CPI Data'!AF:AF,MATCH(1,('CPI Data'!$A:$A=$B$3)*('CPI Data'!$B:$B=$C8)*('CPI Data'!$C:$C=$D8),0))} -> 2039.3 | F8: {=INDEX('CPI Data'!AG:AG,MATCH(1,('CPI Data'!$A:$A=$B$3)*('CPI Data'!$B:$B=$C8)*('CPI Data'!$C:$C=$D8),0))} -> 460.4 | G8: {=INDEX('CPI Data'!AH:AH,MATCH(1,('CPI Data'!$A:$A=$B$3)*('CPI Data'!$B:$B=$C8)*('CPI Data'!$C:$C=$D8),0))} -> 470.2 | H8: {=INDEX('CPI Data'!AI:AI,MATCH(1,('CPI Data'!$A:$A=$B$3)*('CPI Data'!$B:$B=$C8)*('CPI Data'!$C:$C=$D8),0))} -> 317.1 | I8: {=INDEX('CPI Data'!AJ:AJ,MATCH(1,('CPI Data'!$A:$A=$B$3)*('CPI Data'!$B:$B=$C8)*('CPI Data'!$C:$C=$D8),0))} -> 297.5 | J8: {=INDEX('CPI Data'!AK:AK,MATCH(1,('CPI Data'!$A:$A=$B$3)*('CPI Data'!$B:$B=$C8)*('CPI Data'!$C:$C=$D8),0))} -> 493.2
B9: Start (After) | C9: 2021 | D9: March | E9: {=INDEX('CPI Data'!AF:AF,MATCH(1,('CPI Data'!$A:$A=$B$3)*('CPI Data'!$B:$B=$C9)*('CPI Data'!$C:$C=$D9),0))} -> 2039.4 | F9: {=INDEX('CPI Data'!AG:AG,MATCH(1,('CPI Data'!$A:$A=$B$3)*('CPI Data'!$B:$B=$C9)*('CPI Data'!$C:$C=$D9),0))} -> 462.1 | G9: {=INDEX('CPI Data'!AH:AH,MATCH(1,('CPI Data'!$A:$A=$B$3)*('CPI Data'!$B:$B=$C9)*('CPI Data'!$C:$C=$D9),0))} -> 471.3 | H9: {=INDEX('CPI Data'!AI:AI,MATCH(1,('CPI Data'!$A:$A=$B$3)*('CPI Data'!$B:$B=$C9)*('CPI Data'!$C:$C=$D9),0))} -> 315.5 | I9: {=INDEX('CPI Data'!AJ:AJ,MATCH(1,('CPI Data'!$A:$A=$B$3)*('CPI Data'!$B:$B=$C9)*('CPI Data'!$C:$C=$D9),0))} -> 301.7 | J9: {=INDEX('CPI Data'!AK:AK,MATCH(1,('CPI Data'!$A:$A=$B$3)*('CPI Data'!$B:$B=$C9)*('CPI Data'!$C:$C=$D9),0))} -> 494.5
B10: End (After) | C10: 2022 | D10: February | E10: {=INDEX('CPI Data'!AF:AF,MATCH(1,('CPI Data'!$A:$A=$B$3)*('CPI Data'!$B:$B=$C10)*('CPI Data'!$C:$C=$D10),0))} -> 2161.2 | F10: {=INDEX('CPI Data'!AG:AG,MATCH(1,('CPI Data'!$A:$A=$B$3)*('CPI Data'!$B:$B=$C10)*('CPI Data'!$C:$C=$D10),0))} -> 502.8 | G10: {=INDEX('CPI Data'!AH:AH,MATCH(1,('CPI Data'!$A:$A=$B$3)*('CPI Data'!$B:$B=$C10)*('CPI Data'!$C:$C=$D10),0))} -> 492.7 | H10: {=INDEX('CPI Data'!AI:AI,MATCH(1,('CPI Data'!$A:$A=$B$3)*('CPI Data'!$B:$B=$C10)*('CPI Data'!$C:$C=$D10),0))} -> 336.6 | I10: {=INDEX('CPI Data'!AJ:AJ,MATCH(1,('CPI Data'!$A:$A=$B$3)*('CPI Data'!$B:$B=$C10)*('CPI Data'!$C:$C=$D10),0))} -> 322.6 | J10: {=INDEX('CPI Data'!AK:AK,MATCH(1,('CPI Data'!$A:$A=$B$3)*('CPI Data'!$B:$B=$C10)*('CPI Data'!$C:$C=$D10),0))} -> 518.4
B13: Period ↓ Category → | C13: FOOD | D13: CLOTHING | E13: ESSENTIAL | F13: HEALTH | G13: ENERGY | H13: LUXURY
B14: Before COVID (Mar19 → Feb20) | C14: =(E6-E5)/E5 -> 0.084349651 | D14: =(F6-F5)/F5 -> 0.01726122 | E14: =(G6-G5)/G5 -> 0.032272625 | F14: =(H6-H5)/H5 -> 0.055436338 | G14: =(I6-I5)/I5 -> 0.049943246 | H14: =(J6-J5)/J5 -> 0.04101162
B15: COVID Year (Mar20 → Feb21) | C15: =(E8-E7)/E7 -> 0.07592065 | D15: =(F8-F7)/F7 -> 0.039512305 | E15: =(G8-G7)/G7 -> 0.028884026 | F15: =(H8-H7)/H7 -> 0.065882353 | G15: =(I8-I7)/I7 -> 0.067073171 | H15: =(J8-J7)/J7 -> 0.075212557
B16: After COVID (Mar21 →Feb22) | C16: =(E10-E9)/E9 -> 0.059723448 | D16: =(F10-F9)/F9 -> 0.088076174 | E16: =(G10-G9)/G9 -> 0.045406323 | F16: =(H10-H9)/H9 -> 0.066877971 | G16: =(I10-I9)/I9 -> 0.069274113 | H16: =(J10-J9)/J9 -> 0.048331648
B19: Take CPI values for three time periods:
B20: Before COVID: March 2019 → February 2020
B21: COVID Year: March 2020 → February 2021
B22: After COVID: March 2021 → February 2022
B24: Interpretation
B25: Food inflation stayed high across all three periods, rising sharply during COVID (8–9%) due to supply-chain disruptions and strong demand for staples.
B26: Clothing and Luxury inflation increased sharply after COVID, reflecting demand recovery.
B27: Essential goods showed stable, moderate inflation (3–5%), reflecting consistent, inelastic household demand.
B28: Health inflation peaked during the COVID phase (6–7%) as spending on medicines, medical care, and hygiene products surged.
B29: Energy inflation rose significantly during COVID (7%+), driven by global crude oil volatility and transportation bottlenecks.
B30: Luxury inflation also increased during COVID, suggesting that higher-income consumers maintained or even increased discretionary spending during the period.
B33: Insights
... B39: The rise in luxury inflation during COVID indicates a differentiated impact — wealthier households retained higher spending capacity.

Sheet 5. Correlation 
A1: 5. M-O-M IMPORTED CRUDE OIL PRICE FLUCTUATIONS INFLATION FOR 2021 -2023
D3: Categories
A4: Sector | B4: Year | C4: Month | D4: Cereals and products | E4: Meat and fish | F4: Egg | G4: Milk and products | H4: Oils and fats | I4: Fruits | J4: Vegetables | K4: Pulses and products | L4: Sugar and Confectionery | M4: Spices | N4: Non-alcoholic beverages | O4: Prepared meals, snacks, sweets etc. | P4: Food and beverages | Q4: Pan, tobacco and intoxicants | R4: Clothing | S4: Footwear | T4: Clothing and footwear | U4: Housing | V4: Fuel and light | W4: Household goods and services | X4: Health | Y4: Transport and communication | Z4: Recreation and amusement | AA4: Education | AB4: Personal care and effects | AC4: Miscellaneous | AD4: General index | AE4: Crude Olil
A5: Rural+Urban | B5: 2021 | C5: January | D5: {=INDEX('CPI Data'!E:E,MATCH(1,('CPI Data'!$A:$A=$A5)*('CPI Data'!$B:$B=$B5)*('CPI Data'!$C:$C=$C5),0))} -> 144.9 | E5: {=INDEX('CPI Data'!F:F,MATCH(1,('CPI Data'!$A:$A=$A5)*('CPI Data'!$B:$B=$B5)*('CPI Data'!$C:$C=$C5),0))} -> 190.1 | F5: {=INDEX('CPI Data'!G:G,MATCH(1,('CPI Data'!$A:$A=$A5)*('CPI Data'!$B:$B=$B5)*('CPI Data'!$C:$C=$C5),0))} -> 175.3 | G5: {=INDEX('CPI Data'!H:H,MATCH(1,('CPI Data'!$A:$A=$A5)*('CPI Data'!$B:$B=$B5)*('CPI Data'!$C:$C=$C5),0))} -> 154.1 | H5: {=INDEX('CPI Data'!I:I,MATCH(1,('CPI Data'!$A:$A=$A5)*('CPI Data'!$B:$B=$B5)*('CPI Data'!$C:$C=$C5),0))} -> 150.9 | I5: {=INDEX('CPI Data'!J:J,MATCH(1,('CPI Data'!$A:$A=$A5)*('CPI Data'!$B:$B=$B5)*('CPI Data'!$C:$C=$C5),0))} -> 149.6 | J5: {=INDEX('CPI Data'!K:K,MATCH(1,('CPI Data'!$A:$A=$A5)*('CPI Data'!$B:$B=$B5)*('CPI Data'!$C:$C=$C5),0))} -> 194.2 | K5: {=INDEX('CPI Data'!L:L,MATCH(1,('CPI Data'!$A:$A=$A5)*('CPI Data'!$B:$B=$B5)*('CPI Data'!$C:$C=$C5),0))} -> 160.4 | L5: {=INDEX('CPI Data'!M:M,MATCH(1,('CPI Data'!$A:$A=$A5)*('CPI Data'!$B:$B=$B5)*('CPI Data'!$C:$C=$C5),0))} -> 114.6 | M5: {=INDEX('CPI Data'!N:N,MATCH(1,('CPI Data'!$A:$A=$A5)*('CPI Data'!$B:$B=$B5)*('CPI Data'!$C:$C=$C5),0))} -> 164 | N5: {=INDEX('CPI Data'!O:O,MATCH(1,('CPI Data'!$A:$A=$A5)*('CPI Data'!$B:$B=$B5)*('CPI Data'!$C:$C=$C5),0))} -> 151.8 | O5: {=INDEX('CPI Data'!P:P,MATCH(1,('CPI Data'!$A:$A=$A5)*('CPI Data'!$B:$B=$B5)*('CPI Data'!$C:$C=$C5),0))} -> 165.6 | P5: {=INDEX('CPI Data'!Q:Q,MATCH(1,('CPI Data'!$A:$A=$A5)*('CPI Data'!$B:$B=$B5)*('CPI Data'!$C:$C=$C5),0))} -> 161 | Q5: {=INDEX('CPI Data'!R:R,MATCH(1,('CPI Data'!$A:$A=$A5)*('CPI Data'!$B:$B=$B5)*('CPI Data'!$C:$C=$C5),0))} -> 186.5 | R5: {=INDEX('CPI Data'!S:S,MATCH(1,('CPI Data'!$A:$A=$A5)*('CPI Data'!$B:$B=$B5)*('CPI Data'!$C:$C=$C5),0))} -> 155.5 | S5: {=INDEX('CPI Data'!T:T,MATCH(1,('CPI Data'!$A:$A=$A5)*('CPI Data'!$B:$B=$B5)*('CPI Data'!$C:$C=$C5),0))} -> 146.1 | T5: {=INDEX('CPI Data'!U:U,MATCH(1,('CPI Data'!$A:$A=$A5)*('CPI Data'!$B:$B=$B5)*('CPI Data'!$C:$C=$C5),0))} -> 154.2 | U5: {=INDEX('CPI Data'!V:V,MATCH(1,('CPI Data'!$A:$A=$A5)*('CPI Data'!$B:$B=$B5)*('CPI Data'!$C:$C=$C5),0))} -> 157.7 | V5: {=INDEX('CPI Data'!W:W,MATCH(1,('CPI Data'!$A:$A=$A5)*('CPI Data'!$B:$B=$B5)*('CPI Data'!$C:$C=$C5),0))} -> 147.9 | W5: {=INDEX('CPI Data'!X:X,MATCH(1,('CPI Data'!$A:$A=$A5)*('CPI Data'!$B:$B=$B5)*('CPI Data'!$C:$C=$C5),0))} -> 150 | X5: {=INDEX('CPI Data'!Y:Y,MATCH(1,('CPI Data'!$A:$A=$A5)*('CPI Data'!$B:$B=$B5)*('CPI Data'!$C:$C=$C5),0))} -> 159.3 | Y5: {=INDEX('CPI Data'!Z:Z,MATCH(1,('CPI Data'!$A:$A=$A5)*('CPI Data'!$B:$B=$B5)*('CPI Data'!$C:$C=$C5),0))} -> 141.9 | Z5: {=INDEX('CPI Data'!AA:AA,MATCH(1,('CPI Data'!$A:$A=$A5)*('CPI Data'!$B:$B=$B5)*('CPI Data'!$C:$C=$C5),0))} -> 149.6 | AA5: {=INDEX('CPI Data'!AB:AB,MATCH(1,('CPI Data'!$A:$A=$A5)*('CPI Data'!$B:$B=$B5)*('CPI Data'!$C:$C=$C5),0))} -> 159.2 | AB5: {=INDEX('CPI Data'!AC:AC,MATCH(1,('CPI Data'!$A:$A=$A5)*('CPI Data'!$B:$B=$B5)*('CPI Data'!$C:$C=$C5),0))} -> 156.8 | AC5: {=INDEX('CPI Data'!AD:AD,MATCH(1,('CPI Data'!$A:$A=$A5)*('CPI Data'!$B:$B=$B5)*('CPI Data'!$C:$C=$C5),0))} -> 151.9 | AD5: {=INDEX('CPI Data'!AE:AE,MATCH(1,('CPI Data'!$A:$A=$A5)*('CPI Data'!$B:$B=$B5)*('CPI Data'!$C:$C=$C5),0))} -> 157.3 | AE5: =SUMIFS('Crude Oil '!$D:$D,'Crude Oil '!$B:$B,'5. Correlation '!B5,'Crude Oil '!$C:$C,'5. Correlation '!C5) -> 66695
A6: Rural+Urban | B6: 2021 | C6: February | D6: {=INDEX('CPI Data'!E:E,MATCH(1,('CPI Data'!$A:$A=$A6)*('CPI Data'!$B:$B=$B6)*('CPI Data'!$C:$C=$C6),0))} -> 144.3 | E6: {=INDEX('CPI Data'!F:F,MATCH(1,('CPI Data'!$A:$A=$A6)*('CPI Data'!$B:$B=$B6)*('CPI Data'!$C:$C=$C6),0))} -> 186.5 | F6: {=INDEX('CPI Data'!G:G,MATCH(1,('CPI Data'!$A:$A=$A6)*('CPI Data'!$B:$B=$B6)*('CPI Data'!$C:$C=$C6),0))} -> 168.7 | G6: {=INDEX('CPI Data'!H:H,MATCH(1,('CPI Data'!$A:$A=$A6)*('CPI Data'!$B:$B=$B6)*('CPI Data'!$C:$C=$C6),0))} -> 154.7 | H6: {=INDEX('CPI Data'!I:I,MATCH(1,('CPI Data'!$A:$A=$A6)*('CPI Data'!$B:$B=$B6)*('CPI Data'!$C:$C=$C6),0))} -> 158.7 | I6: {=INDEX('CPI Data'!J:J,MATCH(1,('CPI Data'!$A:$A=$A6)*('CPI Data'!$B:$B=$B6)*('CPI Data'!$C:$C=$C6),0))} -> 150.7 | J6: {=INDEX('CPI Data'!K:K,MATCH(1,('CPI Data'!$A:$A=$A6)*('CPI Data'!$B:$B=$B6)*('CPI Data'!$C:$C=$C6),0))} -> 160 | K6: {=INDEX('CPI Data'!L:L,MATCH(1,('CPI Data'!$A:$A=$A6)*('CPI Data'!$B:$B=$B6)*('CPI Data'!$C:$C=$C6),0))} -> 158.8 | L6: {=INDEX('CPI Data'!M:M,MATCH(1,('CPI Data'!$A:$A=$A6)*('CPI Data'!$B:$B=$B6)*('CPI Data'!$C:$C=$C6),0))} -> 112.8 | M6: {=INDEX('CPI Data'!N:N,MATCH(1,('CPI Data'!$A:$A=$A6)*('CPI Data'!$B:$B=$B6)*('CPI Data'!$C:$C=$C6),0))} -> 164.2 | N6: {=INDEX('CPI Data'!O:O,MATCH(1,('CPI Data'!$A:$A=$A6)*('CPI Data'!$B:$B=$B6)*('CPI Data'!$C:$C=$C6),0))} -> 155.5 | O6: {=INDEX('CPI Data'!P:P,MATCH(1,('CPI Data'!$A:$A=$A6)*('CPI Data'!$B:$B=$B6)*('CPI Data'!$C:$C=$C6),0))} -> 167.5 | P6: {=INDEX('CPI Data'!Q:Q,MATCH(1,('CPI Data'!$A:$A=$A6)*('CPI Data'!$B:$B=$B6)*('CPI Data'!$C:$C=$C6),0))} -> 156.9 | Q6: {=INDEX('CPI Data'!R:R,MATCH(1,('CPI Data'!$A:$A=$A6)*('CPI Data'!$B:$B=$B6)*('CPI Data'!$C:$C=$C6),0))} -> 188.3 | R6: {=INDEX('CPI Data'!S:S,MATCH(1,('CPI Data'!$A:$A=$A6)*('CPI Data'!$B:$B=$B6)*('CPI Data'!$C:$C=$C6),0))} -> 157.2 | S6: {=INDEX('CPI Data'!T:T,MATCH(1,('CPI Data'!$A:$A=$A6)*('CPI Data'!$B:$B=$B6)*('CPI Data'!$C:$C=$C6),0))} -> 147.4 | T6: {=INDEX('CPI Data'!U:U,MATCH(1,('CPI Data'!$A:$A=$A6)*('CPI Data'!$B:$B=$B6)*('CPI Data'!$C:$C=$C6),0))} -> 155.8 | U6: {=INDEX('CPI Data'!V:V,MATCH(1,('CPI Data'!$A:$A=$A6)*('CPI Data'!$B:$B=$B6)*('CPI Data'!$C:$C=$C6),0))} -> 159.8 | V6: {=INDEX('CPI Data'!W:W,MATCH(1,('CPI Data'!$A:$A=$A6)*('CPI Data'!$B:$B=$B6)*('CPI Data'!$C:$C=$C6),0))} -> 152.4 | W6: {=INDEX('CPI Data'!X:X,MATCH(1,('CPI Data'!$A:$A=$A6)*('CPI Data'!$B:$B=$B6)*('CPI Data'!$C:$C=$C6),0))} -> 150.9 | X6: {=INDEX('CPI Data'!Y:Y,MATCH(1,('CPI Data'!$A:$A=$A6)*('CPI Data'!$B:$B=$B6)*('CPI Data'!$C:$C=$C6),0))} -> 161.3 | Y6: {=INDEX('CPI Data'!Z:Z,MATCH(1,('CPI Data'!$A:$A=$A6)*('CPI Data'!$B:$B=$B6)*('CPI Data'!$C:$C=$C6),0))} -> 145.1 | Z6: {=INDEX('CPI Data'!AA:AA,MATCH(1,('CPI Data'!$A:$A=$A6)*('CPI Data'!$B:$B=$B6)*('CPI Data'!$C:$C=$C6),0))} -> 151.5 | AA6: {=INDEX('CPI Data'!AB:AB,MATCH(1,('CPI Data'!$A:$A=$A6)*('CPI Data'!$B:$B=$B6)*('CPI Data'!$C:$C=$C6),0))} -> 159.5 | AB6: {=INDEX('CPI Data'!AC:AC,MATCH(1,('CPI Data'!$A:$A=$A6)*('CPI Data'!$B:$B=$B6)*('CPI Data'!$C:$C=$C6),0))} -> 155.8 | AC6: {=INDEX('CPI Data'!AD:AD,MATCH(1,('CPI Data'!$A:$A=$A6)*('CPI Data'!$B:$B=$B6)*('CPI Data'!$C:$C=$C6),0))} -> 153.4 | AD6: {=INDEX('CPI Data'!AE:AE,MATCH(1,('CPI Data'!$A:$A=$A6)*('CPI Data'!$B:$B=$B6)*('CPI Data'!$C:$C=$C6),0))} -> 156.6 | AE6: =SUMIFS('Crude Oil '!$D:$D,'Crude Oil '!$B:$B,'5. Correlation '!B6,'Crude Oil '!$C:$C,'5. Correlation '!C6) -> 60966
A7: Rural+Urban | B7: 2021 | C7: March | D7: {=INDEX('CPI Data'!E:E,MATCH(1,('CPI Data'!$A:$A=$A7)*('CPI Data'!$B:$B=$B7)*('CPI Data'!$C:$C=$C7),0))} -> 144.1 | E7: {=INDEX('CPI Data'!F:F,MATCH(1,('CPI Data'!$A:$A=$A7)*('CPI Data'!$B:$B=$B7)*('CPI Data'!$C:$C=$C7),0))} -> 192.2 | F7: {=INDEX('CPI Data'!G:G,MATCH(1,('CPI Data'!$A:$A=$A7)*('CPI Data'!$B:$B=$B7)*('CPI Data'!$C:$C=$C7),0))} -> 163.8 | G7: {=INDEX('CPI Data'!H:H,MATCH(1,('CPI Data'!$A:$A=$A7)*('CPI Data'!$B:$B=$B7)*('CPI Data'!$C:$C=$C7),0))} -> 154.9 | H7: {=INDEX('CPI Data'!I:I,MATCH(1,('CPI Data'!$A:$A=$A7)*('CPI Data'!$B:$B=$B7)*('CPI Data'!$C:$C=$C7),0))} -> 163.9 | I7: {=INDEX('CPI Data'!J:J,MATCH(1,('CPI Data'!$A:$A=$A7)*('CPI Data'!$B:$B=$B7)*('CPI Data'!$C:$C=$C7),0))} -> 153.7 | J7: {=INDEX('CPI Data'!K:K,MATCH(1,('CPI Data'!$A:$A=$A7)*('CPI Data'!$B:$B=$B7)*('CPI Data'!$C:$C=$C7),0))} -> 149.5 | K7: {=INDEX('CPI Data'!L:L,MATCH(1,('CPI Data'!$A:$A=$A7)*('CPI Data'!$B:$B=$B7)*('CPI Data'!$C:$C=$C7),0))} -> 159.8 | L7: {=INDEX('CPI Data'!M:M,MATCH(1,('CPI Data'!$A:$A=$A7)*('CPI Data'!$B:$B=$B7)*('CPI Data'!$C:$C=$C7),0))} -> 112.6 | M7: {=INDEX('CPI Data'!N:N,MATCH(1,('CPI Data'!$A:$A=$A7)*('CPI Data'!$B:$B=$B7)*('CPI Data'!$C:$C=$C7),0))} -> 163.5 | N7: {=INDEX('CPI Data'!O:O,MATCH(1,('CPI Data'!$A:$A=$A7)*('CPI Data'!$B:$B=$B7)*('CPI Data'!$C:$C=$C7),0))} -> 156.5 | O7: {=INDEX('CPI Data'!P:P,MATCH(1,('CPI Data'!$A:$A=$A7)*('CPI Data'!$B:$B=$B7)*('CPI Data'!$C:$C=$C7),0))} -> 168.2 | P7: {=INDEX('CPI Data'!Q:Q,MATCH(1,('CPI Data'!$A:$A=$A7)*('CPI Data'!$B:$B=$B7)*('CPI Data'!$C:$C=$C7),0))} -> 156.7 | Q7: {=INDEX('CPI Data'!R:R,MATCH(1,('CPI Data'!$A:$A=$A7)*('CPI Data'!$B:$B=$B7)*('CPI Data'!$C:$C=$C7),0))} -> 188.1 | R7: {=INDEX('CPI Data'!S:S,MATCH(1,('CPI Data'!$A:$A=$A7)*('CPI Data'!$B:$B=$B7)*('CPI Data'!$C:$C=$C7),0))} -> 157.8 | S7: {=INDEX('CPI Data'!T:T,MATCH(1,('CPI Data'!$A:$A=$A7)*('CPI Data'!$B:$B=$B7)*('CPI Data'!$C:$C=$C7),0))} -> 147.9 | T7: {=INDEX('CPI Data'!U:U,MATCH(1,('CPI Data'!$A:$A=$A7)*('CPI Data'!$B:$B=$B7)*('CPI Data'!$C:$C=$C7),0))} -> 156.4 | U7: {=INDEX('CPI Data'!V:V,MATCH(1,('CPI Data'!$A:$A=$A7)*('CPI Data'!$B:$B=$B7)*('CPI Data'!$C:$C=$C7),0))} -> 159.9 | V7: {=INDEX('CPI Data'!W:W,MATCH(1,('CPI Data'!$A:$A=$A7)*('CPI Data'!$B:$B=$B7)*('CPI Data'!$C:$C=$C7),0))} -> 155.5 | W7: {=INDEX('CPI Data'!X:X,MATCH(1,('CPI Data'!$A:$A=$A7)*('CPI Data'!$B:$B=$B7)*('CPI Data'!$C:$C=$C7),0))} -> 151.2 | X7: {=INDEX('CPI Data'!Y:Y,MATCH(1,('CPI Data'!$A:$A=$A7)*('CPI Data'!$B:$B=$B7)*('CPI Data'!$C:$C=$C7),0))} -> 161.7 | Y7: {=INDEX('CPI Data'!Z:Z,MATCH(1,('CPI Data'!$A:$A=$A7)*('CPI Data'!$B:$B=$B7)*('CPI Data'!$C:$C=$C7),0))} -> 146.2 | Z7: {=INDEX('CPI Data'!AA:AA,MATCH(1,('CPI Data'!$A:$A=$A7)*('CPI Data'!$B:$B=$B7)*('CPI Data'!$C:$C=$C7),0))} -> 152.6 | AA7: {=INDEX('CPI Data'!AB:AB,MATCH(1,('CPI Data'!$A:$A=$A7)*('CPI Data'!$B:$B=$B7)*('CPI Data'!$C:$C=$C7),0))} -> 160.2 | AB7: {=INDEX('CPI Data'!AC:AC,MATCH(1,('CPI Data'!$A:$A=$A7)*('CPI Data'!$B:$B=$B7)*('CPI Data'!$C:$C=$C7),0))} -> 153.8 | AC7: {=INDEX('CPI Data'!AD:AD,MATCH(1,('CPI Data'!$A:$A=$A7)*('CPI Data'!$B:$B=$B7)*('CPI Data'!$C:$C=$C7),0))} -> 153.8 | AD7: {=INDEX('CPI Data'!AE:AE,MATCH(1,('CPI Data'!$A:$A=$A7)*('CPI Data'!$B:$B=$B7)*('CPI Data'!$C:$C=$C7),0))} -> 156.8 | AE7: =SUMIFS('Crude Oil '!$D:$D,'Crude Oil '!$B:$B,'5. Correlation '!B7,'Crude Oil '!$C:$C,'5. Correlation '!C7) -> 75471
A8: Rural+Urban | B8: 2021 | C8: April | D8: {=INDEX('CPI Data'!E:E,MATCH(1,('CPI Data'!$A:$A=$A8)*('CPI Data'!$B:$B=$B8)*('CPI Data'!$C:$C=$C8),0))} -> 144.3 | E8: {=INDEX('CPI Data'!F:F,MATCH(1,('CPI Data'!$A:$A=$A8)*('CPI Data'!$B:$B=$B8)*('CPI Data'!$C:$C=$C8),0))} -> 198 | F8: {=INDEX('CPI Data'!G:G,MATCH(1,('CPI Data'!$A:$A=$A8)*('CPI Data'!$B:$B=$B8)*('CPI Data'!$C:$C=$C8),0))} -> 164.6 | G8: {=INDEX('CPI Data'!H:H,MATCH(1,('CPI Data'!$A:$A=$A8)*('CPI Data'!$B:$B=$B8)*('CPI Data'!$C:$C=$C8),0))} -> 155.4 | H8: {=INDEX('CPI Data'!I:I,MATCH(1,('CPI Data'!$A:$A=$A8)*('CPI Data'!$B:$B=$B8)*('CPI Data'!$C:$C=$C8),0))} -> 170.1 | I8: {=INDEX('CPI Data'!J:J,MATCH(1,('CPI Data'!$A:$A=$A8)*('CPI Data'!$B:$B=$B8)*('CPI Data'!$C:$C=$C8),0))} -> 164.4 | J8: {=INDEX('CPI Data'!K:K,MATCH(1,('CPI Data'!$A:$A=$A8)*('CPI Data'!$B:$B=$B8)*('CPI Data'!$C:$C=$C8),0))} -> 144.1 | K8: {=INDEX('CPI Data'!L:L,MATCH(1,('CPI Data'!$A:$A=$A8)*('CPI Data'!$B:$B=$B8)*('CPI Data'!$C:$C=$C8),0))} -> 161.7 | L8: {=INDEX('CPI Data'!M:M,MATCH(1,('CPI Data'!$A:$A=$A8)*('CPI Data'!$B:$B=$B8)*('CPI Data'!$C:$C=$C8),0))} -> 113.1 | M8: {=INDEX('CPI Data'!N:N,MATCH(1,('CPI Data'!$A:$A=$A8)*('CPI Data'!$B:$B=$B8)*('CPI Data'!$C:$C=$C8),0))} -> 163.9 | N8: {=INDEX('CPI Data'!O:O,MATCH(1,('CPI Data'!$A:$A=$A8)*('CPI Data'!$B:$B=$B8)*('CPI Data'!$C:$C=$C8),0))} -> 157.6 | O8: {=INDEX('CPI Data'!P:P,MATCH(1,('CPI Data'!$A:$A=$A8)*('CPI Data'!$B:$B=$B8)*('CPI Data'!$C:$C=$C8),0))} -> 168.9 | P8: {=INDEX('CPI Data'!Q:Q,MATCH(1,('CPI Data'!$A:$A=$A8)*('CPI Data'!$B:$B=$B8)*('CPI Data'!$C:$C=$C8),0))} -> 158 | Q8: {=INDEX('CPI Data'!R:R,MATCH(1,('CPI Data'!$A:$A=$A8)*('CPI Data'!$B:$B=$B8)*('CPI Data'!$C:$C=$C8),0))} -> 188.8 | R8: {=INDEX('CPI Data'!S:S,MATCH(1,('CPI Data'!$A:$A=$A8)*('CPI Data'!$B:$B=$B8)*('CPI Data'!$C:$C=$C8),0))} -> 158.8 | S8: {=INDEX('CPI Data'!T:T,MATCH(1,('CPI Data'!$A:$A=$A8)*('CPI Data'!$B:$B=$B8)*('CPI Data'!$C:$C=$C8),0))} -> 148.5 | T8: {=INDEX('CPI Data'!U:U,MATCH(1,('CPI Data'!$A:$A=$A8)*('CPI Data'!$B:$B=$B8)*('CPI Data'!$C:$C=$C8),0))} -> 157.3 | U8: {=INDEX('CPI Data'!V:V,MATCH(1,('CPI Data'!$A:$A=$A8)*('CPI Data'!$B:$B=$B8)*('CPI Data'!$C:$C=$C8),0))} -> 161.4 | V8: {=INDEX('CPI Data'!W:W,MATCH(1,('CPI Data'!$A:$A=$A8)*('CPI Data'!$B:$B=$B8)*('CPI Data'!$C:$C=$C8),0))} -> 155.6 | W8: {=INDEX('CPI Data'!X:X,MATCH(1,('CPI Data'!$A:$A=$A8)*('CPI Data'!$B:$B=$B8)*('CPI Data'!$C:$C=$C8),0))} -> 151.8 | X8: {=INDEX('CPI Data'!Y:Y,MATCH(1,('CPI Data'!$A:$A=$A8)*('CPI Data'!$B:$B=$B8)*('CPI Data'!$C:$C=$C8),0))} -> 162.3 | Y8: {=INDEX('CPI Data'!Z:Z,MATCH(1,('CPI Data'!$A:$A=$A8)*('CPI Data'!$B:$B=$B8)*('CPI Data'!$C:$C=$C8),0))} -> 146.6 | Z8: {=INDEX('CPI Data'!AA:AA,MATCH(1,('CPI Data'!$A:$A=$A8)*('CPI Data'!$B:$B=$B8)*('CPI Data'!$C:$C=$C8),0))} -> 153.2 | AA8: {=INDEX('CPI Data'!AB:AB,MATCH(1,('CPI Data'!$A:$A=$A8)*('CPI Data'!$B:$B=$B8)*('CPI Data'!$C:$C=$C8),0))} -> 160.3 | AB8: {=INDEX('CPI Data'!AC:AC,MATCH(1,('CPI Data'!$A:$A=$A8)*('CPI Data'!$B:$B=$B8)*('CPI Data'!$C:$C=$C8),0))} -> 155.4 | AC8: {=INDEX('CPI Data'!AD:AD,MATCH(1,('CPI Data'!$A:$A=$A8)*('CPI Data'!$B:$B=$B8)*('CPI Data'!$C:$C=$C8),0))} -> 154.4 | AD8: {=INDEX('CPI Data'!AE:AE,MATCH(1,('CPI Data'!$A:$A=$A8)*('CPI Data'!$B:$B=$B8)*('CPI Data'!$C:$C=$C8),0))} -> 157.8 | AE8: =SUMIFS('Crude Oil '!$D:$D,'Crude Oil '!$B:$B,'5. Correlation '!B8,'Crude Oil '!$C:$C,'5. Correlation '!C8) -> 74208
A9: Rural+Urban | B9: 2021 | C9: May | D9: {=INDEX('CPI Data'!E:E,MATCH(1,('CPI Data'!$A:$A=$A9)*('CPI Data'!$B:$B=$B9)*('CPI Data'!$C:$C=$C9),0))} -> 146.3 | E9: {=INDEX('CPI Data'!F:F,MATCH(1,('CPI Data'!$A:$A=$A9)*('CPI Data'!$B:$B=$B9)*('CPI Data'!$C:$C=$C9),0))} -> 200.5 | F9: {=INDEX('CPI Data'!G:G,MATCH(1,('CPI Data'!$A:$A=$A9)*('CPI Data'!$B:$B=$B9)*('CPI Data'!$C:$C=$C9),0))} -> 170.3 | G9: {=INDEX('CPI Data'!H:H,MATCH(1,('CPI Data'!$A:$A=$A9)*('CPI Data'!$B:$B=$B9)*('CPI Data'!$C:$C=$C9),0))} -> 156.1 | H9: {=INDEX('CPI Data'!I:I,MATCH(1,('CPI Data'!$A:$A=$A9)*('CPI Data'!$B:$B=$B9)*('CPI Data'!$C:$C=$C9),0))} -> 178.7 | I9: {=INDEX('CPI Data'!J:J,MATCH(1,('CPI Data'!$A:$A=$A9)*('CPI Data'!$B:$B=$B9)*('CPI Data'!$C:$C=$C9),0))} -> 167.1 | J9: {=INDEX('CPI Data'!K:K,MATCH(1,('CPI Data'!$A:$A=$A9)*('CPI Data'!$B:$B=$B9)*('CPI Data'!$C:$C=$C9),0))} -> 147.9 | K9: {=INDEX('CPI Data'!L:L,MATCH(1,('CPI Data'!$A:$A=$A9)*('CPI Data'!$B:$B=$B9)*('CPI Data'!$C:$C=$C9),0))} -> 165.4 | L9: {=INDEX('CPI Data'!M:M,MATCH(1,('CPI Data'!$A:$A=$A9)*('CPI Data'!$B:$B=$B9)*('CPI Data'!$C:$C=$C9),0))} -> 114.8 | M9: {=INDEX('CPI Data'!N:N,MATCH(1,('CPI Data'!$A:$A=$A9)*('CPI Data'!$B:$B=$B9)*('CPI Data'!$C:$C=$C9),0))} -> 168.2 | N9: {=INDEX('CPI Data'!O:O,MATCH(1,('CPI Data'!$A:$A=$A9)*('CPI Data'!$B:$B=$B9)*('CPI Data'!$C:$C=$C9),0))} -> 159.3 | O9: {=INDEX('CPI Data'!P:P,MATCH(1,('CPI Data'!$A:$A=$A9)*('CPI Data'!$B:$B=$B9)*('CPI Data'!$C:$C=$C9),0))} -> 170.4 | P9: {=INDEX('CPI Data'!Q:Q,MATCH(1,('CPI Data'!$A:$A=$A9)*('CPI Data'!$B:$B=$B9)*('CPI Data'!$C:$C=$C9),0))} -> 160.7 | Q9: {=INDEX('CPI Data'!R:R,MATCH(1,('CPI Data'!$A:$A=$A9)*('CPI Data'!$B:$B=$B9)*('CPI Data'!$C:$C=$C9),0))} -> 191.9 | R9: {=INDEX('CPI Data'!S:S,MATCH(1,('CPI Data'!$A:$A=$A9)*('CPI Data'!$B:$B=$B9)*('CPI Data'!$C:$C=$C9),0))} -> 161.8 | S9: {=INDEX('CPI Data'!T:T,MATCH(1,('CPI Data'!$A:$A=$A9)*('CPI Data'!$B:$B=$B9)*('CPI Data'!$C:$C=$C9),0))} -> 152.1 | T9: {=INDEX('CPI Data'!U:U,MATCH(1,('CPI Data'!$A:$A=$A9)*('CPI Data'!$B:$B=$B9)*('CPI Data'!$C:$C=$C9),0))} -> 160.4 | U9: {=INDEX('CPI Data'!V:V,MATCH(1,('CPI Data'!$A:$A=$A9)*('CPI Data'!$B:$B=$B9)*('CPI Data'!$C:$C=$C9),0))} -> 161.6 | V9: {=INDEX('CPI Data'!W:W,MATCH(1,('CPI Data'!$A:$A=$A9)*('CPI Data'!$B:$B=$B9)*('CPI Data'!$C:$C=$C9),0))} -> 159.4 | W9: {=INDEX('CPI Data'!X:X,MATCH(1,('CPI Data'!$A:$A=$A9)*('CPI Data'!$B:$B=$B9)*('CPI Data'!$C:$C=$C9),0))} -> 154.7 | X9: {=INDEX('CPI Data'!Y:Y,MATCH(1,('CPI Data'!$A:$A=$A9)*('CPI Data'!$B:$B=$B9)*('CPI Data'!$C:$C=$C9),0))} -> 165.8 | Y9: {=INDEX('CPI Data'!Z:Z,MATCH(1,('CPI Data'!$A:$A=$A9)*('CPI Data'!$B:$B=$B9)*('CPI Data'!$C:$C=$C9),0))} -> 148.9 | Z9: {=INDEX('CPI Data'!AA:AA,MATCH(1,('CPI Data'!$A:$A=$A9)*('CPI Data'!$B:$B=$B9)*('CPI Data'!$C:$C=$C9),0))} -> 155.8 | AA9: {=INDEX('CPI Data'!AB:AB,MATCH(1,('CPI Data'!$A:$A=$A9)*('CPI Data'!$B:$B=$B9)*('CPI Data'!$C:$C=$C9),0))} -> 161.2 | AB9: {=INDEX('CPI Data'!AC:AC,MATCH(1,('CPI Data'!$A:$A=$A9)*('CPI Data'!$B:$B=$B9)*('CPI Data'!$C:$C=$C9),0))} -> 158.6 | AC9: {=INDEX('CPI Data'!AD:AD,MATCH(1,('CPI Data'!$A:$A=$A9)*('CPI Data'!$B:$B=$B9)*('CPI Data'!$C:$C=$C9),0))} -> 156.8 | AD9: {=INDEX('CPI Data'!AE:AE,MATCH(1,('CPI Data'!$A:$A=$A9)*('CPI Data'!$B:$B=$B9)*('CPI Data'!$C:$C=$C9),0))} -> 160.4 | AE9: =SUMIFS('Crude Oil '!$D:$D,'Crude Oil '!$B:$B,'5. Correlation '!B9,'Crude Oil '!$C:$C,'5. Correlation '!C9) -> 70046
A10: Rural+Urban | B10: 2021 | C10: June | D10: {=INDEX('CPI Data'!E:E,MATCH(1,('CPI Data'!$A:$A=$A10)*('CPI Data'!$B:$B=$B10)*('CPI Data'!$C:$C=$C10),0))} -> 146.7 | E10: {=INDEX('CPI Data'!F:F,MATCH(1,('CPI Data'!$A:$A=$A10)*('CPI Data'!$B:$B=$B10)*('CPI Data'!$C:$C=$C10),0))} -> 202 | F10: {=INDEX('CPI Data'!G:G,MATCH(1,('CPI Data'!$A:$A=$A10)*('CPI Data'!$B:$B=$B10)*('CPI Data'!$C:$C=$C10),0))} -> 180.7 | G10: {=INDEX('CPI Data'!H:H,MATCH(1,('CPI Data'!$A:$A=$A10)*('CPI Data'!$B:$B=$B10)*('CPI Data'!$C:$C=$C10),0))} -> 156.2 | H10: {=INDEX('CPI Data'!I:I,MATCH(1,('CPI Data'!$A:$A=$A10)*('CPI Data'!$B:$B=$B10)*('CPI Data'!$C:$C=$C10),0))} -> 183.7 | I10: {=INDEX('CPI Data'!J:J,MATCH(1,('CPI Data'!$A:$A=$A10)*('CPI Data'!$B:$B=$B10)*('CPI Data'!$C:$C=$C10),0))} -> 164.6 | J10: {=INDEX('CPI Data'!K:K,MATCH(1,('CPI Data'!$A:$A=$A10)*('CPI Data'!$B:$B=$B10)*('CPI Data'!$C:$C=$C10),0))} -> 155.4 | K10: {=INDEX('CPI Data'!L:L,MATCH(1,('CPI Data'!$A:$A=$A10)*('CPI Data'!$B:$B=$B10)*('CPI Data'!$C:$C=$C10),0))} -> 166 | L10: {=INDEX('CPI Data'!M:M,MATCH(1,('CPI Data'!$A:$A=$A10)*('CPI Data'!$B:$B=$B10)*('CPI Data'!$C:$C=$C10),0))} -> 115.1 | M10: {=INDEX('CPI Data'!N:N,MATCH(1,('CPI Data'!$A:$A=$A10)*('CPI Data'!$B:$B=$B10)*('CPI Data'!$C:$C=$C10),0))} -> 168.5 | N10: {=INDEX('CPI Data'!O:O,MATCH(1,('CPI Data'!$A:$A=$A10)*('CPI Data'!$B:$B=$B10)*('CPI Data'!$C:$C=$C10),0))} -> 160 | O10: {=INDEX('CPI Data'!P:P,MATCH(1,('CPI Data'!$A:$A=$A10)*('CPI Data'!$B:$B=$B10)*('CPI Data'!$C:$C=$C10),0))} -> 172.4 | P10: {=INDEX('CPI Data'!Q:Q,MATCH(1,('CPI Data'!$A:$A=$A10)*('CPI Data'!$B:$B=$B10)*('CPI Data'!$C:$C=$C10),0))} -> 162.6 | Q10: {=INDEX('CPI Data'!R:R,MATCH(1,('CPI Data'!$A:$A=$A10)*('CPI Data'!$B:$B=$B10)*('CPI Data'!$C:$C=$C10),0))} -> 190.8 | R10: {=INDEX('CPI Data'!S:S,MATCH(1,('CPI Data'!$A:$A=$A10)*('CPI Data'!$B:$B=$B10)*('CPI Data'!$C:$C=$C10),0))} -> 162.2 | S10: {=INDEX('CPI Data'!T:T,MATCH(1,('CPI Data'!$A:$A=$A10)*('CPI Data'!$B:$B=$B10)*('CPI Data'!$C:$C=$C10),0))} -> 151.8 | T10: {=INDEX('CPI Data'!U:U,MATCH(1,('CPI Data'!$A:$A=$A10)*('CPI Data'!$B:$B=$B10)*('CPI Data'!$C:$C=$C10),0))} -> 160.7 | U10: {=INDEX('CPI Data'!V:V,MATCH(1,('CPI Data'!$A:$A=$A10)*('CPI Data'!$B:$B=$B10)*('CPI Data'!$C:$C=$C10),0))} -> 160.5 | V10: {=INDEX('CPI Data'!W:W,MATCH(1,('CPI Data'!$A:$A=$A10)*('CPI Data'!$B:$B=$B10)*('CPI Data'!$C:$C=$C10),0))} -> 159.8 | W10: {=INDEX('CPI Data'!X:X,MATCH(1,('CPI Data'!$A:$A=$A10)*('CPI Data'!$B:$B=$B10)*('CPI Data'!$C:$C=$C10),0))} -> 154.8 | X10: {=INDEX('CPI Data'!Y:Y,MATCH(1,('CPI Data'!$A:$A=$A10)*('CPI Data'!$B:$B=$B10)*('CPI Data'!$C:$C=$C10),0))} -> 166.3 | Y10: {=INDEX('CPI Data'!Z:Z,MATCH(1,('CPI Data'!$A:$A=$A10)*('CPI Data'!$B:$B=$B10)*('CPI Data'!$C:$C=$C10),0))} -> 150.7 | Z10: {=INDEX('CPI Data'!AA:AA,MATCH(1,('CPI Data'!$A:$A=$A10)*('CPI Data'!$B:$B=$B10)*('CPI Data'!$C:$C=$C10),0))} -> 154.9 | AA10: {=INDEX('CPI Data'!AB:AB,MATCH(1,('CPI Data'!$A:$A=$A10)*('CPI Data'!$B:$B=$B10)*('CPI Data'!$C:$C=$C10),0))} -> 161.7 | AB10: {=INDEX('CPI Data'!AC:AC,MATCH(1,('CPI Data'!$A:$A=$A10)*('CPI Data'!$B:$B=$B10)*('CPI Data'!$C:$C=$C10),0))} -> 158.8 | AC10: {=INDEX('CPI Data'!AD:AD,MATCH(1,('CPI Data'!$A:$A=$A10)*('CPI Data'!$B:$B=$B10)*('CPI Data'!$C:$C=$C10),0))} -> 157.6 | AD10: {=INDEX('CPI Data'!AE:AE,MATCH(1,('CPI Data'!$A:$A=$A10)*('CPI Data'!$B:$B=$B10)*('CPI Data'!$C:$C=$C10),0))} -> 161.3 | AE10: =SUMIFS('Crude Oil '!$D:$D,'Crude Oil '!$B:$B,'5. Correlation '!B10,'Crude Oil '!$C:$C,'5. Correlation '!C10) -> 71679
A11: Rural+Urban | B11: 2021 | C11: July | D11: {=INDEX('CPI Data'!E:E,MATCH(1,('CPI Data'!$A:$A=$A11)*('CPI Data'!$B:$B=$B11)*('CPI Data'!$C:$C=$C11),0))} -> 146.4 | E11: {=INDEX('CPI Data'!F:F,MATCH(1,('CPI Data'!$A:$A=$A11)*('CPI Data'!$B:$B=$B11)*('CPI Data'!$C:$C=$C11),0))} -> 206.8 | F11: {=INDEX('CPI Data'!G:G,MATCH(1,('CPI Data'!$A:$A=$A11)*('CPI Data'!$B:$B=$B11)*('CPI Data'!$C:$C=$C11),0))} -> 182.2 | G11: {=INDEX('CPI Data'!H:H,MATCH(1,('CPI Data'!$A:$A=$A11)*('CPI Data'!$B:$B=$B11)*('CPI Data'!$C:$C=$C11),0))} -> 157.5 | H11: {=INDEX('CPI Data'!I:I,MATCH(1,('CPI Data'!$A:$A=$A11)*('CPI Data'!$B:$B=$B11)*('CPI Data'!$C:$C=$C11),0))} -> 182.1 | I11: {=INDEX('CPI Data'!J:J,MATCH(1,('CPI Data'!$A:$A=$A11)*('CPI Data'!$B:$B=$B11)*('CPI Data'!$C:$C=$C11),0))} -> 163.9 | J11: {=INDEX('CPI Data'!K:K,MATCH(1,('CPI Data'!$A:$A=$A11)*('CPI Data'!$B:$B=$B11)*('CPI Data'!$C:$C=$C11),0))} -> 164.2 | K11: {=INDEX('CPI Data'!L:L,MATCH(1,('CPI Data'!$A:$A=$A11)*('CPI Data'!$B:$B=$B11)*('CPI Data'!$C:$C=$C11),0))} -> 164 | L11: {=INDEX('CPI Data'!M:M,MATCH(1,('CPI Data'!$A:$A=$A11)*('CPI Data'!$B:$B=$B11)*('CPI Data'!$C:$C=$C11),0))} -> 114.5 | M11: {=INDEX('CPI Data'!N:N,MATCH(1,('CPI Data'!$A:$A=$A11)*('CPI Data'!$B:$B=$B11)*('CPI Data'!$C:$C=$C11),0))} -> 168.3 | N11: {=INDEX('CPI Data'!O:O,MATCH(1,('CPI Data'!$A:$A=$A11)*('CPI Data'!$B:$B=$B11)*('CPI Data'!$C:$C=$C11),0))} -> 160.9 | O11: {=INDEX('CPI Data'!P:P,MATCH(1,('CPI Data'!$A:$A=$A11)*('CPI Data'!$B:$B=$B11)*('CPI Data'!$C:$C=$C11),0))} -> 172.2 | P11: {=INDEX('CPI Data'!Q:Q,MATCH(1,('CPI Data'!$A:$A=$A11)*('CPI Data'!$B:$B=$B11)*('CPI Data'!$C:$C=$C11),0))} -> 164 | Q11: {=INDEX('CPI Data'!R:R,MATCH(1,('CPI Data'!$A:$A=$A11)*('CPI Data'!$B:$B=$B11)*('CPI Data'!$C:$C=$C11),0))} -> 191.2 | R11: {=INDEX('CPI Data'!S:S,MATCH(1,('CPI Data'!$A:$A=$A11)*('CPI Data'!$B:$B=$B11)*('CPI Data'!$C:$C=$C11),0))} -> 162.8 | S11: {=INDEX('CPI Data'!T:T,MATCH(1,('CPI Data'!$A:$A=$A11)*('CPI Data'!$B:$B=$B11)*('CPI Data'!$C:$C=$C11),0))} -> 153.1 | T11: {=INDEX('CPI Data'!U:U,MATCH(1,('CPI Data'!$A:$A=$A11)*('CPI Data'!$B:$B=$B11)*('CPI Data'!$C:$C=$C11),0))} -> 161.4 | U11: {=INDEX('CPI Data'!V:V,MATCH(1,('CPI Data'!$A:$A=$A11)*('CPI Data'!$B:$B=$B11)*('CPI Data'!$C:$C=$C11),0))} -> 161.5 | V11: {=INDEX('CPI Data'!W:W,MATCH(1,('CPI Data'!$A:$A=$A11)*('CPI Data'!$B:$B=$B11)*('CPI Data'!$C:$C=$C11),0))} -> 160.7 | W11: {=INDEX('CPI Data'!X:X,MATCH(1,('CPI Data'!$A:$A=$A11)*('CPI Data'!$B:$B=$B11)*('CPI Data'!$C:$C=$C11),0))} -> 155.8 | X11: {=INDEX('CPI Data'!Y:Y,MATCH(1,('CPI Data'!$A:$A=$A11)*('CPI Data'!$B:$B=$B11)*('CPI Data'!$C:$C=$C11),0))} -> 167 | Y11: {=INDEX('CPI Data'!Z:Z,MATCH(1,('CPI Data'!$A:$A=$A11)*('CPI Data'!$B:$B=$B11)*('CPI Data'!$C:$C=$C11),0))} -> 153.1 | Z11: {=INDEX('CPI Data'!AA:AA,MATCH(1,('CPI Data'!$A:$A=$A11)*('CPI Data'!$B:$B=$B11)*('CPI Data'!$C:$C=$C11),0))} -> 155.3 | AA11: {=INDEX('CPI Data'!AB:AB,MATCH(1,('CPI Data'!$A:$A=$A11)*('CPI Data'!$B:$B=$B11)*('CPI Data'!$C:$C=$C11),0))} -> 163.2 | AB11: {=INDEX('CPI Data'!AC:AC,MATCH(1,('CPI Data'!$A:$A=$A11)*('CPI Data'!$B:$B=$B11)*('CPI Data'!$C:$C=$C11),0))} -> 160.1 | AC11: {=INDEX('CPI Data'!AD:AD,MATCH(1,('CPI Data'!$A:$A=$A11)*('CPI Data'!$B:$B=$B11)*('CPI Data'!$C:$C=$C11),0))} -> 159 | AD11: {=INDEX('CPI Data'!AE:AE,MATCH(1,('CPI Data'!$A:$A=$A11)*('CPI Data'!$B:$B=$B11)*('CPI Data'!$C:$C=$C11),0))} -> 162.5 | AE11: =SUMIFS('Crude Oil '!$D:$D,'Crude Oil '!$B:$B,'5. Correlation '!B11,'Crude Oil '!$C:$C,'5. Correlation '!C11) -> 72860
A12: Rural+Urban | B12: 2021 | C12: August | D12: {=INDEX('CPI Data'!E:E,MATCH(1,('CPI Data'!$A:$A=$A12)*('CPI Data'!$B:$B=$B12)*('CPI Data'!$C:$C=$C12),0))} -> 146.6 | E12: {=INDEX('CPI Data'!F:F,MATCH(1,('CPI Data'!$A:$A=$A12)*('CPI Data'!$B:$B=$B12)*('CPI Data'!$C:$C=$C12),0))} -> 204 | F12: {=INDEX('CPI Data'!G:G,MATCH(1,('CPI Data'!$A:$A=$A12)*('CPI Data'!$B:$B=$B12)*('CPI Data'!$C:$C=$C12),0))} -> 172.8 | G12: {=INDEX('CPI Data'!H:H,MATCH(1,('CPI Data'!$A:$A=$A12)*('CPI Data'!$B:$B=$B12)*('CPI Data'!$C:$C=$C12),0))} -> 158.4 | H12: {=INDEX('CPI Data'!I:I,MATCH(1,('CPI Data'!$A:$A=$A12)*('CPI Data'!$B:$B=$B12)*('CPI Data'!$C:$C=$C12),0))} -> 188 | I12: {=INDEX('CPI Data'!J:J,MATCH(1,('CPI Data'!$A:$A=$A12)*('CPI Data'!$B:$B=$B12)*('CPI Data'!$C:$C=$C12),0))} -> 156.8 | J12: {=INDEX('CPI Data'!K:K,MATCH(1,('CPI Data'!$A:$A=$A12)*('CPI Data'!$B:$B=$B12)*('CPI Data'!$C:$C=$C12),0))} -> 162.2 | K12: {=INDEX('CPI Data'!L:L,MATCH(1,('CPI Data'!$A:$A=$A12)*('CPI Data'!$B:$B=$B12)*('CPI Data'!$C:$C=$C12),0))} -> 164.1 | L12: {=INDEX('CPI Data'!M:M,MATCH(1,('CPI Data'!$A:$A=$A12)*('CPI Data'!$B:$B=$B12)*('CPI Data'!$C:$C=$C12),0))} -> 119.7 | M12: {=INDEX('CPI Data'!N:N,MATCH(1,('CPI Data'!$A:$A=$A12)*('CPI Data'!$B:$B=$B12)*('CPI Data'!$C:$C=$C12),0))} -> 168.8 | N12: {=INDEX('CPI Data'!O:O,MATCH(1,('CPI Data'!$A:$A=$A12)*('CPI Data'!$B:$B=$B12)*('CPI Data'!$C:$C=$C12),0))} -> 162.7 | O12: {=INDEX('CPI Data'!P:P,MATCH(1,('CPI Data'!$A:$A=$A12)*('CPI Data'!$B:$B=$B12)*('CPI Data'!$C:$C=$C12),0))} -> 173.9 | P12: {=INDEX('CPI Data'!Q:Q,MATCH(1,('CPI Data'!$A:$A=$A12)*('CPI Data'!$B:$B=$B12)*('CPI Data'!$C:$C=$C12),0))} -> 164 | Q12: {=INDEX('CPI Data'!R:R,MATCH(1,('CPI Data'!$A:$A=$A12)*('CPI Data'!$B:$B=$B12)*('CPI Data'!$C:$C=$C12),0))} -> 192.1 | R12: {=INDEX('CPI Data'!S:S,MATCH(1,('CPI Data'!$A:$A=$A12)*('CPI Data'!$B:$B=$B12)*('CPI Data'!$C:$C=$C12),0))} -> 164.5 | S12: {=INDEX('CPI Data'!T:T,MATCH(1,('CPI Data'!$A:$A=$A12)*('CPI Data'!$B:$B=$B12)*('CPI Data'!$C:$C=$C12),0))} -> 155.3 | T12: {=INDEX('CPI Data'!U:U,MATCH(1,('CPI Data'!$A:$A=$A12)*('CPI Data'!$B:$B=$B12)*('CPI Data'!$C:$C=$C12),0))} -> 163.2 | U12: {=INDEX('CPI Data'!V:V,MATCH(1,('CPI Data'!$A:$A=$A12)*('CPI Data'!$B:$B=$B12)*('CPI Data'!$C:$C=$C12),0))} -> 162.1 | V12: {=INDEX('CPI Data'!W:W,MATCH(1,('CPI Data'!$A:$A=$A12)*('CPI Data'!$B:$B=$B12)*('CPI Data'!$C:$C=$C12),0))} -> 162.6 | W12: {=INDEX('CPI Data'!X:X,MATCH(1,('CPI Data'!$A:$A=$A12)*('CPI Data'!$B:$B=$B12)*('CPI Data'!$C:$C=$C12),0))} -> 157.5 | X12: {=INDEX('CPI Data'!Y:Y,MATCH(1,('CPI Data'!$A:$A=$A12)*('CPI Data'!$B:$B=$B12)*('CPI Data'!$C:$C=$C12),0))} -> 168.4 | Y12: {=INDEX('CPI Data'!Z:Z,MATCH(1,('CPI Data'!$A:$A=$A12)*('CPI Data'!$B:$B=$B12)*('CPI Data'!$C:$C=$C12),0))} -> 154 | Z12: {=INDEX('CPI Data'!AA:AA,MATCH(1,('CPI Data'!$A:$A=$A12)*('CPI Data'!$B:$B=$B12)*('CPI Data'!$C:$C=$C12),0))} -> 157.6 | AA12: {=INDEX('CPI Data'!AB:AB,MATCH(1,('CPI Data'!$A:$A=$A12)*('CPI Data'!$B:$B=$B12)*('CPI Data'!$C:$C=$C12),0))} -> 163.8 | AB12: {=INDEX('CPI Data'!AC:AC,MATCH(1,('CPI Data'!$A:$A=$A12)*('CPI Data'!$B:$B=$B12)*('CPI Data'!$C:$C=$C12),0))} -> 160 | AC12: {=INDEX('CPI Data'!AD:AD,MATCH(1,('CPI Data'!$A:$A=$A12)*('CPI Data'!$B:$B=$B12)*('CPI Data'!$C:$C=$C12),0))} -> 160 | AD12: {=INDEX('CPI Data'!AE:AE,MATCH(1,('CPI Data'!$A:$A=$A12)*('CPI Data'!$B:$B=$B12)*('CPI Data'!$C:$C=$C12),0))} -> 163.2 | AE12: =SUMIFS('Crude Oil '!$D:$D,'Crude Oil '!$B:$B,'5. Correlation '!B12,'Crude Oil '!$C:$C,'5. Correlation '!C12) -> 80983
A13: Rural+Urban | B13: 2021 | C13: September | D13: {=INDEX('CPI Data'!E:E,MATCH(1,('CPI Data'!$A:$A=$A13)*('CPI Data'!$B:$B=$B13)*('CPI Data'!$C:$C=$C13),0))} -> 146.6 | E13: {=INDEX('CPI Data'!F:F,MATCH(1,('CPI Data'!$A:$A=$A13)*('CPI Data'!$B:$B=$B13)*('CPI Data'!$C:$C=$C13),0))} -> 204 | F13: {=INDEX('CPI Data'!G:G,MATCH(1,('CPI Data'!$A:$A=$A13)*('CPI Data'!$B:$B=$B13)*('CPI Data'!$C:$C=$C13),0))} -> 172.8 | G13: {=INDEX('CPI Data'!H:H,MATCH(1,('CPI Data'!$A:$A=$A13)*('CPI Data'!$B:$B=$B13)*('CPI Data'!$C:$C=$C13),0))} -> 158.4 | H13: {=INDEX('CPI Data'!I:I,MATCH(1,('CPI Data'!$A:$A=$A13)*('CPI Data'!$B:$B=$B13)*('CPI Data'!$C:$C=$C13),0))} -> 188 | I13: {=INDEX('CPI Data'!J:J,MATCH(1,('CPI Data'!$A:$A=$A13)*('CPI Data'!$B:$B=$B13)*('CPI Data'!$C:$C=$C13),0))} -> 156.7 | J13: {=INDEX('CPI Data'!K:K,MATCH(1,('CPI Data'!$A:$A=$A13)*('CPI Data'!$B:$B=$B13)*('CPI Data'!$C:$C=$C13),0))} -> 162.3 | K13: {=INDEX('CPI Data'!L:L,MATCH(1,('CPI Data'!$A:$A=$A13)*('CPI Data'!$B:$B=$B13)*('CPI Data'!$C:$C=$C13),0))} -> 164.1 | L13: {=INDEX('CPI Data'!M:M,MATCH(1,('CPI Data'!$A:$A=$A13)*('CPI Data'!$B:$B=$B13)*('CPI Data'!$C:$C=$C13),0))} -> 119.7 | M13: {=INDEX('CPI Data'!N:N,MATCH(1,('CPI Data'!$A:$A=$A13)*('CPI Data'!$B:$B=$B13)*('CPI Data'!$C:$C=$C13),0))} -> 168.8 | N13: {=INDEX('CPI Data'!O:O,MATCH(1,('CPI Data'!$A:$A=$A13)*('CPI Data'!$B:$B=$B13)*('CPI Data'!$C:$C=$C13),0))} -> 162.7 | O13: {=INDEX('CPI Data'!P:P,MATCH(1,('CPI Data'!$A:$A=$A13)*('CPI Data'!$B:$B=$B13)*('CPI Data'!$C:$C=$C13),0))} -> 173.9 | P13: {=INDEX('CPI Data'!Q:Q,MATCH(1,('CPI Data'!$A:$A=$A13)*('CPI Data'!$B:$B=$B13)*('CPI Data'!$C:$C=$C13),0))} -> 164 | Q13: {=INDEX('CPI Data'!R:R,MATCH(1,('CPI Data'!$A:$A=$A13)*('CPI Data'!$B:$B=$B13)*('CPI Data'!$C:$C=$C13),0))} -> 192.1 | R13: {=INDEX('CPI Data'!S:S,MATCH(1,('CPI Data'!$A:$A=$A13)*('CPI Data'!$B:$B=$B13)*('CPI Data'!$C:$C=$C13),0))} -> 164.6 | S13: {=INDEX('CPI Data'!T:T,MATCH(1,('CPI Data'!$A:$A=$A13)*('CPI Data'!$B:$B=$B13)*('CPI Data'!$C:$C=$C13),0))} -> 155.3 | T13: {=INDEX('CPI Data'!U:U,MATCH(1,('CPI Data'!$A:$A=$A13)*('CPI Data'!$B:$B=$B13)*('CPI Data'!$C:$C=$C13),0))} -> 163.3 | U13: {=INDEX('CPI Data'!V:V,MATCH(1,('CPI Data'!$A:$A=$A13)*('CPI Data'!$B:$B=$B13)*('CPI Data'!$C:$C=$C13),0))} -> 162.1 | V13: {=INDEX('CPI Data'!W:W,MATCH(1,('CPI Data'!$A:$A=$A13)*('CPI Data'!$B:$B=$B13)*('CPI Data'!$C:$C=$C13),0))} -> 162.6 | W13: {=INDEX('CPI Data'!X:X,MATCH(1,('CPI Data'!$A:$A=$A13)*('CPI Data'!$B:$B=$B13)*('CPI Data'!$C:$C=$C13),0))} -> 157.5 | X13: {=INDEX('CPI Data'!Y:Y,MATCH(1,('CPI Data'!$A:$A=$A13)*('CPI Data'!$B:$B=$B13)*('CPI Data'!$C:$C=$C13),0))} -> 168.4 | Y13: {=INDEX('CPI Data'!Z:Z,MATCH(1,('CPI Data'!$A:$A=$A13)*('CPI Data'!$B:$B=$B13)*('CPI Data'!$C:$C=$C13),0))} -> 154 | Z13: {=INDEX('CPI Data'!AA:AA,MATCH(1,('CPI Data'!$A:$A=$A13)*('CPI Data'!$B:$B=$B13)*('CPI Data'!$C:$C=$C13),0))} -> 157.7 | AA13: {=INDEX('CPI Data'!AB:AB,MATCH(1,('CPI Data'!$A:$A=$A13)*('CPI Data'!$B:$B=$B13)*('CPI Data'!$C:$C=$C13),0))} -> 163.7 | AB13: {=INDEX('CPI Data'!AC:AC,MATCH(1,('CPI Data'!$A:$A=$A13)*('CPI Data'!$B:$B=$B13)*('CPI Data'!$C:$C=$C13),0))} -> 160 | AC13: {=INDEX('CPI Data'!AD:AD,MATCH(1,('CPI Data'!$A:$A=$A13)*('CPI Data'!$B:$B=$B13)*('CPI Data'!$C:$C=$C13),0))} -> 160 | AD13: {=INDEX('CPI Data'!AE:AE,MATCH(1,('CPI Data'!$A:$A=$A13)*('CPI Data'!$B:$B=$B13)*('CPI Data'!$C:$C=$C13),0))} -> 163.2 | AE13: =SUMIFS('Crude Oil '!$D:$D,'Crude Oil '!$B:$B,'5. Correlation '!B13,'Crude Oil '!$C:$C,'5. Correlation '!C13) -> 83035
A14: Rural+Urban | B14: 2021 | C14: October | D14: {=INDEX('CPI Data'!E:E,MATCH(1,('CPI Data'!$A:$A=$A14)*('CPI Data'!$B:$B=$B14)*('CPI Data'!$C:$C=$C14),0))} -> 147.4 | E14: {=INDEX('CPI Data'!F:F,MATCH(1,('CPI Data'!$A:$A=$A14)*('CPI Data'!$B:$B=$B14)*('CPI Data'!$C:$C=$C14),0))} -> 204.6 | F14: {=INDEX('CPI Data'!G:G,MATCH(1,('CPI Data'!$A:$A=$A14)*('CPI Data'!$B:$B=$B14)*('CPI Data'!$C:$C=$C14),0))} -> 171.2 | G14: {=INDEX('CPI Data'!H:H,MATCH(1,('CPI Data'!$A:$A=$A14)*('CPI Data'!$B:$B=$B14)*('CPI Data'!$C:$C=$C14),0))} -> 158.7 | H14: {=INDEX('CPI Data'!I:I,MATCH(1,('CPI Data'!$A:$A=$A14)*('CPI Data'!$B:$B=$B14)*('CPI Data'!$C:$C=$C14),0))} -> 190.6 | I14: {=INDEX('CPI Data'!J:J,MATCH(1,('CPI Data'!$A:$A=$A14)*('CPI Data'!$B:$B=$B14)*('CPI Data'!$C:$C=$C14),0))} -> 155.7 | J14: {=INDEX('CPI Data'!K:K,MATCH(1,('CPI Data'!$A:$A=$A14)*('CPI Data'!$B:$B=$B14)*('CPI Data'!$C:$C=$C14),0))} -> 185.3 | K14: {=INDEX('CPI Data'!L:L,MATCH(1,('CPI Data'!$A:$A=$A14)*('CPI Data'!$B:$B=$B14)*('CPI Data'!$C:$C=$C14),0))} -> 165.2 | L14: {=INDEX('CPI Data'!M:M,MATCH(1,('CPI Data'!$A:$A=$A14)*('CPI Data'!$B:$B=$B14)*('CPI Data'!$C:$C=$C14),0))} -> 121.9 | M14: {=INDEX('CPI Data'!N:N,MATCH(1,('CPI Data'!$A:$A=$A14)*('CPI Data'!$B:$B=$B14)*('CPI Data'!$C:$C=$C14),0))} -> 169.3 | N14: {=INDEX('CPI Data'!O:O,MATCH(1,('CPI Data'!$A:$A=$A14)*('CPI Data'!$B:$B=$B14)*('CPI Data'!$C:$C=$C14),0))} -> 163.2 | O14: {=INDEX('CPI Data'!P:P,MATCH(1,('CPI Data'!$A:$A=$A14)*('CPI Data'!$B:$B=$B14)*('CPI Data'!$C:$C=$C14),0))} -> 174.7 | P14: {=INDEX('CPI Data'!Q:Q,MATCH(1,('CPI Data'!$A:$A=$A14)*('CPI Data'!$B:$B=$B14)*('CPI Data'!$C:$C=$C14),0))} -> 167.7 | Q14: {=INDEX('CPI Data'!R:R,MATCH(1,('CPI Data'!$A:$A=$A14)*('CPI Data'!$B:$B=$B14)*('CPI Data'!$C:$C=$C14),0))} -> 192.7 | R14: {=INDEX('CPI Data'!S:S,MATCH(1,('CPI Data'!$A:$A=$A14)*('CPI Data'!$B:$B=$B14)*('CPI Data'!$C:$C=$C14),0))} -> 165.7 | S14: {=INDEX('CPI Data'!T:T,MATCH(1,('CPI Data'!$A:$A=$A14)*('CPI Data'!$B:$B=$B14)*('CPI Data'!$C:$C=$C14),0))} -> 156.3 | T14: {=INDEX('CPI Data'!U:U,MATCH(1,('CPI Data'!$A:$A=$A14)*('CPI Data'!$B:$B=$B14)*('CPI Data'!$C:$C=$C14),0))} -> 164.3 | U14: {=INDEX('CPI Data'!V:V,MATCH(1,('CPI Data'!$A:$A=$A14)*('CPI Data'!$B:$B=$B14)*('CPI Data'!$C:$C=$C14),0))} -> 163.6 | V14: {=INDEX('CPI Data'!W:W,MATCH(1,('CPI Data'!$A:$A=$A14)*('CPI Data'!$B:$B=$B14)*('CPI Data'!$C:$C=$C14),0))} -> 164.2 | W14: {=INDEX('CPI Data'!X:X,MATCH(1,('CPI Data'!$A:$A=$A14)*('CPI Data'!$B:$B=$B14)*('CPI Data'!$C:$C=$C14),0))} -> 158.4 | X14: {=INDEX('CPI Data'!Y:Y,MATCH(1,('CPI Data'!$A:$A=$A14)*('CPI Data'!$B:$B=$B14)*('CPI Data'!$C:$C=$C14),0))} -> 169.1 | Y14: {=INDEX('CPI Data'!Z:Z,MATCH(1,('CPI Data'!$A:$A=$A14)*('CPI Data'!$B:$B=$B14)*('CPI Data'!$C:$C=$C14),0))} -> 155.7 | Z14: {=INDEX('CPI Data'!AA:AA,MATCH(1,('CPI Data'!$A:$A=$A14)*('CPI Data'!$B:$B=$B14)*('CPI Data'!$C:$C=$C14),0))} -> 158.6 | AA14: {=INDEX('CPI Data'!AB:AB,MATCH(1,('CPI Data'!$A:$A=$A14)*('CPI Data'!$B:$B=$B14)*('CPI Data'!$C:$C=$C14),0))} -> 163.9 | AB14: {=INDEX('CPI Data'!AC:AC,MATCH(1,('CPI Data'!$A:$A=$A14)*('CPI Data'!$B:$B=$B14)*('CPI Data'!$C:$C=$C14),0))} -> 160.8 | AC14: {=INDEX('CPI Data'!AD:AD,MATCH(1,('CPI Data'!$A:$A=$A14)*('CPI Data'!$B:$B=$B14)*('CPI Data'!$C:$C=$C14),0))} -> 161 | AD14: {=INDEX('CPI Data'!AE:AE,MATCH(1,('CPI Data'!$A:$A=$A14)*('CPI Data'!$B:$B=$B14)*('CPI Data'!$C:$C=$C14),0))} -> 165.5 | AE14: =SUMIFS('Crude Oil '!$D:$D,'Crude Oil '!$B:$B,'5. Correlation '!B14,'Crude Oil '!$C:$C,'5. Correlation '!C14) -> 91472
A15: Rural+Urban | B15: 2021 | C15: November | D15: {=INDEX('CPI Data'!E:E,MATCH(1,('CPI Data'!$A:$A=$A15)*('CPI Data'!$B:$B=$B15)*('CPI Data'!$C:$C=$C15),0))} -> 148.2 | E15: {=INDEX('CPI Data'!F:F,MATCH(1,('CPI Data'!$A:$A=$A15)*('CPI Data'!$B:$B=$B15)*('CPI Data'!$C:$C=$C15),0))} -> 201.6 | F15: {=INDEX('CPI Data'!G:G,MATCH(1,('CPI Data'!$A:$A=$A15)*('CPI Data'!$B:$B=$B15)*('CPI Data'!$C:$C=$C15),0))} -> 173 | G15: {=INDEX('CPI Data'!H:H,MATCH(1,('CPI Data'!$A:$A=$A15)*('CPI Data'!$B:$B=$B15)*('CPI Data'!$C:$C=$C15),0))} -> 159.3 | H15: {=INDEX('CPI Data'!I:I,MATCH(1,('CPI Data'!$A:$A=$A15)*('CPI Data'!$B:$B=$B15)*('CPI Data'!$C:$C=$C15),0))} -> 190.1 | I15: {=INDEX('CPI Data'!J:J,MATCH(1,('CPI Data'!$A:$A=$A15)*('CPI Data'!$B:$B=$B15)*('CPI Data'!$C:$C=$C15),0))} -> 156.5 | J15: {=INDEX('CPI Data'!K:K,MATCH(1,('CPI Data'!$A:$A=$A15)*('CPI Data'!$B:$B=$B15)*('CPI Data'!$C:$C=$C15),0))} -> 199.2 | K15: {=INDEX('CPI Data'!L:L,MATCH(1,('CPI Data'!$A:$A=$A15)*('CPI Data'!$B:$B=$B15)*('CPI Data'!$C:$C=$C15),0))} -> 165.3 | L15: {=INDEX('CPI Data'!M:M,MATCH(1,('CPI Data'!$A:$A=$A15)*('CPI Data'!$B:$B=$B15)*('CPI Data'!$C:$C=$C15),0))} -> 122.4 | M15: {=INDEX('CPI Data'!N:N,MATCH(1,('CPI Data'!$A:$A=$A15)*('CPI Data'!$B:$B=$B15)*('CPI Data'!$C:$C=$C15),0))} -> 169.6 | N15: {=INDEX('CPI Data'!O:O,MATCH(1,('CPI Data'!$A:$A=$A15)*('CPI Data'!$B:$B=$B15)*('CPI Data'!$C:$C=$C15),0))} -> 163.7 | O15: {=INDEX('CPI Data'!P:P,MATCH(1,('CPI Data'!$A:$A=$A15)*('CPI Data'!$B:$B=$B15)*('CPI Data'!$C:$C=$C15),0))} -> 175.5 | P15: {=INDEX('CPI Data'!Q:Q,MATCH(1,('CPI Data'!$A:$A=$A15)*('CPI Data'!$B:$B=$B15)*('CPI Data'!$C:$C=$C15),0))} -> 169.7 | Q15: {=INDEX('CPI Data'!R:R,MATCH(1,('CPI Data'!$A:$A=$A15)*('CPI Data'!$B:$B=$B15)*('CPI Data'!$C:$C=$C15),0))} -> 192.9 | R15: {=INDEX('CPI Data'!S:S,MATCH(1,('CPI Data'!$A:$A=$A15)*('CPI Data'!$B:$B=$B15)*('CPI Data'!$C:$C=$C15),0))} -> 167.2 | S15: {=INDEX('CPI Data'!T:T,MATCH(1,('CPI Data'!$A:$A=$A15)*('CPI Data'!$B:$B=$B15)*('CPI Data'!$C:$C=$C15),0))} -> 157.4 | T15: {=INDEX('CPI Data'!U:U,MATCH(1,('CPI Data'!$A:$A=$A15)*('CPI Data'!$B:$B=$B15)*('CPI Data'!$C:$C=$C15),0))} -> 165.8 | U15: {=INDEX('CPI Data'!V:V,MATCH(1,('CPI Data'!$A:$A=$A15)*('CPI Data'!$B:$B=$B15)*('CPI Data'!$C:$C=$C15),0))} -> 164.2 | V15: {=INDEX('CPI Data'!W:W,MATCH(1,('CPI Data'!$A:$A=$A15)*('CPI Data'!$B:$B=$B15)*('CPI Data'!$C:$C=$C15),0))} -> 163.9 | W15: {=INDEX('CPI Data'!X:X,MATCH(1,('CPI Data'!$A:$A=$A15)*('CPI Data'!$B:$B=$B15)*('CPI Data'!$C:$C=$C15),0))} -> 159.3 | X15: {=INDEX('CPI Data'!Y:Y,MATCH(1,('CPI Data'!$A:$A=$A15)*('CPI Data'!$B:$B=$B15)*('CPI Data'!$C:$C=$C15),0))} -> 169.9 | Y15: {=INDEX('CPI Data'!Z:Z,MATCH(1,('CPI Data'!$A:$A=$A15)*('CPI Data'!$B:$B=$B15)*('CPI Data'!$C:$C=$C15),0))} -> 154.8 | Z15: {=INDEX('CPI Data'!AA:AA,MATCH(1,('CPI Data'!$A:$A=$A15)*('CPI Data'!$B:$B=$B15)*('CPI Data'!$C:$C=$C15),0))} -> 159.8 | AA15: {=INDEX('CPI Data'!AB:AB,MATCH(1,('CPI Data'!$A:$A=$A15)*('CPI Data'!$B:$B=$B15)*('CPI Data'!$C:$C=$C15),0))} -> 164.3 | AB15: {=INDEX('CPI Data'!AC:AC,MATCH(1,('CPI Data'!$A:$A=$A15)*('CPI Data'!$B:$B=$B15)*('CPI Data'!$C:$C=$C15),0))} -> 162.2 | AC15: {=INDEX('CPI Data'!AD:AD,MATCH(1,('CPI Data'!$A:$A=$A15)*('CPI Data'!$B:$B=$B15)*('CPI Data'!$C:$C=$C15),0))} -> 161.4 | AD15: {=INDEX('CPI Data'!AE:AE,MATCH(1,('CPI Data'!$A:$A=$A15)*('CPI Data'!$B:$B=$B15)*('CPI Data'!$C:$C=$C15),0))} -> 166.7 | AE15: =SUMIFS('Crude Oil '!$D:$D,'Crude Oil '!$B:$B,'5. Correlation '!B15,'Crude Oil '!$C:$C,'5. Correlation '!C15) -> 95105
A16: Rural+Urban | B16: 2021 | C16: December | D16: {=INDEX('CPI Data'!E:E,MATCH(1,('CPI Data'!$A:$A=$A16)*('CPI Data'!$B:$B=$B16)*('CPI Data'!$C:$C=$C16),0))} -> 148.7 | E16: {=INDEX('CPI Data'!F:F,MATCH(1,('CPI Data'!$A:$A=$A16)*('CPI Data'!$B:$B=$B16)*('CPI Data'!$C:$C=$C16),0))} -> 198.8 | F16: {=INDEX('CPI Data'!G:G,MATCH(1,('CPI Data'!$A:$A=$A16)*('CPI Data'!$B:$B=$B16)*('CPI Data'!$C:$C=$C16),0))} -> 177.9 | G16: {=INDEX('CPI Data'!H:H,MATCH(1,('CPI Data'!$A:$A=$A16)*('CPI Data'!$B:$B=$B16)*('CPI Data'!$C:$C=$C16),0))} -> 159.9 | H16: {=INDEX('CPI Data'!I:I,MATCH(1,('CPI Data'!$A:$A=$A16)*('CPI Data'!$B:$B=$B16)*('CPI Data'!$C:$C=$C16),0))} -> 187.6 | I16: {=INDEX('CPI Data'!J:J,MATCH(1,('CPI Data'!$A:$A=$A16)*('CPI Data'!$B:$B=$B16)*('CPI Data'!$C:$C=$C16),0))} -> 154.9 | J16: {=INDEX('CPI Data'!K:K,MATCH(1,('CPI Data'!$A:$A=$A16)*('CPI Data'!$B:$B=$B16)*('CPI Data'!$C:$C=$C16),0))} -> 188.3 | K16: {=INDEX('CPI Data'!L:L,MATCH(1,('CPI Data'!$A:$A=$A16)*('CPI Data'!$B:$B=$B16)*('CPI Data'!$C:$C=$C16),0))} -> 164.4 | L16: {=INDEX('CPI Data'!M:M,MATCH(1,('CPI Data'!$A:$A=$A16)*('CPI Data'!$B:$B=$B16)*('CPI Data'!$C:$C=$C16),0))} -> 121 | M16: {=INDEX('CPI Data'!N:N,MATCH(1,('CPI Data'!$A:$A=$A16)*('CPI Data'!$B:$B=$B16)*('CPI Data'!$C:$C=$C16),0))} -> 170.5 | N16: {=INDEX('CPI Data'!O:O,MATCH(1,('CPI Data'!$A:$A=$A16)*('CPI Data'!$B:$B=$B16)*('CPI Data'!$C:$C=$C16),0))} -> 164.2 | O16: {=INDEX('CPI Data'!P:P,MATCH(1,('CPI Data'!$A:$A=$A16)*('CPI Data'!$B:$B=$B16)*('CPI Data'!$C:$C=$C16),0))} -> 176.5 | P16: {=INDEX('CPI Data'!Q:Q,MATCH(1,('CPI Data'!$A:$A=$A16)*('CPI Data'!$B:$B=$B16)*('CPI Data'!$C:$C=$C16),0))} -> 168.2 | Q16: {=INDEX('CPI Data'!R:R,MATCH(1,('CPI Data'!$A:$A=$A16)*('CPI Data'!$B:$B=$B16)*('CPI Data'!$C:$C=$C16),0))} -> 192.4 | R16: {=INDEX('CPI Data'!S:S,MATCH(1,('CPI Data'!$A:$A=$A16)*('CPI Data'!$B:$B=$B16)*('CPI Data'!$C:$C=$C16),0))} -> 168.5 | S16: {=INDEX('CPI Data'!T:T,MATCH(1,('CPI Data'!$A:$A=$A16)*('CPI Data'!$B:$B=$B16)*('CPI Data'!$C:$C=$C16),0))} -> 158.7 | T16: {=INDEX('CPI Data'!U:U,MATCH(1,('CPI Data'!$A:$A=$A16)*('CPI Data'!$B:$B=$B16)*('CPI Data'!$C:$C=$C16),0))} -> 167 | U16: {=INDEX('CPI Data'!V:V,MATCH(1,('CPI Data'!$A:$A=$A16)*('CPI Data'!$B:$B=$B16)*('CPI Data'!$C:$C=$C16),0))} -> 163.4 | V16: {=INDEX('CPI Data'!W:W,MATCH(1,('CPI Data'!$A:$A=$A16)*('CPI Data'!$B:$B=$B16)*('CPI Data'!$C:$C=$C16),0))} -> 164.1 | W16: {=INDEX('CPI Data'!X:X,MATCH(1,('CPI Data'!$A:$A=$A16)*('CPI Data'!$B:$B=$B16)*('CPI Data'!$C:$C=$C16),0))} -> 160.2 | X16: {=INDEX('CPI Data'!Y:Y,MATCH(1,('CPI Data'!$A:$A=$A16)*('CPI Data'!$B:$B=$B16)*('CPI Data'!$C:$C=$C16),0))} -> 170.6 | Y16: {=INDEX('CPI Data'!Z:Z,MATCH(1,('CPI Data'!$A:$A=$A16)*('CPI Data'!$B:$B=$B16)*('CPI Data'!$C:$C=$C16),0))} -> 155.7 | Z16: {=INDEX('CPI Data'!AA:AA,MATCH(1,('CPI Data'!$A:$A=$A16)*('CPI Data'!$B:$B=$B16)*('CPI Data'!$C:$C=$C16),0))} -> 160.6 | AA16: {=INDEX('CPI Data'!AB:AB,MATCH(1,('CPI Data'!$A:$A=$A16)*('CPI Data'!$B:$B=$B16)*('CPI Data'!$C:$C=$C16),0))} -> 164.4 | AB16: {=INDEX('CPI Data'!AC:AC,MATCH(1,('CPI Data'!$A:$A=$A16)*('CPI Data'!$B:$B=$B16)*('CPI Data'!$C:$C=$C16),0))} -> 162.6 | AC16: {=INDEX('CPI Data'!AD:AD,MATCH(1,('CPI Data'!$A:$A=$A16)*('CPI Data'!$B:$B=$B16)*('CPI Data'!$C:$C=$C16),0))} -> 162 | AD16: {=INDEX('CPI Data'!AE:AE,MATCH(1,('CPI Data'!$A:$A=$A16)*('CPI Data'!$B:$B=$B16)*('CPI Data'!$C:$C=$C16),0))} -> 166.2 | AE16: =SUMIFS('Crude Oil '!$D:$D,'Crude Oil '!$B:$B,'5. Correlation '!B16,'Crude Oil '!$C:$C,'5. Correlation '!C16) -> 100381
... A33: Rural+Urban | B33: 2023 | C33: May | D33: {=INDEX('CPI Data'!E:E,MATCH(1,('CPI Data'!$A:$A=$A33)*('CPI Data'!$B:$B=$B33)*('CPI Data'!$C:$C=$C33),0))} -> 173.7 | E33: {=INDEX('CPI Data'!F:F,MATCH(1,('CPI Data'!$A:$A=$A33)*('CPI Data'!$B:$B=$B33)*('CPI Data'!$C:$C=$C33),0))} -> 214.3 | F33: {=INDEX('CPI Data'!G:G,MATCH(1,('CPI Data'!$A:$A=$A33)*('CPI Data'!$B:$B=$B33)*('CPI Data'!$C:$C=$C33),0))} -> 173.2 | G33: {=INDEX('CPI Data'!H:H,MATCH(1,('CPI Data'!$A:$A=$A33)*('CPI Data'!$B:$B=$B33)*('CPI Data'!$C:$C=$C33),0))} -> 179.5 | H33: {=INDEX('CPI Data'!I:I,MATCH(1,('CPI Data'!$A:$A=$A33)*('CPI Data'!$B:$B=$B33)*('CPI Data'!$C:$C=$C33),0))} -> 170 | I33: {=INDEX('CPI Data'!J:J,MATCH(1,('CPI Data'!$A:$A=$A33)*('CPI Data'!$B:$B=$B33)*('CPI Data'!$C:$C=$C33),0))} -> 172.2 | J33: {=INDEX('CPI Data'!K:K,MATCH(1,('CPI Data'!$A:$A=$A33)*('CPI Data'!$B:$B=$B33)*('CPI Data'!$C:$C=$C33),0))} -> 161 | K33: {=INDEX('CPI Data'!L:L,MATCH(1,('CPI Data'!$A:$A=$A33)*('CPI Data'!$B:$B=$B33)*('CPI Data'!$C:$C=$C33),0))} -> 175.6 | L33: {=INDEX('CPI Data'!M:M,MATCH(1,('CPI Data'!$A:$A=$A33)*('CPI Data'!$B:$B=$B33)*('CPI Data'!$C:$C=$C33),0))} -> 122.7 | M33: {=INDEX('CPI Data'!N:N,MATCH(1,('CPI Data'!$A:$A=$A33)*('CPI Data'!$B:$B=$B33)*('CPI Data'!$C:$C=$C33),0))} -> 218 | N33: {=INDEX('CPI Data'!O:O,MATCH(1,('CPI Data'!$A:$A=$A33)*('CPI Data'!$B:$B=$B33)*('CPI Data'!$C:$C=$C33),0))} -> 173.4 | O33: {=INDEX('CPI Data'!P:P,MATCH(1,('CPI Data'!$A:$A=$A33)*('CPI Data'!$B:$B=$B33)*('CPI Data'!$C:$C=$C33),0))} -> 194.2 | P33: {=INDEX('CPI Data'!Q:Q,MATCH(1,('CPI Data'!$A:$A=$A33)*('CPI Data'!$B:$B=$B33)*('CPI Data'!$C:$C=$C33),0))} -> 179.1 | Q33: {=INDEX('CPI Data'!R:R,MATCH(1,('CPI Data'!$A:$A=$A33)*('CPI Data'!$B:$B=$B33)*('CPI Data'!$C:$C=$C33),0))} -> 201 | R33: {=INDEX('CPI Data'!S:S,MATCH(1,('CPI Data'!$A:$A=$A33)*('CPI Data'!$B:$B=$B33)*('CPI Data'!$C:$C=$C33),0))} -> 187.3 | S33: {=INDEX('CPI Data'!T:T,MATCH(1,('CPI Data'!$A:$A=$A33)*('CPI Data'!$B:$B=$B33)*('CPI Data'!$C:$C=$C33),0))} -> 179.7 | T33: {=INDEX('CPI Data'!U:U,MATCH(1,('CPI Data'!$A:$A=$A33)*('CPI Data'!$B:$B=$B33)*('CPI Data'!$C:$C=$C33),0))} -> 186.2 | U33: {=INDEX('CPI Data'!V:V,MATCH(1,('CPI Data'!$A:$A=$A33)*('CPI Data'!$B:$B=$B33)*('CPI Data'!$C:$C=$C33),0))} -> 175.6 | V33: {=INDEX('CPI Data'!W:W,MATCH(1,('CPI Data'!$A:$A=$A33)*('CPI Data'!$B:$B=$B33)*('CPI Data'!$C:$C=$C33),0))} -> 182.8 | W33: {=INDEX('CPI Data'!X:X,MATCH(1,('CPI Data'!$A:$A=$A33)*('CPI Data'!$B:$B=$B33)*('CPI Data'!$C:$C=$C33),0))} -> 175.2 | X33: {=INDEX('CPI Data'!Y:Y,MATCH(1,('CPI Data'!$A:$A=$A33)*('CPI Data'!$B:$B=$B33)*('CPI Data'!$C:$C=$C33),0))} -> 185.7 | Y33: {=INDEX('CPI Data'!Z:Z,MATCH(1,('CPI Data'!$A:$A=$A33)*('CPI Data'!$B:$B=$B33)*('CPI Data'!$C:$C=$C33),0))} -> 164.8 | Z33: {=INDEX('CPI Data'!AA:AA,MATCH(1,('CPI Data'!$A:$A=$A33)*('CPI Data'!$B:$B=$B33)*('CPI Data'!$C:$C=$C33),0))} -> 171.2 | AA33: {=INDEX('CPI Data'!AB:AB,MATCH(1,('CPI Data'!$A:$A=$A33)*('CPI Data'!$B:$B=$B33)*('CPI Data'!$C:$C=$C33),0))} -> 177.1 | AB33: {=INDEX('CPI Data'!AC:AC,MATCH(1,('CPI Data'!$A:$A=$A33)*('CPI Data'!$B:$B=$B33)*('CPI Data'!$C:$C=$C33),0))} -> 185.2 | AC33: {=INDEX('CPI Data'!AD:AD,MATCH(1,('CPI Data'!$A:$A=$A33)*('CPI Data'!$B:$B=$B33)*('CPI Data'!$C:$C=$C33),0))} -> 175.7 | AD33: {=INDEX('CPI Data'!AE:AE,MATCH(1,('CPI Data'!$A:$A=$A33)*('CPI Data'!$B:$B=$B33)*('CPI Data'!$C:$C=$C33),0))} -> 179.1 | AE33: =SUMIFS('Crude Oil '!$D:$D,'Crude Oil '!$B:$B,'5. Correlation '!B33,'Crude Oil '!$C:$C,'5. Correlation '!C33) -> 103487
C34: Correlation | D34: =CORREL($AE$5:$AE$33,D5:D33) -> 0.43987242 | E34: =CORREL($AE$5:$AE$33,E5:E33) -> 0.79268233 | F34: =CORREL($AE$5:$AE$33,F5:F33) -> -0.083051312 | G34: =CORREL($AE$5:$AE$33,G5:G33) -> 0.52771474 | H34: =CORREL($AE$5:$AE$33,H5:H33) -> 0.75142784 | I34: =CORREL($AE$5:$AE$33,I5:I33) -> 0.52538929 | J34: =CORREL($AE$5:$AE$33,J5:J33) -> 0.32872193 | K34: =CORREL($AE$5:$AE$33,K5:K33) -> 0.3224881 | ... AD34: =CORREL($AE$5:$AE$33,AD5:AD33) -> 0.6951715
B37: CPI Categories | C37: Correlation with Crude Oil (2021-2023)
B38: Meat and fish | C38: 0.79268233
B39: Transport and communication | C39: 0.77857896
B40: Oils and fats | C40: 0.75142784
B41: Recreation and amusement | C41: 0.7240359
B42: Fuel and light | C42: 0.71027263
B43: Food and beverages | C43: 0.70967042
B44: General index | C44: 0.6951715
B45: Footwear | C45: 0.69238547
B46: Non-alcoholic beverages | C46: 0.67563293
B47: Miscellaneous | C47: 0.67548272
B48: Clothing and footwear | C48: 0.67152083
B49: Clothing | C49: 0.66726282
... B64: Egg | C64: -0.083051312
B67: Interpretation & Insights
B68: Fuel-linked categories like Meal & Fish, Transport & Communication, Oils & Fats show the strongest correlation with crude oil prices, meaning inflation in these sectors is directly oil-driven.
B69: General CPI(69.5%) has a moderate correlation with oil, indicating crude oil significantly influences overall inflation in India.
B70: Essential food items like Pulses, Vegetables, Eggs show weak or negative correlation, suggesting they are driven more by domestic supply conditions than global oil prices.
B71: High-income & lifestyle-based categories (recreation, beverages, luxury) also reflect oil price fluctuations due to cost-push inflation.

Sheet Data Validation
B2: Sectors | C2: Year | D2: Month
B3: Rural | C3: 2013 | D3: January
B4: Urban | C4: 2014 | D4: February
B5: Rural+Urban | C5: 2015 | D5: March
C6: 2016 | D6: April
C7: 2017 | D7: May
C8: 2018 | D8: June
C9: 2019 | D9: July
C10: 2020 | D10: August
C11: 2021 | D11: September
C12: 2022 | D12: October
C13: 2023 | D13: November
C14: 2023 | D14: December

Sheet Crude Oil 
B2: Year | C2: Month | D2: Crude Olil
B3: 2021 | C3: January | D3: 66695
B4: 2021 | C4: February | D4: 60966
B5: 2021 | C5: March | D5: 75471
B6: 2021 | C6: April | D6: 74208
B7: 2021 | C7: May | D7: 70046
B8: 2021 | C8: June | D8: 71679
B9: 2021 | C9: July | D9: 72860
B10: 2021 | C10: August | D10: 80983
B11: 2021 | C11: September | D11: 83035
B12: 2021 | C12: October | D12: 91472
B13: 2021 | C13: November | D13: 95105
B14: 2021 | C14: December | D14: 100381
... B31: 2023 | C31: May | D31: 103487

Sheet Notes
D2: Data Summary
D3: Rows | K3: 372
D4: Columns | K4: 30
D5: Sectors | K5: Rural, Urban, Rural+Urban
D6: Blank Values | K6: 243
D7: Time Line | K7: 2013 – 2023
D9: Calculation for Problem Statement an Formulas
D10: 1. Broader Category Contribution Analysis | K10: Contribution = ((CPI index of Category) / TOTAL CPI Value) * 100
D11: 2. YOY Increase In Overall CPI For Rural + Urban | K11: YOY Inflation = ((Current Year – Previous Year) / Previous Year) * 100
D12: 3. Month Over Month Inflation Over Food Categories | K12: MOM Inflation = ((Current Month – Previous Month) / Previous Month) * 100
D13: 4. Category Wise Inflation Over COVID Periods | K13: Periodic Inflation = ((End Of Year – Start Of Year) / Start Of Year) * 100
D14: 5. Impact of Crude Oil With All Categories And Correlation | K14: Correl Function Between Crude Oil Array and The Category Array
D16: List Of Formulas Used For Project
D17: Index Match (Nested)
D18: Averageifs
D19: Sum
D20: Hlookup
D21: Correl
D23: Data Cleaning Steps
D24: Identification of columns having null values using countif and sum function
D25: Replacing the null values using moving average
D27: Extras
D28: Crude Oil Data Exported from PPAC Website
D29: Data Validation for Selection of Sectors
